Workbook
Name StrMod: '角色卡'!$J$15
Name WisMod: '角色卡'!$J$19
Name Cha: '角色卡'!$G$20
Name Str: '角色卡'!$G$15
Name DexMod: '角色卡'!$J$16
Name Int: '角色卡'!$G$18
Name tweight: '裝備與物品'!$AB$34
Name Con: '角色卡'!$G$17
Name Dex: '角色卡'!$G$16
Name AC: '角色卡'!$AN$27
Name Lvl: '角色卡'!$Q$7
Name Wis: '角色卡'!$G$19
Name Prof: '角色卡'!$C$47
Name Lvsum: #REF!
Name tweight: #REF!
Name ConMod: '角色卡'!$J$17
Name ChaMod: '角色卡'!$J$20
Name IntMod: '角色卡'!$J$18

Sheet 請先閱讀
Q1: 更新LOG | R1: 45562 | S1: 1.0 | T1: 角色卡完成 | V1: 45994 | W1: 3.0d | X1: 。加入資源《艾伯倫：奇械師的鍛造爐》堡壘設施
B2: 。前言。 | K2: 身高換算 | R2: 45564 | S2: 1.1 | T2: 。新增更新Log、英雄激勵、護甲選項自動化 。調整了先攻加值的位置 。移除了角色關係，改為陣營及能力值特質 | V2: 45996 | W2: 3.0.1 | X2: 。修正了奇械師未顯示生命骰的問題 。修正了年齡欄位會出現體重單位的問題 。修正了奇械師無法出現在法術表來源的問題
L3: 公分 | M3: =ROUNDDOWN(K3/(2.54*12),0) -> 0 | N3: 呎 | R3: 45568 | S3: 1.2 | T3: 。新增金錢紀錄表、施法等級、召喚物先攻 。法術書比照職業能力選項摺疊 | V3: 45998 | W3: 3.1 | X3: 。增加組織聲望(費倫派系跟艾伯倫家族都會用到對吧？)
B4: 本角卡構築在多位前人的努力上，旨在為喜愛D&D的玩家提供便利且較容易的入門手段， | M4: =ROUND((K3-M3*2.54*12)/2.54,1) -> 0 | N4: 吋 | R4: 45570 | S4: 1.3 | T4: 。載重移動到裝備與物品，並加入拖/抬/推上限 。現在開始購點出現範圍外的數字會出現error 。角色簡卡新增英雄激勵、移除速查表 | V4: 46000 | W4: 3.1.1 | X4: 。我居然現在才發現專長沒有重甲大師？？
B5: ！本角卡僅做為一個便利工具，不提供在任何形式上進行宣傳或營利手段！ | L5: 呎 | M5: =ROUND((K5*12+K6)*2.54,1) -> 0 | N5: 公分 | R5: 45576 | S5: 1.4 | T5: 。新增身高體重換算機 。移除了不存在的"變體"購點規則 。各種版面調整 | V5: 46024 | W5: 3.2 | X5: 。加入資源《銃士職業：瓦爾達的秘密尖塔》
B6: 在此感謝前人製作的角色卡 是你們給予了我啟發與動力，我玩得很開心，也才有了今天的魔改版 本角色卡翻譯僅供參考，如有歧異一切內容請以原書 D&D 2024 原文書內容為準。 P.S.隱藏工作表中有許多可供複製的內容或列表，還請多加利用 P.S.S.本角色卡並未包含2024 PHB以前的其他5e資源，請謹慎選用 P.S.S.S.本角色卡使用部分AI資源，敬請見諒 | L6: 吋 | R6: 45577 | S6: 1.4.1 | T6: 。修正了guard的譯名跟技能熟練錯誤 | V6: 46026 | W6: 3.3 | X6: 。加入資源《瓦爾達的秘密尖塔：玩家資料包》
K7: 體重換算 | R7: 45581 | S7: 1.4.2 | T7: 。修正了熾炎斬文本錯誤 。修正了負重公式錯誤的問題 | V7: 46027 | W7: 3.4a | X7: 。加入資源《鬼魅幽谷：玩家指南》職業與子職業
L8: 公斤 | M8: =ROUND(K8*2.20462262,1) -> 0 | N8: 磅 | R8: 45590 | S8: 1.4.3 | T8: 。修正了神奇的金錢紀錄bug | V8: 46028 | W8: 3.4b | X8: 。加入資源《鬼魅幽谷：玩家指南》背景&專長
R9: 45619 | S9: 1.5 | T9: 。新增堡壘頁面 | V9: 46029 | W9: 3.4c | X9: 。加入資源《鬼魅幽谷：玩家指南》法術及召喚物
L10: 磅 | M10: =ROUND(K10*0.45359237,1) -> 0 | N10: 公斤 | R10: 45627 | S10: 1.5.1 | T10: 。新增DMG自定義背景選項(這東西真的有用嗎...) | V10: 46030 | W10: 3.4d | X10: 。加入資源《鬼魅幽谷：玩家指南》種族
R11: 45637 | S11: 1.6 | T11: 。新增職業語言熟練自動化 。新增工具熟練項 。新增德魯伊：原初誓約-術師技能加值自動化 。調整魔法物品排版 。修正了裝備AC值可以跟無甲及法甲相疊的情況 。修正了造水術/枯水術的法術導航錯誤 | V11: 46031 | W11: 3.4e | X11: 。加入資源《鬼魅幽谷：玩家指南》型態轉變(在隱藏列)
R12: 45677 | S12: 1.6.1 | T12: 。修正了獸王天空野獸會是中型的問題 。修正了次元袋會記入本身重量的問題 | V12: 46032 | W12: 3.4 | X12: 。加入資源《鬼魅幽谷：玩家指南》進階武器
B13: 購點計算機 | K13: 購點表 | R13: 45726 | S13: 1.7 | T13: 。新增尋獲魔寵的部分野獸及契術師鎖鏈魔契魔寵 。新憎現代及未來武器 。又調了一次魔法物品的排版 。修正了野獸知覺、動植物定位術及舞光術的資料錯誤 | V13: 46034 | W13: 3.4.1 | X13: 。調整血量計算，整合額外生命
B14: 屬性 | C14: 屬性值 | D14: 背景加值 | E14: 專長加值 | F14: = | G14: 加總 | H14: 調整值 | I14: 花費點數 | K14: 屬性值 | M14: 花費點數 | R14: 45732 | S14: 1.7.1 | T14: 。修正了三叉戟的傷害 。修正了部分法術的錯誤 。調整部分中文翻譯 | V14: 46038 | W14: 3.4.2 | X14: 。終於想起來要補GH野蠻人原初精魂的數據了
B15: 力量 | C15: 10 | F15: = | G15: =SUM(C15:E15) -> 10 | H15: =ROUNDDOWN(G15/2,0)-5 -> 0 | I15: =IFNA(IF(OR(C15="",AND(C15<16,C15>7)),VLOOKUP(C15,$K$15:$M$22,3,FALSE),"ERROR"),"") -> 2 | K15: 8 | M15: 0 | R15: 45742 | S15: 1.7.2 | T15: 。為專長補上了英文原文 | V15: 46039 | W15: 3.5 | X15: 。加入資源《歪曲之月》 。加入資源《一發團奇觀：節慶冒險包》種族 。加入資源《火炬光下的克蘇魯》
B16: 敏捷 | C16: 12 | F16: = | G16: =SUM(C16:E16) -> 12 | H16: =ROUNDDOWN(G16/2,0)-5 -> 1 | I16: =IFNA(IF(OR(C16="",AND(C16<16,C16>7)),VLOOKUP(C16,$K$15:$M$22,3,FALSE),"ERROR"),"") -> 4 | K16: 9 | M16: 1 | R16: 45745 | S16: 1.7.3 | T16: 。種族統一改成物種了(DEI哈哈) 。修正了野蠻人3級缺少的原初知識特性 。調整部分中文翻譯 。法術列表的來源會追蹤你的物種了 | V16: 46051 | W16: 3.5.1 | X16: 。把法術DC/豁免位置替換成數值計算 。豁免列加入優劣勾選欄 。生命骰加入剩餘欄
B17: 體魄 | C17: 12 | F17: = | G17: =SUM(C17:E17) -> 12 | H17: =ROUNDDOWN(G17/2,0)-5 -> 1 | I17: =IFNA(IF(OR(C17="",AND(C17<16,C17>7)),VLOOKUP(C17,$K$15:$M$22,3,FALSE),"ERROR"),"") -> 4 | K17: 10 | M17: 2 | R17: 45753 | S17: 1.7.4 | T17: 。修正了異界坐騎的屬性值 。補上了尋獲坐騎缺少的數據 | V17: 46058 | W17: 3.6 | X17: 。加入資源《拳鬥士職業》
B18: 智力 | C18: 15 | F18: = | G18: =SUM(C18:E18) -> 15 | H18: =ROUNDDOWN(G18/2,0)-5 -> 2 | I18: =IFNA(IF(OR(C18="",AND(C18<16,C18>7)),VLOOKUP(C18,$K$15:$M$22,3,FALSE),"ERROR"),"") -> 9 | K18: 11 | M18: 3 | R18: 45754 | S18: 1.8 | T18: 。新增準備法術數量 。新增玩家手冊可購買的坐騎 | V18: 46070 | W18: 3.7 | X18: 。加入資源《探索艾伯倫》 。修復了調整豁免列所產生的一系列bug
B19: 感知 | C19: 12 | F19: = | G19: =SUM(C19:E19) -> 12 | H19: =ROUNDDOWN(G19/2,0)-5 -> 1 | I19: =IFNA(IF(OR(C19="",AND(C19<16,C19>7)),VLOOKUP(C19,$K$15:$M$22,3,FALSE),"ERROR"),"") -> 4 | K19: 12 | M19: 4 | R19: 45764 | S19: 1.8.1 | T19: 。同日dndbeyond公布第一次勘誤表，同勘誤表修改法術描述，勘誤表連結如下： https://www.dndbeyond.com/changelog#2024CoreRulesErrata | V19: 46102 | W19: 3.7.1 | X19: 。補上德魯伊缺少的施法能力 。補上奇械師子職業缺少的召喚物資料
B20: 魅力 | C20: 12 | F20: = | G20: =SUM(C20:E20) -> 12 | H20: =ROUNDDOWN(G20/2,0)-5 -> 1 | I20: =IFNA(IF(OR(C20="",AND(C20<16,C20>7)),VLOOKUP(C20,$K$15:$M$22,3,FALSE),"ERROR"),"") -> 4 | K20: 13 | M20: 5 | R20: 45788 | S20: 1.8.2 | T20: 。修正了術士7級沒有獲得術法化身能力的問題 。補上困惑術少掉的文本內容 | V20: 46133 | W20: 3.7.2 | X20: 。調整一些文本 。重新修正了德魯伊原初誓約及牧師神聖誓約的特性 。準備更新一些東西
D21: 總花費點數 | E21: =SUM(I15:I20) -> 27 | F21: / | G21: 27 | K21: 14 | M21: 7 | R21: 45794 | S21: 1.9 | T21: 。增加血脈選項自動化 。工具熟練、種族能力、專長及筆記各增加了一列 。調整部分物種及能力翻譯 。調整專長的順序 。調整生命值的排版 | V21: 46137 | W21: 3.8 | X21: 。加入資源《獅鷲的鞍袋 (一)》 。修正了遊俠子職業能力等級顯示錯誤的問題
B22: 元角色卡作者:Nicola 優化版角色卡作者:杯麵 部分修訂格式及優化來源:犬良、玉米 | H22: 角色卡作者：雷它 協作者：Klassified | K22: 15 | M22: 9 | R22: 45803 | S22: 1.10 | T22: 。法術環區重做 。裝備與物品重做 。調整角色簡卡排版 | V22: 46151 | W22: 3.9 | X22: 。新增DnD Beyond Drop 內容 (DDBD) 。加入資源《德羅林博士的恐龍寶典》物種、遊俠子職 。加回背景選項的書目(什麼時候消失的都不知道) 。調整了《艾伯倫：奇械師鍛爐》的專長位置 。修改了一些翻譯
R23: 45812 | S23: 1.10.1 | T23: 。新增牧師：神聖職責-奇術使技能加值自動化 。補上疫病射線少掉的文本內容
L24: 角色卡版本:3.9 | R24: 45815 | S24: 1.10.2 | T24: 。修正了德魯伊原初誓約及牧師神聖誓約的特性
A25: ⭣選擇書目 | R25: 45843 | S25: 1.11 | T25: 。調整了坐騎/召喚物的排版 。修正了解離術的環位 。移除了法術書的某些東西(會回來的，大概)
R26: 45859 | S26: 1.11.1 | T26: 。更新了手動的坐騎/召喚物卡 。補上了立繪的圖像比例
B27: 核心 資源 | C27: 玩家手冊(2024) | E27: PHB | H27: 合作 資源 | I27: 歪曲之月 | M27: TCM | O27: FALSE | R27: 45926 | S27: 1.11.2 | T27: 。修正了逸聞學院跟迷惑學院的文本錯誤
C28: 地下城主指南(2024) | E28: DMG | I28: 瓦爾達的秘密尖塔 | M28: VSS:PP | O28: FALSE | R28: 45961 | S28: 2.0 | T28: 。加入資源《被遺忘的國度：費倫的英雄們》 。加入書目選擇(核心資源無法取消，肯定的吧？)
C29: 怪物圖鑑(2025) | E29: MM | I29: 銃士職業：瓦爾達的秘密尖塔 | M29: GC:VSS | O29: FALSE | R29: 45970 | S29: 2.01 | T29: 。補上了一些缺漏的專長 。修改了一些翻譯
I30: 火炬光下的克蘇魯 | M30: CbT | O30: FALSE | R30: 45971 | S30: 2.1 | T30: 。將堡壘更名為據點。 。加入資源《被遺忘的國度：費倫的英雄們》據點設施。
B31: 官方 資源 | C31: 被遺忘的國度：費倫的英雄們 | E31: FPHF | F31: TRUE | I31: 鬼魅幽谷 | M31: GH | O31: FALSE | R31: 45977 | S31: 2.2 | T31: 。加入資源《阿斯代倫的飢渴之書》
C32: 洛溫：第一曙光 | E32: LFL | F32: TRUE | I32: 一發團奇觀：節慶冒險包 | M32: OSW:HAP | O32: FALSE | R32: 45980 | S32: 2.3 | T32: 。加入資源《洛溫：第一曙光》的背景與專長
C33: 阿斯代倫的飢渴之書 | E33: ABH | F33: TRUE | I33: 探索艾伯倫 | M33: EE | O33: FALSE | R33: 45987 | S33: 3.0a | T33: 。加入資源《艾伯倫：奇械師鍛爐》奇械師職業、子職業能力
C34: 艾伯倫：奇械師鍛爐 | E34: EFA | F34: TRUE | I34: 拳鬥士職業 | M34: PC | O34: FALSE | R34: 45988 | S34: 3.0b | T34: 。加入資源《艾伯倫：奇械師鍛爐》法術
I35: 獅鷲的鞍袋 (一) | M35: TGS1 | O35: FALSE | R35: 45991 | S35: 3.0c | T35: 。加入資源《艾伯倫：奇械師鍛爐》種族、背景、專長、職業能力選項 。新增角色卡生物類型欄位 。修正了兼職子職業顯示錯誤的問題
B36: DnD Beyond Drop (DDBD) | E36: 46150 | F36: FALSE | I36: 德羅林博士的恐龍寶典 (施工中) | M36: DDDD | O36: FALSE

Sheet 角色簡卡
A1: 角色簡卡
B2: 戴夫林 | J2: ='角色卡'!P7 -> 阿不 | N2: ='角色卡'!Y7 -> 人類 Human | V2: ='角色卡'!AZ7 | AA2: ='角色卡'!AY9 -> 學者 Sage | AF2: ='角色卡'!C9 -> 中型or小型 | AI2: ='角色卡'!AT9
AL3: 法術環位
B4: 角色名稱 | J4: 玩家 | N4: 物種 | V4: 所屬陣營 | AA4: 人物背景 | AF4: 體型 | AI4: 性別 | AL4: 一環 | AN4: ='法術表'!G7 -> FALSE | AO4: ='法術表'!H7 -> FALSE | AP4: ='法術表'!I7 -> FALSE | AQ4: ='法術表'!J7 -> FALSE
F6: 屬性 | I6: 豁免 | K6: ='角色卡'!V27 | L6: 血量 | P6: 先攻 | S6: 護甲值 | W6: 法術豁免\攻擊 | AC6: 法術豁免\攻擊 | AI6: 等級 | AL6: 二環 | AN6: ='法術表'!G8 -> FALSE | AO6: ='法術表'!H8 -> FALSE | AP6: ='法術表'!I8 -> FALSE
B7: 力量 | D7: ='角色卡'!G15 -> 10 | F7: ='角色卡'!J15 -> 0 | H7: ='角色卡'!P15 | I7: ='角色卡'!W15 -> 0 | L7: ='角色卡'!AA27 -> 17 | P7: ='角色卡'!AF27 -> 0 | S7: ='角色卡'!AN27 -> 12 | W7: ='角色卡'!CC33 -> 13 / +5 / +3 | AC7: ='角色卡'!CC34 | AI7: ='角色卡'!CA3 -> 3
B8: 敏捷 | D8: ='角色卡'!G16 -> 12 | F8: ='角色卡'!J16 -> 1 | H8: ='角色卡'!P16 | I8: ='角色卡'!W16 -> 1 | AL8: 三環 | AN8: ='法術表'!G9 -> FALSE | AO8: ='法術表'!H9 -> FALSE | AP8: ='法術表'!I9 -> FALSE
B9: 體魄 | D9: ='角色卡'!G17 -> 12 | F9: ='角色卡'!J17 -> 1 | H9: ='角色卡'!P17 | I9: ='角色卡'!W17 -> 1 | L9: 運動 | P9: ='角色卡'!C27 -> 0 | R9: 馴服動物 | V9: ='角色卡'!C36 -> 1 | Y9: 人設立繪
B10: 智力 | D10: ='角色卡'!G18 -> 17 | F10: ='角色卡'!J18 -> 3 | H10: ='角色卡'!P18 | I10: ='角色卡'!W18 -> 5 | L10: 特技動作 | P10: ='角色卡'!C28 -> 1 | R10: 察言觀色 | V10: ='角色卡'!C37 -> 1 | Y10: ='角色卡'!BV7 | AL10: 四環 | AN10: ='法術表'!G10 -> FALSE | AO10: ='法術表'!H10 -> FALSE | AP10: ='法術表'!I10 -> FALSE
B11: 感知 | D11: ='角色卡'!G19 -> 13 | F11: ='角色卡'!J19 -> 1 | H11: ='角色卡'!P19 | I11: ='角色卡'!W19 -> 3 | L11: 巧手 | P11: ='角色卡'!C29 -> 1 | R11: 醫藥 | V11: ='角色卡'!C38 -> 1
B12: 魅力 | D12: ='角色卡'!G20 -> 12 | F12: ='角色卡'!J20 -> 1 | H12: ='角色卡'!P20 | I12: ='角色卡'!W20 -> 1 | L12: 隱匿 | P12: ='角色卡'!C30 -> 1 | R12: 察覺 | V12: ='角色卡'!C39 -> 3 | AL12: 五環 | AN12: ='法術表'!G11 -> FALSE | AO12: ='法術表'!H11 -> FALSE | AP12: ='法術表'!I11 -> FALSE
L13: 奧秘 | P13: ='角色卡'!C31 -> 7 | R13: 求生 | V13: ='角色卡'!C40 -> 1
B14: ='角色卡'!C46 -> 13 | D14: 被動察覺 | L14: 歷史 | P14: ='角色卡'!C32 -> 5 | R14: 欺瞞 | V14: ='角色卡'!C41 -> 1 | AL14: 六環 | AN14: ='法術表'!L7 -> FALSE | AO14: ='法術表'!M7 -> FALSE
B15: ='角色卡'!C47 -> 2 | D15: 熟練加值 | L15: 調查 | P15: ='角色卡'!C33 -> 3 | R15: 威嚇 | V15: ='角色卡'!C42 -> 1
L16: 自然 | P16: ='角色卡'!C34 -> 3 | R16: 表演 | V16: ='角色卡'!C43 -> 1 | AL16: 七環 | AN16: ='法術表'!L8 -> FALSE | AO16: ='法術表'!M8 -> FALSE
B17: 職業 | L17: 宗教 | P17: ='角色卡'!C35 -> 3 | R17: 說服 | V17: ='角色卡'!C44 -> 3
A18: Ⅰ | B18: ='角色卡'!AB16 -> 法師-Wizard | G18: ='角色卡'!AK57 -> 劍詠師 | AL18: 八環 | AN18: ='法術表'!L9 -> FALSE
A19: Ⅱ | B19: ='角色卡'!AB17 | G19: ='角色卡'!BH57 | L19: 速度 | N19: 游泳 | P19: 飛行 | R19: 攀爬 | U19: 激勵
A20: Ⅲ | B20: ='角色卡'!AB18 | G20: ='角色卡'!CE57 | L20: ='角色卡'!AY18 -> 40 | N20: ='角色卡'!BB18 -> 0 | P20: ='角色卡'!AY20 -> 0 | R20: ='角色卡'!BB20 -> 0 | U20: ='角色卡'!AN30 -> FALSE | AL20: 九環 | AN20: ='法術表'!L10 -> FALSE
B21: ='裝備與物品'!AG32 -> 負重上限=150磅 現在負重=0磅 拖/抬/推上限=300磅 | AP21: ='法術表'!D12 -> 3 | AQ21: ='法術表'!D13 -> 0
AL22: 契術師環位
L23: 金幣 | P23: 銀幣 | T23: 銅幣 | AL23: ='法術表'!H13 -> 一環 | AN23: ='法術表'!J13 -> FALSE | AO23: ='法術表'!K13 -> FALSE | AP23: ='法術表'!L13 -> FALSE | AQ23: ='法術表'!M13 -> FALSE
L24: ='裝備與物品'!AG6 -> 490 | P24: ='裝備與物品'!AK6 -> 0 | T24: ='裝備與物品'!AO6 -> 0
A25: special for DM

Sheet 角色卡
CA2: 等級
CA3: =AL20 -> 3
B6: 人物設定 | BV6: 人設立繪
C7: 戴夫林 | P7: 阿不 | Y7: 人類 Human
C8: 角色名稱 | P8: 玩家名稱 | AE8: 物種 | AJ8: =IFNA(VLOOKUP(Y7,'物種'!A2:B113,2,False),"") -> PHB | AP8: 血脈 | AZ8: 所屬陣營 | BI8: 信仰神祇
C9: =Ifna(VLOOKUP(Y7,'物種'!A2:L213,3,FALSE),"") -> 中型or小型 | I9: =Ifna(VLOOKUP(Y7,'物種'!A2:L213,4,FALSE),"") -> 類人生物 | AY9: 學者 Sage
C10: 體型 | I10: 生物類型 | P10: 髮色 | U10: 膚色 | Z10: 瞳色 | AE10: 身高 | AJ10: 體重 | AO10: 年齡 | AT10: 性別 | BD10: 人物背景 | BO10: =IFNA(VLOOKUP(AY9,'背景'!A:B,2,False),"") -> PHB
B12: 主要數值
BG13: =SWITCH(AB16, "野蠻人-Barbarian", IMAGE("https://i.imgur.com/0EYltrl.png"), "法師-Wizard", IMAGE("https://i.imgur.com/B5X4tLg.png"), "術士-Sorcerer", IMAGE("https://i.imgur.com/v7SFUJL.png"), "聖騎士-Paladin", IMAGE("https://i.imgur.com/Lw78TxR.png"), "吟遊詩人-Bard", IMAGE("https://i.imgur.com/wxf5Px2.png"), "契術師-Warlock", IMAGE("https://i.imgur.com/C9HruiS.png"), "武僧-Monk", IMAGE("https://i.imgur.com/5sbMf18.png"), "牧師-Cleric", IMAGE("https://i.imgur.com/JbGHYPQ.png"), "德魯伊-Druid", IMAGE("https://i.imgur.com/Xws8X1s.png"), "遊俠-Ranger", IMAGE("https://i.imgur.com/owoN7t4.png"), "戰士-Fighter", IMAGE("https://i.imgur.com/XGIdtMF.png"), "盜賊-Rogue", IMAGE("https://imgur.com/Hvk5a27.png"), "奇械師-Artificer", IMAGE("https://i.imgur.com/BOrkMQ9.png"), "銃士-Gunslinger", IMAGE("https://duk.tw/Dq0X79.png"), "怪物獵人-Monster Hunter", IMAGE("https://duk.tw/9Zxjiv.png"), "拳鬥士-Pugilist", IMAGE("https://duk.tw/sAcpDy.jpg"), "", IMAGE("https://i.imgur.com/Ebaz1xz.png") )
C14: 屬性值 | O14: 豁免值 | AB14: 血量計算 | AY14: 經驗值
C15: 力量 | G15: 10 | J15: =ROUNDDOWN(Str/2,0)-5 -> 0 | N15: =if(O15="✓",IMAGE("https://i.imgur.com/APyehpS.png"), IF(O15="🗴",IMAGE("https://i.imgur.com/wXw7xUR.png"),"")) | Q15: FALSE | S15: 力量 | W15: =StrMod+IF('角色卡'!Q15=TRUE,Prof,0) -> 0 | AB15: 職業 | AL15: Lv | AN15: 生命骰 | AS15: HP | AU15: 體魄 | AY15: 0
C16: 敏捷 | G16: 12 | J16: =ROUNDDOWN(Dex/2,0)-5 -> 1 | N16: =if(O16="✓",IMAGE("https://i.imgur.com/APyehpS.png"), IF(O16="🗴",IMAGE("https://i.imgur.com/wXw7xUR.png"),"")) | Q16: FALSE | S16: 敏捷 | W16: =DexMod+IF('角色卡'!Q16=TRUE,Prof,0) -> 1 | Z16: Ⅰ | AB16: 法師-Wizard | AL16: 3 | AN16: =SWITCH(AB16, "野蠻人-Barbarian", "1d12", "法師-Wizard", "1d6", "術士-Sorcerer", "1d6", "聖騎士-Paladin", "1d10", "吟遊詩人-Bard", "1d8", "契術師-Warlock", "1d8", "武僧-Monk", "1d8", "牧師-Cleric", "1d8", "德魯伊-Druid", "1d8", "遊俠-Ranger", "1d10", "戰士-Fighter", "1d10", "盜賊-Rogue", "1d8", "奇械師-Artificer", "1d8", "銃士-Gunslinger", "1d8", "怪物獵人-Monster Hunter", "1d10", "拳鬥士-Pugilist", "1d10", "", "") -> 1d6 | AU16: =IF(AL16="","",AL16*ConMod) -> 3
C17: 體魄 | G17: 12 | J17: =ROUNDDOWN(Con/2,0)-5 -> 1 | N17: =if(O17="✓",IMAGE("https://i.imgur.com/APyehpS.png"), IF(O17="🗴",IMAGE("https://i.imgur.com/wXw7xUR.png"),"")) | S17: 體魄 | W17: =ConMod+IF('角色卡'!Q17=TRUE,Prof,0) -> 1 | Z17: Ⅱ | AN17: =SWITCH(AB17, "野蠻人-Barbarian", "1d12", "法師-Wizard", "1d6", "術士-Sorcerer", "1d6", "聖騎士-Paladin", "1d10", "吟遊詩人-Bard", "1d8", "契術師-Warlock", "1d8", "武僧-Monk", "1d8", "牧師-Cleric", "1d8", "德魯伊-Druid", "1d8", "遊俠-Ranger", "1d10", "戰士-Fighter", "1d10", "盜賊-Rogue", "1d8", "奇械師-Artificer", "1d8", "銃士-Gunslinger", "1d8", "怪物獵人-Monster Hunter", "1d10", "", "") | AU17: =IF(AL17="","",AL17*ConMod) | AY17: 速度 | BB17: 游泳
C18: 智力 | G18: 17 | J18: =ROUNDDOWN(Int/2,0)-5 -> 3 | N18: =if(O18="✓",IMAGE("https://i.imgur.com/APyehpS.png"), IF(O18="🗴",IMAGE("https://i.imgur.com/wXw7xUR.png"),"")) | Q18: TRUE | S18: 智力 | W18: =IntMod+IF('角色卡'!Q18=TRUE,Prof,0) -> 5 | Z18: Ⅲ | AN18: =SWITCH(AB18, "野蠻人-Barbarian", "1d12", "法師-Wizard", "1d6", "術士-Sorcerer", "1d6", "聖騎士-Paladin", "1d10", "吟遊詩人-Bard", "1d8", "契術師-Warlock", "1d8", "武僧-Monk", "1d8", "牧師-Cleric", "1d8", "德魯伊-Druid", "1d8", "遊俠-Ranger", "1d10", "戰士-Fighter", "1d10", "盜賊-Rogue", "1d8", "奇械師-Artificer", "1d8", "銃士-Gunslinger", "1d8", "怪物獵人-Monster Hunter", "1d10", "", "") | AU18: =IF(AL18="","",AL18*ConMod) | AY18: 40 | BB18: 0
C19: 感知 | G19: 13 | J19: =ROUNDDOWN(Wis/2,0)-5 -> 1 | N19: =if(O19="✓",IMAGE("https://i.imgur.com/APyehpS.png"), IF(O19="🗴",IMAGE("https://i.imgur.com/wXw7xUR.png"),"")) | Q19: TRUE | S19: 感知 | W19: =WisMod+IF('角色卡'!Q19=TRUE,Prof,0) -> 3 | AF19: 每級額外生命 | AN19: 總額外生命 | AU19: =AL20*AL19 -> 0 | AY19: 飛行 | BB19: 攀爬
C20: 魅力 | G20: 12 | J20: =ROUNDDOWN(Cha/2,0)-5 -> 1 | N20: =if(O20="✓",IMAGE("https://i.imgur.com/APyehpS.png"), IF(O20="🗴",IMAGE("https://i.imgur.com/wXw7xUR.png"),"")) | Q20: FALSE | S20: 魅力 | W20: =ChaMod+IF('角色卡'!Q20=TRUE,Prof,0) -> 1 | AB20: 總等級 | AL20: =SUM(AL16:AM18) -> 3 | AN20: ᚲᚢᛈᚾᛟᛟᛞᛚᛖ9141 | AS20: =SUM(AS16:AT18) -> 0 | AU20: =SUM(AU16:AV18) -> 3 | AY20: 0 | BB20: 0
J21: 調整值 | O21: 優劣 | Q21: 熟練 | W21: 調整值
R22: Icon | U22: FALSE | AC22: =SUM(AF22:AJ22) -> 9 | AE22: = | AF22: =MAX(AL20-1,0) -> 2 | AH22: + | AI22: =AL22 -> 7 | AK22: = | AL22: =IF(OR(AN16="1d6"),6+ConMod,IF(OR(AN16="1d8"),8+ConMod,IF(OR(AN16="1d10"),10+ConMod,IF(OR(AN16="1d12"),12+ConMod,0)))) -> 7 | AT22: =MAX(SUM(AS20:AV20),0) -> 3 | AW22: =IF(and(AT22=0,abs(AS20)>=AU20),1,0) -> 0
X23: .
B24: 技能數值 | V24: 戰鬥數值
X25: 臨時生命 | AB25: 0 | AF25: 警覺 | AJ25: FALSE
C26: 加值 | F26: 技能 | N26: 熟練 | Q26: 優劣 | X26: 生命值 | AF26: 先攻加值 | AN26: 護甲值 | AV26: 護甲 | AY26: 智力 | BB26: 法師 | BF26: 箭袋/弩矢匣 | BP26: 穿戴護甲 | BX26: 屬性 | CA26: AC | CD26: 敏捷 | CG26: 劣勢 | CJ26: 重量
B27: =if(Q27="✓",IMAGE("https://i.imgur.com/APyehpS.png"), IF(Q27="🗴",IMAGE("https://i.imgur.com/wXw7xUR.png"),"")) | C27: =StrMod+(Prof*IF(N27="x2",2,IF(N27="½",0.4,IF(N27="●",1,0)))) -> 0 | F27: 運動-力量 | V27: =IF(U22=true,IMAGE("https://i.imgur.com/Ko3ATxC.png"),"") | X27: 17 | AA27: 17 | AF27: 0 | AI27: =J16+IF(OR(AK57="幽域追蹤者",BH57="幽域追蹤者",CE57="幽域追蹤者"),J19)+IF(AJ25=TRUE,C47) -> 1 | AL27: =IF(U22=true,IMAGE("https://i.imgur.com/SB2v8hd.png"),"") | AN27: 12 | AT27: = | AV27: =CA27 -> 10 | AY27: =2 -> 2 | BB27: =IF(AND(BX27="法師",BR27=""),IF(3-AV29<0,0,3-AV29),"") | BF27: 0 | BI27: 無 | CA27: =IFNA(VLOOKUP(BR27,'武器&護甲'!J2:L14,2,FALSE),10)+BP27 -> 10 | CD27: =IF(BX27="重甲",0,IF(BX27="中甲",IF(DexMod>=2,2,DexMod),DexMod)) -> 1 | CG27: FALSE | CJ27: =IFNA(VLOOKUP(BR27,'武器&護甲'!J2:L14,3,FALSE),0) -> 0
B28: =if(Q28="✓",IMAGE("https://i.imgur.com/APyehpS.png"), IF(Q28="🗴",IMAGE("https://i.imgur.com/wXw7xUR.png"),"")) | C28: =DexMod+(Prof*IF(N28="x2",2,IF(N28="½",0.4,IF(N28="●",1,0)))) -> 1 | F28: 特技動作-敏捷 | Q28: ✓ | AV28: 無甲 | AY28: 天生 | BB28: 其他 | BF28: 0 | BI28: 無 | BR28: 盾牌 | CA28: =IF(BX28="卸下",0,IF(BX28="握持",2+BP28,IF(BX28="無",0,))) | CD28: 它 | CG28: FALSE | CJ28: =IF(BX28="卸下",6,IF(BX28="握持",6,IF(BX28="無",0,)))
B29: =if(Q29="✓",IMAGE("https://i.imgur.com/APyehpS.png"), IF(Q29="🗴",IMAGE("https://i.imgur.com/wXw7xUR.png"),"")) | C29: =DexMod+(Prof*IF(N29="x2",2,IF(N29="½",0.4,IF(N29="●",1,0)))) -> 1 | F29: 巧手-敏捷 | X29: 目前 | AA29: 最大 | AF29: 目前 | AI29: 加值 | BF29: 0 | BI29: 無 | BX29: 合計: | CA29: =SUM(CA27:CC28)+CD27 -> 11
B30: =if(Q30="✓",IMAGE("https://i.imgur.com/APyehpS.png"), IF(Q30="🗴",IMAGE("https://i.imgur.com/wXw7xUR.png"),"")) | C30: =DexMod+(Prof*IF(N30="x2",2,IF(N30="½",0.4,IF(N30="●",1,0)))) -> 1 | F30: 隱匿-敏捷 | X30: 生命骰 | AH30: 英雄激勵 | AN30: FALSE
B31: =if(Q31="✓",IMAGE("https://i.imgur.com/APyehpS.png"), IF(Q31="🗴",IMAGE("https://i.imgur.com/wXw7xUR.png"),"")) | C31: =IntMod+(Prof*IF(N31="x2",2,IF(N31="½",0.4,IF(N31="●",1,0))))+IF(AND('職業能力選項'!R3="-魔術師",'職業能力'!E2>0),IF(WisMod>1,WisMod,1),"")+IF(AND('職業能力選項'!N3="-奇術使",'職業能力'!D2>0),IF(WisMod>1,WisMod,1),"") -> 7 | F31: 奧秘-智力 | N31: x2 | V31: D6 | Z31: =SUMIF(AN16:AR18, "1d6", AL16:AM18) -> 3 | AB31: =IF(Z31>0,if(ConMod<0,"1d6"&ConMod,if(ConMod=0,"1d6"&"+"&+0,"1d6"&"+"&+ConMod)),"") -> 1d6+1 | AU31: 術法點 | BB31: 狂暴 | BI31: 功力 | BP31: 武藝 | BW31: 數值計算
B32: =if(Q32="✓",IMAGE("https://i.imgur.com/APyehpS.png"), IF(Q32="🗴",IMAGE("https://i.imgur.com/wXw7xUR.png"),"")) | C32: =IntMod+(Prof*IF(N32="x2",2,IF(N32="½",0.4,IF(N32="●",1,0)))) -> 5 | F32: 歷史-智力 | N32: ● | V32: D8 | Z32: =SUMIF(AN16:AR18, "1d8", AL16:AM18) -> 0 | AB32: =IF(Z32>0,if(ConMod<0,"1d8"&ConMod,if(ConMod=0,"1d8"&"+"&+0,"1d8"&"+"&+ConMod)),"") | AH32: ~死亡豁免~ | BW32: 屬性 | BZ32: 額外 | CC32: DC / 檢定 / 加值
B33: =if(Q33="✓",IMAGE("https://i.imgur.com/APyehpS.png"), IF(Q33="🗴",IMAGE("https://i.imgur.com/wXw7xUR.png"),"")) | C33: =IntMod+(Prof*IF(N33="x2",2,IF(N33="½",0.4,IF(N33="●",1,0)))) -> 3 | F33: 調查-智力 | V33: D10 | Z33: =SUMIF(AN16:AR18, "1d10", AL16:AM18) -> 0 | AB33: =IF(Z33>0,if(ConMod<0,"1d10"&ConMod,if(ConMod=0,"1d10"&"+"&+0,"1d10"&"+"&+ConMod)),"") | AH33: 成功( ≧10) | AM33: FALSE | AO33: FALSE | AQ33: FALSE | BW33: 智力 | CC33: =IF(BW33="","",'索引資料'!J33&" / "&TEXT('索引資料'!K33,'索引資料'!K33)&" / "&TEXT('索引資料'!L33,'索引資料'!L33)) -> 13 / +5 / +3
B34: =if(Q34="✓",IMAGE("https://i.imgur.com/APyehpS.png"), IF(Q34="🗴",IMAGE("https://i.imgur.com/wXw7xUR.png"),"")) | C34: =IntMod+(Prof*IF(N34="x2",2,IF(N34="½",0.4,IF(N34="●",1,0))))+IF(AND('職業能力選項'!R3="-魔術師",'職業能力'!E2>0),IF(WisMod>1,WisMod,1),"") -> 3 | F34: 自然-智力 | V34: D12 | Z34: =SUMIF(AN16:AR18, "1d12", AL16:AM18) -> 0 | AB34: =IF(Z34>0,if(ConMod<0,"1d12"&ConMod,if(ConMod=0,"1d12"&"+"&+0,"1d12"&"+"&+ConMod)),"") | AH34: 失敗(＜10) | AM34: FALSE | AO34: FALSE | AQ34: FALSE | AU34: 剩餘次數 | AY34: - | BB34: 剩餘次數 | BF34: - | BI34: 剩餘次數 | BM34: - | BP34: 剩餘次數 | BT34: - | CC34: =IF(BW34="","",'索引資料'!J34&" / "&TEXT('索引資料'!K34,'索引資料'!K34)&" / "&TEXT('索引資料'!L34,'索引資料'!L34))
B35: =if(Q35="✓",IMAGE("https://i.imgur.com/APyehpS.png"), IF(Q35="🗴",IMAGE("https://i.imgur.com/wXw7xUR.png"),"")) | C35: =IntMod+(Prof*IF(N35="x2",2,IF(N35="½",0.4,IF(N35="●",1,0))))+IF(AND('職業能力選項'!N3="-奇術使",'職業能力'!D2>0),IF(WisMod>1,WisMod,1),"") -> 3 | F35: 宗教-智力 | X35: 剩餘 | Z35: 最大 | CC35: =IF(BW35="","",'索引資料'!J35&" / "&TEXT('索引資料'!K35,'索引資料'!K35)&" / "&TEXT('索引資料'!L35,'索引資料'!L35))
B36: =if(Q36="✓",IMAGE("https://i.imgur.com/APyehpS.png"), IF(Q36="🗴",IMAGE("https://i.imgur.com/wXw7xUR.png"),"")) | C36: =WisMod+(Prof*IF(N36="x2",2,IF(N36="½",0.4,IF(N36="●",1,0)))) -> 1 | F36: 動物馴服-感知 | X36: 武器與法器 | AF36: 命中 | AI36: 傷害骰 | AO36: 調整值 | AR36: 距離 | AV36: 傷害 | AY36: 重量 | BB36: # | BD36: 精 | BF36: 精通屬性 | BL36: 屬性
B37: =if(Q37="✓",IMAGE("https://i.imgur.com/APyehpS.png"), IF(Q37="🗴",IMAGE("https://i.imgur.com/wXw7xUR.png"),"")) | C37: =WisMod+(Prof*IF(N37="x2",2,IF(N37="½",0.4,IF(N37="●",1,0)))) -> 1 | F37: 察言觀色-感知 | Z37: 長劍 | AF37: =2 -> 2 | AI37: =IFNA((VLOOKUP(Z37,'武器&護甲'!$A$2:$H$118,3,False))&X37,"") -> 1d8(1d10) | AO37: 0 | AR37: =IFNA(VLOOKUP(Z37,'武器&護甲'!$A$2:$H$118,4,False),"") -> 觸及 | AV37: =IFNA(VLOOKUP(Z37,'武器&護甲'!$A$2:$H$118,5,False),"") -> 劈砍 | AY37: =IFNA(VLOOKUP(Z37,'武器&護甲'!$A$2:$H$118,6,FALSE),"") -> 3 | BD37: FALSE | BF37: =IFNA(IF(BD37=TRUE,VLOOKUP(Z37,'武器&護甲'!$A$2:$H$118,8,False),""),"") | BL37: =IFNA(VLOOKUP(Z37,'武器&護甲'!$A$2:$H$118,7,False),"") -> 可雙手 | BW37: 筆記
B38: =if(Q38="✓",IMAGE("https://i.imgur.com/APyehpS.png"), IF(Q38="🗴",IMAGE("https://i.imgur.com/wXw7xUR.png"),"")) | C38: =WisMod+(Prof*IF(N38="x2",2,IF(N38="½",0.4,IF(N38="●",1,0)))) -> 1 | F38: 醫藥-感知 | AI38: =IFNA((VLOOKUP(Z38,'武器&護甲'!$A$2:$H$118,3,False))&X38,"") | AR38: =IFNA(VLOOKUP(Z38,'武器&護甲'!$A$2:$H$118,4,False),"") | AV38: =IFNA(VLOOKUP(Z38,'武器&護甲'!$A$2:$H$118,5,False),"") | AY38: =IFNA(VLOOKUP(Z38,'武器&護甲'!$A$2:$H$118,6,FALSE),"") | BD38: FALSE | BF38: =IFNA(IF(BD38=TRUE,VLOOKUP(Z38,'武器&護甲'!$A$2:$H$118,8,False),""),"") | BL38: =IFNA(VLOOKUP(Z38,'武器&護甲'!$A$2:$H$118,7,False),"") | BW38: 攻擊擲骰(+2)
B39: =if(Q39="✓",IMAGE("https://i.imgur.com/APyehpS.png"), IF(Q39="🗴",IMAGE("https://i.imgur.com/wXw7xUR.png"),"")) | C39: =WisMod+(Prof*IF(N39="x2",2,IF(N39="½",0.4,IF(N39="●",1,0)))) -> 3 | F39: 察覺-感知 | N39: ● | AI39: =IFNA((VLOOKUP(Z39,'武器&護甲'!$A$2:$H$118,3,False))&X39,"") | AR39: =IFNA(VLOOKUP(Z39,'武器&護甲'!$A$2:$H$118,4,False),"") | AV39: =IFNA(VLOOKUP(Z39,'武器&護甲'!$A$2:$H$118,5,False),"") | AY39: =IFNA(VLOOKUP(Z39,'武器&護甲'!$A$2:$H$118,6,FALSE),"") | BD39: FALSE | BF39: =IFNA(IF(BD39=TRUE,VLOOKUP(Z39,'武器&護甲'!$A$2:$H$118,8,False),""),"") | BL39: =IFNA(VLOOKUP(Z39,'武器&護甲'!$A$2:$H$118,7,False),"") | BW39: 可以花費其中的一次使用次數，並使用一個動作治療你 5 呎內的一個生物。該生物花費一個自身的生命骰，然後你擲出該骰。該生物恢復的生命值等於擲出的結果加上你的熟練加值。
B40: =if(Q40="✓",IMAGE("https://i.imgur.com/APyehpS.png"), IF(Q40="🗴",IMAGE("https://i.imgur.com/wXw7xUR.png"),"")) | C40: =WisMod+(Prof*IF(N40="x2",2,IF(N40="½",0.4,IF(N40="●",1,0)))) -> 1 | F40: 求生-感知 | AI40: =IFNA((VLOOKUP(Z40,'武器&護甲'!$A$2:$H$118,3,False))&X40,"") | AR40: =IFNA(VLOOKUP(Z40,'武器&護甲'!$A$2:$H$118,4,False),"") | AV40: =IFNA(VLOOKUP(Z40,'武器&護甲'!$A$2:$H$118,5,False),"") | AY40: =IFNA(VLOOKUP(Z40,'武器&護甲'!$A$2:$H$118,6,FALSE),"") | BD40: FALSE | BF40: =IFNA(IF(BD40=TRUE,VLOOKUP(Z40,'武器&護甲'!$A$2:$H$118,8,False),""),"") | BL40: =IFNA(VLOOKUP(Z40,'武器&護甲'!$A$2:$H$118,7,False),"")
B41: =if(Q41="✓",IMAGE("https://i.imgur.com/APyehpS.png"), IF(Q41="🗴",IMAGE("https://i.imgur.com/wXw7xUR.png"),"")) | C41: =ChaMod+(Prof*IF(N41="x2",2,IF(N41="½",0.4,IF(N41="●",1,0)))) -> 1 | F41: 欺瞞-魅力 | AI41: =IFNA((VLOOKUP(Z41,'武器&護甲'!$A$2:$H$118,3,False))&X41,"") | AR41: =IFNA(VLOOKUP(Z41,'武器&護甲'!$A$2:$H$118,4,False),"") | AV41: =IFNA(VLOOKUP(Z41,'武器&護甲'!$A$2:$H$118,5,False),"") | AY41: =IFNA(VLOOKUP(Z41,'武器&護甲'!$A$2:$H$118,6,FALSE),"") | BD41: FALSE | BF41: =IFNA(IF(BD41=TRUE,VLOOKUP(Z41,'武器&護甲'!$A$2:$H$118,8,False),""),"") | BL41: =IFNA(VLOOKUP(Z41,'武器&護甲'!$A$2:$H$118,7,False),"")
B42: =if(Q42="✓",IMAGE("https://i.imgur.com/APyehpS.png"), IF(Q42="🗴",IMAGE("https://i.imgur.com/wXw7xUR.png"),"")) | C42: =ChaMod+(Prof*IF(N42="x2",2,IF(N42="½",0.4,IF(N42="●",1,0)))) -> 1 | F42: 威嚇-魅力 | AI42: =IFNA((VLOOKUP(Z42,'武器&護甲'!$A$2:$H$118,3,False))&X42,"") | AR42: =IFNA(VLOOKUP(Z42,'武器&護甲'!$A$2:$H$118,4,False),"") | AV42: =IFNA(VLOOKUP(Z42,'武器&護甲'!$A$2:$H$118,5,False),"") | AY42: =IFNA(VLOOKUP(Z42,'武器&護甲'!$A$2:$H$118,6,FALSE),"") | BD42: FALSE | BF42: =IFNA(IF(BD42=TRUE,VLOOKUP(Z42,'武器&護甲'!$A$2:$H$118,8,False),""),"") | BL42: =IFNA(VLOOKUP(Z42,'武器&護甲'!$A$2:$H$118,7,False),"")
B43: =if(Q43="✓",IMAGE("https://i.imgur.com/APyehpS.png"), IF(Q43="🗴",IMAGE("https://i.imgur.com/wXw7xUR.png"),"")) | C43: =ChaMod+(Prof*IF(N43="x2",2,IF(N43="½",0.4,IF(N43="●",1,0)))) -> 1 | F43: 表演-魅力
B44: =if(Q44="✓",IMAGE("https://i.imgur.com/APyehpS.png"), IF(Q44="🗴",IMAGE("https://i.imgur.com/wXw7xUR.png"),"")) | C44: =ChaMod+(Prof*IF(N44="x2",2,IF(N44="½",0.4,IF(N44="●",1,0)))) -> 3 | F44: 說服-魅力 | N44: ● | X44: 物種能力 | AV44: 專長
X45: =Ifna(VLOOKUP(Y7,'物種'!A2:L213,5,FALSE),"") -> 創造力 Resourceful | AV45: 起源專長: | AZ45: =IFNA(VLOOKUP(C66,'背景'!A1:I114,6,FALSE),"") -> 魔法學徒(法師) Magic Initiate
C46: =WisMod+(Prof*IF(N39="x2",2,IF(N39="½",0.4,IF(N39="●",1,0))))+10+IF(Q39="✓",5,if(Q39="🗴",-5,0)) -> 13 | F46: 被動感知【察覺】 | X46: =IFNA(VLOOKUP(Y7,'物種'!A2:L213,6,FALSE),"") -> 技能熟練 Skillful
C47: =IF(AL20<5,2,IF(AL20<9,3,IF(AL20<13,4,IF(AL20<17,5,IF(AL20<21,6,0))))) -> 2 | F47: 熟練加值 | X47: =IFNA(VLOOKUP(Y7,'物種'!A2:L213,7,False),"") -> 多才多藝 Versatile
C48: =IFNA(VLOOKUP(N48,$C$15:$L$20,8,FALSE)+(Prof*IF(Q48="x2",2,IF(Q48="½",0.4,IF(Q48="●",1,0)))),"") -> 1 | F48: 書法工具 | N48: =IFNA(VLOOKUP(F48,'索引資料'!$L$41:$M$65,2,False),"") -> 敏捷 | X48: =IFNA(VLOOKUP(Y7,'物種'!A2:L213,8,False),"")
C49: =IFNA(VLOOKUP(N49,$C$15:$L$20,8,FALSE)+(Prof*IF(Q49="x2",2,IF(Q49="½",0.4,IF(Q49="●",1,0)))),"") -> 1 | F49: 樂器(通用) | N49: =IFNA(VLOOKUP(F49,'索引資料'!$L$41:$M$65,2,False),"") -> 魅力 | X49: =IFNA(VLOOKUP(Y7,'物種'!A2:L213,9,FALSE),"")
C50: =IFNA(VLOOKUP(N50,$C$15:$L$20,8,FALSE)+(Prof*IF(Q50="x2",2,IF(Q50="½",0.4,IF(Q50="●",1,0)))),"") -> 1 | F50: 賭具(通用) | N50: =IFNA(VLOOKUP(F50,'索引資料'!$L$41:$M$65,2,False),"") -> 感知 | X50: =IFNA(VLOOKUP(Y7,'物種'!A2:L213,10,FALSE),"") | AV50: 傳奇恩惠:
C51: =IFNA(VLOOKUP(N51,$C$15:$L$20,8,FALSE)+(Prof*IF(Q51="x2",2,IF(Q51="½",0.4,IF(Q51="●",1,0)))),"") -> 3 | F51: 草藥工具 | N51: =IFNA(VLOOKUP(F51,'索引資料'!$L$41:$M$65,2,False),"") -> 智力 | X51: =IFNA(VLOOKUP(Y7,'物種'!A2:L213,11,FALSE),"") | AV51: 傳奇恩惠:
C52: =IFNA(VLOOKUP(N52,$C$15:$L$20,8,FALSE)+(Prof*IF(Q52="x2",2,IF(Q52="½",0.4,IF(Q52="●",1,0)))),"") -> 3 | F52: 製毒工具 | N52: =IFNA(VLOOKUP(F52,'索引資料'!$L$41:$M$65,2,False),"") -> 智力 | X52: =IFNA(VLOOKUP(Y7,'物種'!A2:L213,12,FALSE),"")
B53: <更多工具熟練、更多種族特質、更多專長
B55: 創卡雜項 | V55: 職業能力
C57: 技能(物種): | W57: 職業Ⅰ能力 | AH57: 子職 | AK57: 劍詠師 | AT57: 職業Ⅱ能力 | BE57: 子職 | BQ57: 職業Ⅲ能力 | CB57: 子職
C58: 語言(起源): | H58: 通用語、 | W58: ='索引資料'!F21 -> 施法 | AH58: ='索引資料'!J21 -> 劍歌 | AT58: ='索引資料'!G21 | BE58: ='索引資料'!K21 | BQ58: ='索引資料'!H21 | CB58: ='索引資料'!L21
C59: =IF('角色卡'!AB16="野蠻人-Barbarian","野蠻人",IF('角色卡'!AB16="法師-Wizard","法師",IF('角色卡'!AB16="術士-Sorcerer","術士",IF('角色卡'!AB16="聖騎士-Paladin","聖騎士",IF('角色卡'!AB16="武僧-Monk","武僧",IF('角色卡'!AB16="契術師-Warlock","契術師",IF('角色卡'!AB16="吟遊詩人-Bard","吟遊",IF('角色卡'!AB16="牧師-Cleric","牧師",IF('角色卡'!AB16="德魯伊-Druid","德魯伊",IF('角色卡'!AB16="遊俠-Ranger","遊俠",IF('角色卡'!AB16="戰士-Fighter","戰士",IF('角色卡'!AB16="盜賊-Rogue","盜賊",IF('角色卡'!AB16="奇械師-Artificer","奇械師","職業"))))))))))))) -> 法師 | F59: =IFNA(VLOOKUP(AB16,'索引資料'!G3:I18,2,False),"") -> 選擇2項：奧秘、歷史、察言觀色、調查、醫藥、自然、宗教 | W59: ='索引資料'!F22 -> 儀式學家 | AH59: ='索引資料'!J22 -> 戰歌訓練 | AT59: ='索引資料'!G22 | BE59: ='索引資料'!K22 | BQ59: ='索引資料'!H22 | CB59: ='索引資料'!L22
C60: 技能 | W60: ='索引資料'!F23 -> 奧術恢復(2個環位) | AH60: ='索引資料'!J23 | AT60: ='索引資料'!G23 | BE60: ='索引資料'!K23 | BQ60: ='索引資料'!H23 | CB60: ='索引資料'!L23
C61: 技能(職業): | W61: ='索引資料'!F24 -> 學者 | AH61: ='索引資料'!J24 | AT61: ='索引資料'!G24 | BE61: ='索引資料'!K24 | BQ61: ='索引資料'!H24 | CB61: ='索引資料'!L24
C62: 語言(職業): | W62: ='索引資料'!F25 | AH62: ='索引資料'!J25 | AT62: ='索引資料'!G25 | BE62: ='索引資料'!K25 | BQ62: ='索引資料'!H25 | CB62: ='索引資料'!L25
C63: 武器(職業): | W63: ='索引資料'!F26 | AH63: ='索引資料'!J26 | AT63: ='索引資料'!G26 | BE63: ='索引資料'!K26 | BQ63: ='索引資料'!H26 | CB63: ='索引資料'!L26
C64: 護甲(職業): | W64: ='索引資料'!F27 | AH64: ='索引資料'!J27 | AT64: ='索引資料'!G27 | BE64: ='索引資料'!K27 | BQ64: ='索引資料'!H27 | CB64: ='索引資料'!L27
C65: 工具(職業): | W65: ='索引資料'!F28 | AH65: ='索引資料'!J28 | AT65: ='索引資料'!G28 | BE65: ='索引資料'!K28 | BQ65: ='索引資料'!H28 | CB65: ='索引資料'!L28
C66: =AY9 -> 學者 Sage | K66: 屬性值 | N66: =IFNA(VLOOKUP(C66,'背景'!A1:I114,3,False)&","&VLOOKUP(C66,'背景'!A1:I114,4,False)&","&VLOOKUP(C66,'背景'!A1:I114,5,False),"") -> 體魄,智力,感知 | W66: ='索引資料'!F29 | AH66: ='索引資料'!F34 | AT66: ='索引資料'!G29 | BE66: ='索引資料'!G34 | BQ66: ='索引資料'!H29 | CB66: ='索引資料'!H34
C67: 屬性(背景): | W67: ='索引資料'!F30 | AH67: ='索引資料'!F35 | AT67: ='索引資料'!G30 | BE67: ='索引資料'!G35 | BQ67: ='索引資料'!H30 | CB67: ='索引資料'!H35
C68: 技能(背景): | H68: =IFNA(VLOOKUP(C66,'背景'!A1:I114,7,False)&","&VLOOKUP(C66,'背景'!A1:I114,8,False),"") -> 奧秘,歷史 | W68: ='索引資料'!F31 | AH68: ='索引資料'!F36 | AT68: ='索引資料'!G31 | BE68: ='索引資料'!G36 | BQ68: ='索引資料'!H31 | CB68: ='索引資料'!H36
C69: 工具(背景): | H69: =IFNA(VLOOKUP(C66,'背景'!A1:I114,9,FALSE),"") -> 書法工具 | W69: ='索引資料'!F32 | AH69: ='索引資料'!F37 | AT69: ='索引資料'!G32 | BE69: ='索引資料'!G37 | BQ69: ='索引資料'!H32 | CB69: ='索引資料'!H37
H70: ="它式"&'請先閱讀'!L24 -> 它式角色卡版本:3.9 | W70: ='索引資料'!F33 | AH70: ='索引資料'!F38 | AT70: ='索引資料'!G33 | BE70: ='索引資料'!G38 | BQ70: ='索引資料'!H33 | CB70: ='索引資料'!H38
C71: 其他熟練
C72: 技能(額外):
C73: 語言(額外):
C74: 武器(額外):
C75: 護甲(額外):
C76: 工具(額外):
C77: 其他(額外):
A79: I hereby declare this sheet is not and will never be copyrighted or used to make any profit with any sort of form, for this sheet is mainly made by Cupnoodle and his servermate.

Sheet 職業能力選項
A1: 野蠻人 | H1: 吟遊詩人 | L1: 牧師 | P1: 德魯伊 | W1: 戰士 | AD1: 武僧 | AH1: 聖騎士 | AM1: 遊俠 | AT1: 盜賊 | AY1: 術士 | BC1: 契術師 | BG1: 法師 | BK1: =IF('請先閱讀'!$F$34=true,"奇械師","") -> 奇械師 | BO1: =IF('請先閱讀'!$O$29=true,"銃士","") | BT1: =IF('請先閱讀'!$O$31=true,"怪物獵人","")
C2: 武器精通 | D2: 精通屬性 | F2: 荒野之心形貌 | J2: =IF('請先閱讀'!$O$31=true,"冒險者學院天賦","") | N2: 神聖誓約 | R2: 原初誓約 | T2: 大地結社法術 | U2: 傷害類型 | Y2: 武器精通 | Z2: 精通屬性 | AB2: 戰鬥大師戰技 | AF2: 活體武器顯化 | AJ2: 武器精通 | AK2: 精通屬性 | AO2: 武器精通 | AP2: 精通屬性 | AR2: 原初動物夥伴 | AV2: 武器精通 | AW2: 精通屬性 | BA2: 超魔法 | BE2: 魔能祈喚 | BI2: 預言學派天眼通 | BM2: 魔法物品方案 | BQ2: 武器精通 | BR2: 精通屬性 | BV2: 怪物寶典
D3: =IFNA(VLOOKUP(C3,'武器&護甲'!$A$2:$H$58,8,FALSE),"") | F3: (請選擇) | N3: (請選擇) | R3: (請選擇) | T3: (請選擇) | Z3: =IFNA(VLOOKUP(Y3,'武器&護甲'!$A$2:$H$58,8,FALSE),"") | AF3: (請選擇) | AK3: =IFNA(VLOOKUP(AJ3,'武器&護甲'!$A$2:$H$58,8,FALSE),"") | AP3: =IFNA(VLOOKUP(AO3,'武器&護甲'!$A$2:$H$58,8,FALSE),"") | AW3: =IFNA(VLOOKUP(AV3,'武器&護甲'!$A$2:$H$58,8,FALSE),"") | BI3: (請選擇) | BR3: =IFNA(VLOOKUP(BQ3,'武器&護甲'!$A$2:$H$58,8,FALSE),"")
D4: =IFNA(VLOOKUP(C4,'武器&護甲'!$A$2:$H$58,8,FALSE),"") | Z4: =IFNA(VLOOKUP(Y4,'武器&護甲'!$A$2:$H$58,8,FALSE),"") | AK4: =IFNA(VLOOKUP(AJ4,'武器&護甲'!$A$2:$H$58,8,FALSE),"") | AP4: =IFNA(VLOOKUP(AO4,'武器&護甲'!$A$2:$H$58,8,FALSE),"") | AW4: =IFNA(VLOOKUP(AV4,'武器&護甲'!$A$2:$H$58,8,FALSE),"") | BR4: =IFNA(VLOOKUP(BQ4,'武器&護甲'!$A$2:$H$58,8,FALSE),"")
D5: =IFNA(VLOOKUP(C5,'武器&護甲'!$A$2:$H$58,8,FALSE),"") | F5: =IF('請先閱讀'!$O$31=true,"憤怒亡靈宣洩","") | N5: 受祝擊 | R5: 已知型態 | T5: 星辰宇宙預兆 | Z5: =IFNA(VLOOKUP(Y5,'武器&護甲'!$A$2:$H$58,8,FALSE),"") | AR5: 獵人狩者獵物 | BI5: =IF('請先閱讀'!$O$31=true,"惡魔學家善惡","") | BR5: =IFNA(VLOOKUP(BQ5,'武器&護甲'!$A$2:$H$58,8,FALSE),"")
D6: =IFNA(VLOOKUP(C6,'武器&護甲'!$A$2:$H$58,8,FALSE),"") | F6: (請選擇) | N6: (請選擇) | T6: (請選擇) | Z6: =IFNA(VLOOKUP(Y6,'武器&護甲'!$A$2:$H$58,8,FALSE),"") | AV6: =IF('請先閱讀'!$O$31=true,"厄運使者禍術","") | BI6: (請選擇) | BR6: =IFNA(VLOOKUP(BQ6,'武器&護甲'!$A$2:$H$58,8,FALSE),"")
Z7: =IFNA(VLOOKUP(Y7,'武器&護甲'!$A$2:$H$58,8,FALSE),"")
T8: =IF('請先閱讀'!$O$31=true,"熵力結社災難","") | Z8: =IFNA(VLOOKUP(Y8,'武器&護甲'!$A$2:$H$58,8,FALSE),"") | AR8: 獵人防守戰術 | BQ8: 銃士戰技 | BV8: 武器精通 | BW8: 精通屬性
T9: (請選擇) | BW9: =IFNA(VLOOKUP(BV9,'武器&護甲'!$A$2:$H$58,8,FALSE),"")
Y10: =IF('請先閱讀'!$O$31=true,"活體坩堝化合物","") | BA10: =IF('請先閱讀'!$O$31=true,"悲慘血脈詛咒","") | BW10: =IFNA(VLOOKUP(BV10,'武器&護甲'!$A$2:$H$58,8,FALSE),"")
BA11: (請選擇) | BW11: =IFNA(VLOOKUP(BV11,'武器&護甲'!$A$2:$H$58,8,FALSE),"")
BW12: =IFNA(VLOOKUP(BV12,'武器&護甲'!$A$2:$H$58,8,FALSE),"")
BW13: =IFNA(VLOOKUP(BV13,'武器&護甲'!$A$2:$H$58,8,FALSE),"")
BE14: =IF('請先閱讀'!$O$31=true,"宇宙寄生體肉體","")
R15: =IF(R$2>=7,"元素狂怒","") -> 元素狂怒
R16: (請選擇)

Sheet 索引資料
B2: 施法等級 | E2: 法術來源 | G2: 職業技能熟練 | K2: 子職業列表
B3: 術 | C3: ='職業能力'!N2 -> 0 | E3: =IF('角色卡'!Y7="","物種",K38) -> 人類 | G3: 野蠻人-Barbarian | H3: 選擇2項：動物馴服、運動、威嚇、自然、察覺、求生 | K3: 野蠻人-Barbarian | L3: 狂戰士道途 | M3: 荒野之心道途 | N3: 世界樹道途 | O3: 狂熱者道途 | P3: =IF('請先閱讀'!$O$27=true,"實驗道途","") | Q3: =IF('請先閱讀'!O28=true,"肌肉魔法使道途","") | R3: =IF('請先閱讀'!$O$30=true,"蔑法道途","") | S3: =IF('請先閱讀'!$O$31=true,"分裂道途","") | T3: =IF('請先閱讀'!$O$31=true,"原初精魂道途","") | U3: =IF('請先閱讀'!$O$31=true,"憤怒亡靈道途","") | V3: =IF('請先閱讀'!O35=true,"冰川道途","")
B4: 法 | C4: ='職業能力'!P2 -> 3 | E4: =IF('角色卡'!AB16="野蠻人-Barbarian","野蠻人",IF('角色卡'!AB16="法師-Wizard","法師",IF('角色卡'!AB16="術士-Sorcerer","術士",IF('角色卡'!AB16="聖騎士-Paladin","聖騎士",IF('角色卡'!AB16="武僧-Monk","武僧",IF('角色卡'!AB16="契術師-Warlock","契術師",IF('角色卡'!AB16="吟遊詩人-Bard","吟遊詩人",IF('角色卡'!AB16="牧師-Cleric","牧師",IF('角色卡'!AB16="德魯伊-Druid","德魯伊",IF('角色卡'!AB16="遊俠-Ranger","遊俠",IF('角色卡'!AB16="戰士-Fighter","戰士",IF('角色卡'!AB16="盜賊-Rogue","盜賊",IF('角色卡'!AB16="奇械師-Artificer","奇械師","職業"))))))))))))) -> 法師 | G4: 吟遊詩人-Bard | H4: 任選3個技能 | K4: 吟遊詩人-Bard | L4: 舞蹈學院 | M4: 迷惑學院 | N4: 軼聞學院 | O4: 勇氣學院 | P4: =IF('請先閱讀'!F31=true,"月亮學院","") -> 月亮學院 | Q4: =IF('請先閱讀'!$O$27=true,"靈哨學院","") | R4: =IF('請先閱讀'!$O$30=true,"戲劇學院","") | S4: =IF('請先閱讀'!$O$31=true,"冒險者學院","") | T4: =IF('請先閱讀'!$O$31=true,"弄臣學院","") | U4: =IF('請先閱讀'!$O$31=true,"安魂學院","") | V4: =IF('請先閱讀'!$O$33=true,"傳頌學院","") | W4: =IF('請先閱讀'!O35=true,"織舞學院","")
B5: 牧 | C5: ='職業能力'!D2 -> 0 | E5: ='角色卡'!AK57 -> 劍詠師 | G5: 牧師-Cleric | H5: 選擇2項：歷史、察言觀色、醫藥、說服、宗教 | K5: 牧師-Cleric | L5: 生命領域 | M5: 光明領域 | N5: 詭術領域 | O5: 戰爭領域 | P5: =IF('請先閱讀'!F31=true,"知識領域","") -> 知識領域 | Q5: =IF('請先閱讀'!$O$27=true,"豐收領域","") | R5: =IF('請先閱讀'!$O$30=true,"天啟領域","") | S5: =IF('請先閱讀'!$O$31=true,"怪異領域","") | T5: =IF('請先閱讀'!$O$31=true,"審判領域","") | U5: =IF('請先閱讀'!$O$31=true,"淨化領域","") | V5: =IF('請先閱讀'!$O$33=true,"心靈領域","") | W5: =IF('請先閱讀'!O35=true,"星界領域","")
B6: 吟 | C6: ='職業能力'!C2 -> 0 | E6: =IF('角色卡'!AB17="野蠻人-Barbarian","野蠻人",IF('角色卡'!AB17="法師-Wizard","法師",IF('角色卡'!AB17="術士-Sorcerer","術士",IF('角色卡'!AB17="聖騎士-Paladin","聖騎士",IF('角色卡'!AB17="武僧-Monk","武僧",IF('角色卡'!AB17="契術師-Warlock","契術師",IF('角色卡'!AB17="吟遊詩人-Bard","吟遊詩人",IF('角色卡'!AB17="牧師-Cleric","牧師",IF('角色卡'!AB17="德魯伊-Druid","德魯伊",IF('角色卡'!AB17="遊俠-Ranger","遊俠",IF('角色卡'!AB17="戰士-Fighter","戰士",IF('角色卡'!AB17="盜賊-Rogue","盜賊",IF('角色卡'!AB17="奇械師-Artificer","奇械師",""))))))))))))) | G6: 德魯伊-Druid | H6: 選擇2項：奧秘、動物馴服、察言觀色、醫藥、自然、察覺、宗教、求生 | K6: 德魯伊-Druid | L6: 大地結社 | M6: 月亮結社 | N6: 海洋結社 | O6: 星辰結社 | P6: =IF('請先閱讀'!$O$27=true,"古道結社","") | Q6: =IF('請先閱讀'!$O$27=true,"柳條結社","") | R6: =IF('請先閱讀'!$O$30=true,"共生結社","") | S6: =IF('請先閱讀'!$O$31=true,"鮮血結社","") | T6: =IF('請先閱讀'!$O$31=true,"熵力結社","") | U6: =IF('請先閱讀'!$O$31=true,"突變結社","") | V6: =IF('請先閱讀'!$O$33=true,"鍛物結社","") | W6: =IF('請先閱讀'!O35=true,"不朽結社","") | X6: =IF('請先閱讀'!O36=true,"輪轉結社","")
B7: 德 | C7: ='職業能力'!E2 -> 0 | E7: ='角色卡'!BH57 | G7: 戰士-Fighter | H7: 選擇2項：特技、動物馴服、運動、歷史、察言觀色、威嚇、說服、察覺、求生 | K7: 戰士-Fighter | L7: 戰鬥大師 | M7: 勇士 | N7: 魔能騎士 | O7: 靈能武士 | P7: =IF('請先閱讀'!F31=true,"旗將","") -> 旗將 | Q7: =IF('請先閱讀'!$O$27=true,"陵墓守衛","") | R7: =IF('請先閱讀'!O28=true,"地城探險家","") | S7: =IF('請先閱讀'!$O$30=true,"英雄","") | T7: =IF('請先閱讀'!$O$31=true,"壁壘衛士","") | U7: =IF('請先閱讀'!$O$31=true,"活體坩堝","") | V7: =IF('請先閱讀'!$O$31=true,"守夜人","") | W7: =IF('請先閱讀'!O35=true,"羽蛇傳令","") | X7: =IF('請先閱讀'!O36=true,"雕骨師","")
B8: 遊 | C8: ='職業能力'!L2 -> 0 | E8: =IF('角色卡'!AB18="野蠻人-Barbarian","野蠻人",IF('角色卡'!AB18="法師-Wizard","法師",IF('角色卡'!AB18="術士-Sorcerer","術士",IF('角色卡'!AB18="聖騎士-Paladin","聖騎士",IF('角色卡'!AB18="武僧-Monk","武僧",IF('角色卡'!AB18="契術師-Warlock","契術師",IF('角色卡'!AB18="吟遊詩人-Bard","吟遊詩人",IF('角色卡'!AB18="牧師-Cleric","牧師",IF('角色卡'!AB18="德魯伊-Druid","德魯伊",IF('角色卡'!AB18="遊俠-Ranger","遊俠",IF('角色卡'!AB18="戰士-Fighter","戰士",IF('角色卡'!AB18="盜賊-Rogue","盜賊",IF('角色卡'!AB18="奇械師-Artificer","奇械師",""))))))))))))) | G8: 武僧-Monk | H8: 選擇2項：特技、運動、歷史、察言觀色、宗教、隱匿 | K8: 武僧-Monk | L8: 命流武者 | M8: 暗影武者 | N8: 四象武者 | O8: 散打武者 | P8: =IF('請先閱讀'!$O$27=true,"瘴癘武者","") | Q8: =IF('請先閱讀'!O28=true,"街頭武者","") | R8: =IF('請先閱讀'!$O$30=true,"天衡武者","") | S8: =IF('請先閱讀'!$O$31=true,"鉛冕武者","") | T8: =IF('請先閱讀'!$O$31=true,"孤高武者","") | U8: =IF('請先閱讀'!$O$31=true,"悔恨武者","") | V8: =IF('請先閱讀'!$O$33=true,"活體武器武者","") | W8: =IF('請先閱讀'!O35=true,"天界武者","")
B9: 聖 | C9: ='職業能力'!J2 -> 0 | E9: ='角色卡'!CE57 | G9: 聖騎士-Paladin | H9: 選擇2項：運動、察言觀色、威嚇、醫藥、說服、宗教 | K9: 聖騎士-Paladin | L9: 奉獻之誓 | M9: 榮耀之誓 | N9: 遠古之誓 | O9: 復仇之誓 | P9: =IF('請先閱讀'!F31=true,"巨靈貴族之誓","") -> 巨靈貴族之誓 | Q9: =IF('請先閱讀'!$O$27=true,"懲戒之誓","") | R9: =IF('請先閱讀'!O28=true,"狂歡之誓","") | S9: =IF('請先閱讀'!$O$30=true,"守護之誓","") | T9: =IF('請先閱讀'!$O$31=true,"瘟疫之誓","") | U9: =IF('請先閱讀'!$O$31=true,"屠戮之誓","") | V9: =IF('請先閱讀'!$O$31=true,"狂熱之誓","") | W9: =IF('請先閱讀'!O35=true,"爐火之誓","")
B10: 詭術師&嗜血竊賊 | C10: =IF(OR('角色卡'!AK57=L11,'角色卡'!BH57=L11,'角色卡'!CE57=L11,'角色卡'!AK57=V11,'角色卡'!BH57=V11,'角色卡'!CE57=V11),'職業能力'!M2,0) -> 0 | E10: =IF(OR('角色卡'!AB16=K13,'角色卡'!AB17=K13,'角色卡'!AB18=K13),"祈喚","") | G10: 遊俠-Ranger | H10: 選擇3項：動物馴服、運動、察言觀色、調查、自然、察覺、隱匿、求生 | K10: 遊俠-Ranger | L10: 獸王 | M10: 妖精漫遊者 | N10: 幽域追蹤者 | O10: 獵人 | P10: =IF('請先閱讀'!F31=true,"凜冬行者","") -> 凜冬行者 | Q10: =IF('請先閱讀'!$O$27=true,"晦暗先驅","") | R10: =IF('請先閱讀'!$O$30=true,"荒徑守護者","") | S10: =IF('請先閱讀'!$O$31=true,"綠林死神","") | T10: =IF('請先閱讀'!$O$31=true,"原初射手","") | U10: =IF('請先閱讀'!$O$31=true,"鼠群之王","") | V10: =IF('請先閱讀'!O35=true,"凜冬陷阱師","") | W10: =IF('請先閱讀'!O36=true,"大獸獵家","")
B11: 魔能騎士 | C11: =IF(OR('角色卡'!AK57="魔能騎士",'角色卡'!BH57="魔能騎士",'角色卡'!CE57="魔能騎士"),'職業能力'!F2,0) -> 0 | E11: 專長 | G11: 盜賊-Rogue | H11: 選擇4項：特技、運動、欺瞞、察言觀色、威嚇、調查、察覺、說服、巧手、隱匿 | K11: 盜賊-Rogue | L11: 詭術師 | M11: 刺客 | N11: 魂刃 | O11: 竊賊 | P11: =IF('請先閱讀'!F31=true,"三神使徒","") -> 三神使徒 | Q11: =IF('請先閱讀'!$O$27=true,"罪人","") | R11: =IF('請先閱讀'!O28=true,"蛛行者","") | S11: =IF('請先閱讀'!$O$30=true,"暗影行者","") | T11: =IF('請先閱讀'!$O$31=true,"響馬","") | U11: =IF('請先閱讀'!$O$31=true,"厄運使者","") | V11: =IF('請先閱讀'!$O$31=true,"嗜血竊賊","") | W11: =IF('請先閱讀'!O35=true,"符文塗鴉客","")
B12: 契 | C12: ='職業能力'!O2 -> 0 | E12: 其他 | G12: 術士-Sorcerer | H12: 選擇2項：奧秘、欺瞞、察言觀色、威嚇、說服、宗教 | K12: 術士-Sorcerer | L12: 畸變術法 | M12: 時械術法 | N12: 龍族術法 | O12: 狂野術法 | P12: =IF('請先閱讀'!F31=true,"咒火術法","") -> 咒火術法 | Q12: =IF('請先閱讀'!$O$27=true,"猩紅術法","") | R12: =IF('請先閱讀'!$O$30=true,"飢渴黑暗術法","") | S12: =IF('請先閱讀'!$O$31=true,"天啟術法","") | T12: =IF('請先閱讀'!$O$31=true,"幽靈術法","") | U12: =IF('請先閱讀'!$O$31=true,"悲慘血脈術法","") | V12: =IF('請先閱讀'!O35=true,"霜凍術法","")
B13: 施法等級 | C13: =C3+C4+C5+C6+C7+ROUNDUP(C8/2+C9/2+C15/2,0)+ROUNDUP((C10+C11+C16)/3,0) -> 3 | G13: 契術師-Warlock | H13: 選擇2項：奧秘、欺瞞、歷史、威嚇、調查、自然、宗教 | K13: 契術師-Warlock | L13: 至高妖精宗主 | M13: 天界宗主 | N13: 邪魔宗主 | O13: 舊日支配者宗主 | P13: =IF('請先閱讀'!$O$27=true,"愚神宗主","") | Q13: =IF('請先閱讀'!$O$27=true,"角之王宗主","") | R13: =IF('請先閱讀'!O28=true,"未來的你宗主","") | S13: =IF('請先閱讀'!$O$30=true,"崇高貓貓庭宗主","") | T13: =IF('請先閱讀'!$O$31=true,"鬼婆集會宗主","") | U13: =IF('請先閱讀'!$O$31=true,"吸血鬼先祖宗主","") | V13: =IF('請先閱讀'!$O$31=true,"宇宙寄生體宗主","") | W13: =IF('請先閱讀'!O35=true,"星界獅鷲獸宗主","")
B14: 契約魔法等級 | C14: =C12 -> 0 | G14: 法師-Wizard | H14: 選擇2項：奧秘、歷史、察言觀色、調查、醫藥、自然、宗教 | K14: 法師-Wizard | L14: 防護師 | M14: 預言師 | N14: 塑能師 | O14: 幻術師 | P14: =IF('請先閱讀'!F31=true,"劍詠師","") -> 劍詠師 | Q14: =IF('請先閱讀'!$O$27=true,"神祕學家","") | R14: =IF('請先閱讀'!$O$27=true,"賢者","") | S14: =IF('請先閱讀'!$O$30=true,"司書","") | T14: =IF('請先閱讀'!$O$31=true,"惡魔學家","") | U14: =IF('請先閱讀'!$O$31=true,"疫醫","") | V14: =IF('請先閱讀'!$O$31=true,"操血師","") | W14: =IF('請先閱讀'!O35=true,"塑形師","")
B15: 奇械師 | C15: ='職業能力'!A2 -> 0 | G15: 奇械師-Artificer | H15: 選擇2項：奧秘、歷史、調查、醫藥、自然、察覺、巧手 | K15: 奇械師-Artificer | L15: 煉金匠 | M15: 裝甲匠 | N15: 魔炮匠 | O15: 戰地工匠 | P15: 製圖匠 | Q15: =IF('請先閱讀'!$O$33=true,"鍛造匠","") | R15: =IF('請先閱讀'!$O$33=true,"獨行匠","")
B16: 咒槍客 | C16: =IF(OR('角色卡'!AK57="咒槍客",'角色卡'!BH57="咒槍客",'角色卡'!CE57="咒槍客"),'職業能力'!G2,0) -> 0 | G16: 銃士-Gunslinger | H16: 選擇2項：特技、動物馴服、運動、欺瞞、察言觀色、威嚇、察覺、說服、巧手、隱匿 | K16: 銃士-Gunslinger | L16: 銳眼客 | M16: 豪賭客 | N16: 密間客 | O16: 咒槍客 | P16: 花槍客 | Q16: 白帽客
B17: 神祕學家公會 | C17: =IF(OR('角色卡'!AK57=N17,'角色卡'!BH57=N17,'角色卡'!CE57=N17),'職業能力'!I2,0) -> 0 | G17: 怪物獵人-Monster Hunter | H17: 選擇3項：運動、歷史、調查、醫藥、自然、察覺、宗教、求生 | K17: 怪物獵人-Monster Hunter | L17: 肢解者公會 | M17: 吞噬者公會 | N17: 神祕學家公會 | O17: 捕獸者公會
G18: 拳鬥士-Pugilist | H18: 選擇2項：特技、運動、欺瞞、威嚇、察覺、巧手、隱匿 | K18: 拳鬥士-Pugilist | L18: 狗與獵犬 | M18: 恐懼之手 | N18: 粗鄙之人 | O18: 擂台摔角 | P18: 街頭聖徒 | Q18: 甜蜜科學
B20: 職業Ⅰ子職 | C20: 職業Ⅱ子職 | D20: 職業Ⅲ子職 | F20: 職業Ⅰ能力 | G20: 職業Ⅱ能力 | H20: 職業Ⅲ能力 | J20: 職業Ⅰ子職能力 | K20: 職業Ⅱ子職能力 | L20: 職業Ⅲ子職能力 | N20: 物種血脈 | O20: 物種血脈列表
B21: =ifna(VLOOKUP('角色卡'!$AB16,$K$3:$X$18,2,false),"") -> 防護師 | C21: =ifna(VLOOKUP('角色卡'!$AB17,$K$3:$X$18,2,false),"") | D21: =ifna(VLOOKUP('角色卡'!$AB18,$K$3:$X$18,2,false),"") | F21: =ifna(HLOOKUP('角色卡'!AB16,'職業能力'!$A$1:$P$21,3,false),"") -> 施法 | G21: =ifna(HLOOKUP('角色卡'!AB17,'職業能力'!$A$1:$P$21,3,false),"") | H21: =ifna(HLOOKUP('角色卡'!$AB$18,'職業能力'!$A$1:$P$21,3,false),"") | J21: =IFNA(VLOOKUP('角色卡'!$AK$57,'子職業能力'!$B$2:$J$291,2,FALSE),"") -> 劍歌 | K21: =IFNA(VLOOKUP('角色卡'!$BH$57,'子職業能力'!$B$2:$J$291,2,FALSE),"") | L21: =IFNA(VLOOKUP('角色卡'!$CE$57,'子職業能力'!$B$2:$J$291,2,FALSE),"") | N21: =IFNA(VLOOKUP('角色卡'!$Y$7,$O$21:$Y$31,2,FALSE),"") | O21: 龍裔 Dragonborn | P21: 黑龍 Black | Q21: 藍龍 Blue | R21: 綠龍 Green | S21: 紅龍 Red | T21: 白龍 White | U21: 金龍 Gold | V21: 銀龍 Silver | W21: 黃銅龍 Brass | X21: 青銅龍 Bronze | Y21: 赤銅龍 Copper
B22: =ifna(VLOOKUP('角色卡'!$AB16,$K$3:$X$18,3,false),"") -> 預言師 | C22: =ifna(VLOOKUP('角色卡'!$AB17,$K$3:$X$18,3,false),"") | D22: =ifna(VLOOKUP('角色卡'!$AB18,$K$3:$X$18,3,false),"") | F22: =ifna(HLOOKUP('角色卡'!AB16,'職業能力'!$A$1:$P$21,4,false),"") -> 儀式學家 | G22: =ifna(HLOOKUP('角色卡'!AB17,'職業能力'!$A$1:$P$21,4,false),"") | H22: =ifna(HLOOKUP('角色卡'!$AB$18,'職業能力'!$A$1:$P$21,4,false),"") | J22: =IFNA(VLOOKUP('角色卡'!$AK$57,'子職業能力'!$B$2:$J$291,3,FALSE),"") -> 戰歌訓練 | K22: =IFNA(VLOOKUP('角色卡'!$BH$57,'子職業能力'!$B$2:$J$291,3,FALSE),"") | L22: =IFNA(VLOOKUP('角色卡'!$CE$57,'子職業能力'!$B$2:$J$291,3,FALSE),"") | N22: =IFNA(VLOOKUP('角色卡'!$Y$7,$O$21:$Y$31,3,FALSE),"") | O22: 精靈 Elf | P22: 卓爾 Drow | Q22: 高等精靈 High Elf | R22: 木精靈 Wood Elf | S22: =if('請先閱讀'!F32=true,"格溫精靈 Lorwyn Elf","") -> 格溫精靈 Lorwyn Elf | T22: =if('請先閱讀'!F32=true,"暗影荒原精靈 Shadowmoor Elf","") -> 暗影荒原精靈 Shadowmoor Elf
B23: =ifna(VLOOKUP('角色卡'!$AB16,$K$3:$X$18,4,false),"") -> 塑能師 | C23: =ifna(VLOOKUP('角色卡'!$AB17,$K$3:$X$18,4,false),"") | D23: =ifna(VLOOKUP('角色卡'!$AB18,$K$3:$X$18,4,false),"") | F23: =ifna(HLOOKUP('角色卡'!AB16,'職業能力'!$A$1:$P$21,5,false),"") -> 奧術恢復(2個環位) | G23: =ifna(HLOOKUP('角色卡'!AB17,'職業能力'!$A$1:$P$21,5,false),"") | H23: =ifna(HLOOKUP('角色卡'!$AB$18,'職業能力'!$A$1:$P$21,5,false),"") | J23: =IFNA(VLOOKUP('角色卡'!$AK$57,'子職業能力'!$B$2:$J$291,4,FALSE),"") | K23: =IFNA(VLOOKUP('角色卡'!$BH$57,'子職業能力'!$B$2:$J$291,4,FALSE),"") | L23: =IFNA(VLOOKUP('角色卡'!$CE$57,'子職業能力'!$B$2:$J$291,4,FALSE),"") | N23: =IFNA(VLOOKUP('角色卡'!$Y$7,$O$21:$Y$31,4,FALSE),"") | O23: 地侏 Gnome | P23: 林地侏 Forest Gnome | Q23: 岩地侏 Rock Gnome
B24: =ifna(VLOOKUP('角色卡'!$AB16,$K$3:$X$18,5,false),"") -> 幻術師 | C24: =ifna(VLOOKUP('角色卡'!$AB17,$K$3:$X$18,5,false),"") | D24: =ifna(VLOOKUP('角色卡'!$AB18,$K$3:$X$18,5,false),"") | F24: =ifna(HLOOKUP('角色卡'!AB16,'職業能力'!$A$1:$P$21,6,false),"") -> 學者 | G24: =ifna(HLOOKUP('角色卡'!AB17,'職業能力'!$A$1:$P$21,6,false),"") | H24: =ifna(HLOOKUP('角色卡'!$AB$18,'職業能力'!$A$1:$P$21,6,false),"") | J24: =IFNA(VLOOKUP('角色卡'!$AK$57,'子職業能力'!$B$2:$J$291,5,FALSE),"") | K24: =IFNA(VLOOKUP('角色卡'!$BH$57,'子職業能力'!$B$2:$J$291,5,FALSE),"") | L24: =IFNA(VLOOKUP('角色卡'!$CE$57,'子職業能力'!$B$2:$J$291,5,FALSE),"") | N24: =IFNA(VLOOKUP('角色卡'!$Y$7,$O$21:$Y$31,5,FALSE),"") | O24: 歌利亞 Goliath | P24: 雲巨人 Cloud Giant | Q24: 火巨人 Fire Giant | R24: 霜巨人 Frost Giant | S24: 山丘巨人 Hill Giant | T24: 石巨人 Stone Giant | U24: 風暴巨人 Storm Giant
B25: =ifna(VLOOKUP('角色卡'!$AB16,$K$3:$X$18,6,false),"") -> 劍詠師 | C25: =ifna(VLOOKUP('角色卡'!$AB17,$K$3:$X$18,6,false),"") | D25: =ifna(VLOOKUP('角色卡'!$AB18,$K$3:$X$18,6,false),"") | F25: =ifna(HLOOKUP('角色卡'!AB16,'職業能力'!$A$1:$P$21,7,false),"") | G25: =ifna(HLOOKUP('角色卡'!AB17,'職業能力'!$A$1:$P$21,7,false),"") | H25: =ifna(HLOOKUP('角色卡'!$AB$18,'職業能力'!$A$1:$P$21,7,false),"") | J25: =IFNA(VLOOKUP('角色卡'!$AK$57,'子職業能力'!$B$2:$J$291,6,FALSE),"") | K25: =IFNA(VLOOKUP('角色卡'!$BH$57,'子職業能力'!$B$2:$J$291,6,FALSE),"") | L25: =IFNA(VLOOKUP('角色卡'!$CE$57,'子職業能力'!$B$2:$J$291,6,FALSE),"") | N25: =IFNA(VLOOKUP('角色卡'!$Y$7,$O$21:$Y$31,6,FALSE),"") | O25: 提夫林 Tiefling | P25: 深淵 Abyssal | Q25: 幽冥 Chthonic | R25: 煉獄 Infernal
B26: =ifna(VLOOKUP('角色卡'!$AB16,$K$3:$X$18,7,false),"") | C26: =ifna(VLOOKUP('角色卡'!$AB17,$K$3:$X$18,7,false),"") | D26: =ifna(VLOOKUP('角色卡'!$AB18,$K$3:$X$18,7,false),"") | F26: =ifna(HLOOKUP('角色卡'!AB16,'職業能力'!$A$1:$P$21,8,false),"") | G26: =ifna(HLOOKUP('角色卡'!AB17,'職業能力'!$A$1:$P$21,8,false),"") | H26: =ifna(HLOOKUP('角色卡'!$AB$18,'職業能力'!$A$1:$P$21,8,false),"") | J26: =IFNA(VLOOKUP('角色卡'!$AK$57,'子職業能力'!$B$2:$J$291,7,FALSE),"") | K26: =IFNA(VLOOKUP('角色卡'!$BH$57,'子職業能力'!$B$2:$J$291,7,FALSE),"") | L26: =IFNA(VLOOKUP('角色卡'!$CE$57,'子職業能力'!$B$2:$J$291,7,FALSE),"") | N26: =IFNA(VLOOKUP('角色卡'!$Y$7,$O$21:$Y$31,7,FALSE),"") | O26: 仙靈 Faerie | P26: =if('請先閱讀'!F32=true,"格溫 Lorwyn","") -> 格溫 Lorwyn | Q26: =if('請先閱讀'!F32=true,"暗影荒原 Shadowmoor","") -> 暗影荒原 Shadowmoor
B27: =ifna(VLOOKUP('角色卡'!$AB16,$K$3:$X$18,8,false),"") | C27: =ifna(VLOOKUP('角色卡'!$AB17,$K$3:$X$18,8,false),"") | D27: =ifna(VLOOKUP('角色卡'!$AB18,$K$3:$X$18,8,false),"") | F27: =ifna(HLOOKUP('角色卡'!AB16,'職業能力'!$A$1:$P$21,9,false),"") | G27: =ifna(HLOOKUP('角色卡'!AB17,'職業能力'!$A$1:$P$21,9,false),"") | H27: =ifna(HLOOKUP('角色卡'!$AB$18,'職業能力'!$A$1:$P$21,9,false),"") | J27: =IFNA(VLOOKUP('角色卡'!$AK$57,'子職業能力'!$B$2:$J$291,8,FALSE),"") | K27: =IFNA(VLOOKUP('角色卡'!$BH$57,'子職業能力'!$B$2:$J$291,8,FALSE),"") | L27: =IFNA(VLOOKUP('角色卡'!$CE$57,'子職業能力'!$B$2:$J$291,8,FALSE),"") | N27: =IFNA(VLOOKUP('角色卡'!$Y$7,$O$21:$Y$31,8,FALSE),"") | O27: 潔英 Kithkin | P27: =if('請先閱讀'!F32=true,"格溫 Lorwyn","") -> 格溫 Lorwyn | Q27: =if('請先閱讀'!F32=true,"暗影荒原 Shadowmoor","") -> 暗影荒原 Shadowmoor
B28: =ifna(VLOOKUP('角色卡'!$AB$16,$K$3:$X$18,9,false),"") | C28: =ifna(VLOOKUP('角色卡'!$AB$17,$K$3:$X$18,9,false),"") | D28: =ifna(VLOOKUP('角色卡'!$AB$18,$K$3:$X$18,9,false),"") | F28: =ifna(HLOOKUP('角色卡'!AB16,'職業能力'!$A$1:$P$21,10,false),"") | G28: =ifna(HLOOKUP('角色卡'!AB17,'職業能力'!$A$1:$P$21,10,false),"") | H28: =ifna(HLOOKUP('角色卡'!$AB$18,'職業能力'!$A$1:$P$21,10,false),"") | J28: =IFNA(VLOOKUP('角色卡'!$AK$57,'子職業能力'!$B$2:$J$291,9,FALSE),"") | K28: =IFNA(VLOOKUP('角色卡'!$BH$57,'子職業能力'!$B$2:$J$291,9,FALSE),"") | L28: =IFNA(VLOOKUP('角色卡'!$CE$57,'子職業能力'!$B$2:$J$291,9,FALSE),"") | N28: =IFNA(VLOOKUP('角色卡'!$Y$7,$O$21:$Y$31,9,FALSE),"") | O28: 吉佩廷 Geppettin | P28: 瓷娃娃 Bisque | Q28: 傀儡 Marionette | R28: 絨毛玩具 Plushie
B29: =ifna(VLOOKUP('角色卡'!$AB16,$K$3:$X$18,10,false),"") | C29: =ifna(VLOOKUP('角色卡'!$AB17,$K$3:$X$18,10,false),"") | D29: =ifna(VLOOKUP('角色卡'!$AB18,$K$3:$X$18,10,false),"") | F29: =ifna(HLOOKUP('角色卡'!AB16,'職業能力'!$A$1:$P$21,11,false),"") | G29: =ifna(HLOOKUP('角色卡'!AB17,'職業能力'!$A$1:$P$21,11,false),"") | H29: =ifna(HLOOKUP('角色卡'!$AB$18,'職業能力'!$A$1:$P$21,11,false),"") | N29: =IFNA(VLOOKUP('角色卡'!$Y$7,$O$21:$Y$31,10,FALSE),"") | O29: 曼德拉 Mandrake | P29: 春季 Spring | Q29: 夏季 Summer | R29: 秋季 Autumn | S29: 冬季 Winter
B30: =ifna(VLOOKUP('角色卡'!$AB$16,$K$3:$X$18,11,false),"") | C30: =ifna(VLOOKUP('角色卡'!$AB$17,$K$3:$X$18,11,false),"") | D30: =ifna(VLOOKUP('角色卡'!$AB$18,$K$3:$X$18,11,false),"") | F30: =ifna(HLOOKUP('角色卡'!AB16,'職業能力'!$A$1:$P$21,12,false),"") | G30: =ifna(HLOOKUP('角色卡'!AB17,'職業能力'!$A$1:$P$21,12,false),"") | H30: =ifna(HLOOKUP('角色卡'!$AB$18,'職業能力'!$A$1:$P$21,12,false),"") | N30: =IFNA(VLOOKUP('角色卡'!$Y$7,$O$21:$Y$31,11,FALSE),"") | O30: 阿斯莫 Aasimar | P30: 費尼亞 Fernian | Q30: 瑪巴爾 Mabaran
B31: =ifna(VLOOKUP('角色卡'!$AB$16,$K$3:$X$18,12,false),"") | C31: =ifna(VLOOKUP('角色卡'!$AB$17,$K$3:$X$18,12,false),"") | D31: =ifna(VLOOKUP('角色卡'!$AB$18,$K$3:$X$18,12,false),"") | F31: =ifna(HLOOKUP('角色卡'!AB16,'職業能力'!$A$1:$P$21,13,false),"") | G31: =ifna(HLOOKUP('角色卡'!AB17,'職業能力'!$A$1:$P$21,13,false),"") | H31: =ifna(HLOOKUP('角色卡'!$AB$18,'職業能力'!$A$1:$P$21,13,false),"") | O31: 羽裔 Feathren | P31: (太麻煩了自己填吧)
B32: =ifna(VLOOKUP('角色卡'!$AB$16,$K$3:$X$18,13,false),"") | C32: =ifna(VLOOKUP('角色卡'!$AB$17,$K$3:$X$18,13,false),"") | D32: =ifna(VLOOKUP('角色卡'!$AB$18,$K$3:$X$18,13,false),"") | F32: =ifna(HLOOKUP('角色卡'!AB16,'職業能力'!$A$1:$P$21,14,false),"") | G32: =ifna(HLOOKUP('角色卡'!AB17,'職業能力'!$A$1:$P$21,14,false),"") | H32: =ifna(HLOOKUP('角色卡'!$AB$18,'職業能力'!$A$1:$P$21,14,false),"") | J32: DC | K32: 命中 | L32: 調整值
B33: =ifna(VLOOKUP('角色卡'!$AB$16,$K$3:$X$18,14,false),"") | C33: =ifna(VLOOKUP('角色卡'!$AB$17,$K$3:$X$18,14,false),"") | D33: =ifna(VLOOKUP('角色卡'!$AB$18,$K$3:$X$18,14,false),"") | F33: =ifna(HLOOKUP('角色卡'!AB16,'職業能力'!$A$1:$P$21,15,false),"") | G33: =ifna(HLOOKUP('角色卡'!AB17,'職業能力'!$A$1:$P$21,15,false),"") | H33: =ifna(HLOOKUP('角色卡'!$AB$18,'職業能力'!$A$1:$P$21,15,false),"") | J33: =IFNA(VLOOKUP('角色卡'!$BW33,'角色卡'!$C$15:$L$20,8,FALSE)+'角色卡'!$C$47+'角色卡'!$BZ33+8,"") -> 13 | K33: =IFNA(VLOOKUP('角色卡'!$BW33,'角色卡'!$C$15:$L$20,8,FALSE)+'角色卡'!$C$47+'角色卡'!$BZ33,"") -> 5 | L33: =IFNA(VLOOKUP('角色卡'!$BW33,'角色卡'!$C$15:$L$20,8,FALSE)+'角色卡'!$BZ33,"") -> 3
F34: =ifna(HLOOKUP('角色卡'!AB16,'職業能力'!$A$1:$P$21,16,false),"") | G34: =ifna(HLOOKUP('角色卡'!AB17,'職業能力'!$A$1:$P$21,16,false),"") | H34: =ifna(HLOOKUP('角色卡'!$AB$18,'職業能力'!$A$1:$P$21,16,false),"") | J34: =IFNA(VLOOKUP('角色卡'!$BW34,'角色卡'!$C$15:$L$20,8,FALSE)+'角色卡'!$C$47+'角色卡'!$BZ34+8,"") | K34: =IFNA(VLOOKUP('角色卡'!$BW34,'角色卡'!$C$15:$L$20,8,FALSE)+'角色卡'!$C$47+'角色卡'!$BZ34,"") | L34: =IFNA(VLOOKUP('角色卡'!$BW34,'角色卡'!$C$15:$L$20,8,FALSE)+'角色卡'!$BZ34,"")
F35: =ifna(HLOOKUP('角色卡'!AB16,'職業能力'!$A$1:$P$21,17,false),"") | G35: =ifna(HLOOKUP('角色卡'!AB17,'職業能力'!$A$1:$P$21,17,false),"") | H35: =ifna(HLOOKUP('角色卡'!$AB$18,'職業能力'!$A$1:$P$21,17,false),"") | J35: =IFNA(VLOOKUP('角色卡'!$BW35,'角色卡'!$C$15:$L$20,8,FALSE)+'角色卡'!$C$47+'角色卡'!$BZ35+8,"") | K35: =IFNA(VLOOKUP('角色卡'!$BW35,'角色卡'!$C$15:$L$20,8,FALSE)+'角色卡'!$C$47+'角色卡'!$BZ35,"") | L35: =IFNA(VLOOKUP('角色卡'!$BW35,'角色卡'!$C$15:$L$20,8,FALSE)+'角色卡'!$BZ35,"")
F36: =ifna(HLOOKUP('角色卡'!AB16,'職業能力'!$A$1:$P$21,18,false),"") | G36: =ifna(HLOOKUP('角色卡'!AB17,'職業能力'!$A$1:$P$21,18,false),"") | H36: =ifna(HLOOKUP('角色卡'!$AB$18,'職業能力'!$A$1:$P$21,18,false),"")
F37: =ifna(HLOOKUP('角色卡'!AB16,'職業能力'!$A$1:$P$21,19,false),"") | G37: =ifna(HLOOKUP('角色卡'!AB17,'職業能力'!$A$1:$P$21,19,false),"") | H37: =ifna(HLOOKUP('角色卡'!$AB$18,'職業能力'!$A$1:$P$21,19,false),"") | J37: 召喚物熟練項 | K37: 物種索引
F38: =ifna(HLOOKUP('角色卡'!AB16,'職業能力'!$A$1:$P$21,20,false),"") | G38: =ifna(HLOOKUP('角色卡'!AB17,'職業能力'!$A$1:$P$21,20,false),"") | H38: =ifna(HLOOKUP('角色卡'!$AB$18,'職業能力'!$A$1:$P$21,20,false),"") | J38: =IFNA(VLOOKUP('坐騎召喚物'!C3,'召喚物資料'!B3:Z1003,25,FALSE),"") | K38: =LEFT('角色卡'!Y7,3) -> 人類
B40: 魔能祈喚 | D40: 召喚物類型 | E40: 召喚物 | F40: 召喚物法術列表 | L40: 工匠工具熟練項
B41: =IF($C$12>=2,"痛苦衝擊","") | D41: =IFNA(VLOOKUP('坐騎召喚物'!M4,F41:J67,2,FALSE),"") | F41: 坐騎 | L41: 樂器(通用) | M41: 魅力
B42: 暗影護甲 | D42: =IFNA(VLOOKUP('坐騎召喚物'!M4,F41:J67,3,FALSE),"") | F42: 尋獲魔寵 | L42: 煉金工具 | M42: 智力
B43: =IF($C$12>=5,"躍升步伐","") | D43: =IFNA(VLOOKUP('坐騎召喚物'!M4,F41:J67,4,FALSE),"") | E43: =IF('坐騎召喚物'!$M$4="尋獲魔寵",IF(COUNTIF('職業能力選項'!$BE$3:$BE$12,"鎖鏈魔契")>0,'魔寵資料'!$B4,""),IF('坐騎召喚物'!$M$4="坐騎",'坐騎資料'!B4,"異界坐騎")) -> 異界坐騎 | F43: 尋獲坐騎 | G43: 天界生物Celestials | H43: 精類Fey | I43: 邪魔Fiends | L43: 釀酒工具 | M43: 智力
B44: =IF($C$12>=2,"魔鬼視覺","") | D44: =IFNA(VLOOKUP('坐騎召喚物'!M4,F41:J67,5,FALSE),"") | E44: =IF('坐騎召喚物'!$M$4="尋獲魔寵",IF(COUNTIF('職業能力選項'!$BE$3:$BE$12,"鎖鏈魔契")>0,'魔寵資料'!$B5,""),IF('坐騎召喚物'!$M$4="坐騎",'坐騎資料'!B5,"原初動物夥伴")) -> 原初動物夥伴 | F44: 獸王遊俠 | G44: 大地野獸Beast of the Land | H44: 海洋野獸Beast of the Sea | I44: 天空野獸Beast of the Sky | L44: 書法工具 | M44: 敏捷
B45: =IF(AND($C$12>=12,COUNTIF('職業能力選項'!BE3:BE12,B65)>0),"滅世鋒刃","") | E45: =IF('坐騎召喚物'!$M$4="尋獲魔寵",IF(COUNTIF('職業能力選項'!$BE$3:$BE$12,"鎖鏈魔契")>0,'魔寵資料'!$B6,""),IF('坐騎召喚物'!$M$4="坐騎",'坐騎資料'!B6,"野獸精魂")) -> 野獸精魂 | F45: 野獸召喚術 | G45: 天空Air | H45: 大地Land | I45: 海洋Water | L45: 木匠工具 | M45: 力量
B46: 魔能意志 | E46: =IF('坐騎召喚物'!$M$4="尋獲魔寵",IF(COUNTIF('職業能力選項'!$BE$3:$BE$12,"鎖鏈魔契")>0,'魔寵資料'!$B2,""),IF('坐騎召喚物'!$M$4="坐騎",'坐騎資料'!B2,"殭屍")) -> 殭屍 | F46: 活化死屍 | L46: 製圖工具 | M46: 感知
B47: =IF(AND($C$12>=5,COUNTIF('職業能力選項'!BE3:BE12,B61)>0),"魔能重斬","") | E47: =IF('坐騎召喚物'!$M$4="尋獲魔寵",IF(COUNTIF('職業能力選項'!$BE$3:$BE$12,"鎖鏈魔契")>0,'魔寵資料'!$B3,""),IF('坐騎召喚物'!$M$4="坐騎",'坐騎資料'!B3,"骷髏")) -> 骷髏 | L47: 鞋匠工具 | M47: 敏捷
B48: =IF($C$12>=2,"魔能之矛","") | E48: =IF('坐騎召喚物'!$M$4="尋獲魔寵",IF(COUNTIF('職業能力選項'!$BE$3:$BE$12,"鎖鏈魔契")>0,'魔寵資料'!$B8,""),IF('坐騎召喚物'!$M$4="坐騎",'坐騎資料'!B8,"妖精精魂")) -> 妖精精魂 | F48: 精類召喚術 | G48: 盛怒妖精Fuming | H48: 歡愉妖精Mirthful | I48: 詭詐妖精Tricksy | L48: 廚師工具 | M48: 感知
B49: =IF($C$12>=2,"邪魔活力","") | E49: =IF('坐騎召喚物'!$M$4="尋獲魔寵",IF(COUNTIF('職業能力選項'!$BE$3:$BE$12,"鎖鏈魔契")>0,'魔寵資料'!$B9,""),IF('坐騎召喚物'!$M$4="坐騎",'坐騎資料'!B9,"亡靈精魂")) -> 亡靈精魂 | F49: 不死生物召喚術 | G49: 幽魂Ghostly | H49: 腐屍Putrid | I49: 骷髏Skeletal | L49: 玻璃匠工具 | M49: 智力
B50: =IF($C$12>=5,"聯心之視","") | E50: =IF('坐騎召喚物'!$M$4="尋獲魔寵",'魔寵資料'!B10,IF('坐騎召喚物'!$M$4="坐騎",'坐騎資料'!B10,"巨蟲")) -> 巨蟲 | F50: 巨蟲術 | G50: 蜈蚣Centipede | H50: 蜘蛛Spider | I50: 黃蜂Wasp | L50: 珠寶匠工具 | M50: 智力
B51: =IF($C$12>=5,"深海餽贈","") | E51: =IF('坐騎召喚物'!$M$4="尋獲魔寵",'魔寵資料'!B11,IF('坐騎召喚物'!$M$4="坐騎",'坐騎資料'!B11,"異怪精魂")) -> 異怪精魂 | F51: 異怪召喚術 | G51: 眼魔Beholderkin | H51: 奪心魔Mind Flayer | I51: 史拉蟾Slaad | L51: 皮匠工具 | M51: 敏捷
B52: =IF(AND($C$12>=9,COUNTIF('職業能力選項'!BE3:BE12,B63)>0),"守護饋贈","") | E52: =IF('坐騎召喚物'!$M$4="尋獲魔寵",'魔寵資料'!B12,IF('坐騎召喚物'!$M$4="坐騎",'坐騎資料'!B12,"構裝精魂")) -> 構裝精魂 | F52: 構裝體召喚術 | G52: 黏土魔偶Clay | H52: 金屬魔偶Metal | I52: 岩石魔偶Stone | L52: 石匠工具 | M52: 力量
B53: =IF(AND($C$12>=5,COUNTIF('職業能力選項'!$BE$3:$BE$12,B62)>0),"鏈主賦能","") | E53: =IF('坐騎召喚物'!$M$4="尋獲魔寵",'魔寵資料'!B13,IF('坐騎召喚物'!$M$4="坐騎",'坐騎資料'!B13,"元素精魂")) -> 元素精魂 | F53: 元素召喚術 | G53: 氣元素Air | H53: 土元素Earth | I53: 火元素Fire | J53: 水元素Water | L53: 畫家工具 | M53: 感知
B54: =IF($C$12>=2,"原初的第一課","") | E54: =IF('坐騎召喚物'!$M$4="尋獲魔寵",'魔寵資料'!B14,IF('坐騎召喚物'!$M$4="坐騎",'坐騎資料'!B14,"活化物體")) -> 活化物體 | F54: 活化物體 | G54: 巨型 | H54: 大型Large | I54: 中型或更小Medium or smaller | L54: 陶匠工具 | M54: 智力
B55: =IF(AND($C$12>=9,COUNTIF('職業能力選項'!$BE$3:$BE$12,B61)>0),"飲命者","") | E55: =IF('坐騎召喚物'!$M$4="尋獲魔寵",'魔寵資料'!B15,IF('坐騎召喚物'!$M$4="坐騎",'坐騎資料'!B15,"天界精魂")) -> 天界精魂 | F55: 天界生物召喚術 | G55: 復仇聖靈Avenger | H55: 守護聖靈Defender | L55: 鐵匠工具 | M55: 力量
B56: =IF($C$12>=2,"千面之臉","") | E56: =IF('坐騎召喚物'!$M$4="尋獲魔寵",'魔寵資料'!B16,IF('坐騎召喚物'!$M$4="坐騎",'坐騎資料'!B16,"龍族精魂")) -> 龍族精魂 | F56: 龍族召喚術 | L56: 修補工具 | M56: 敏捷
B57: =IF($C$12>=5,"萬形之主","") | E57: =IF('坐騎召喚物'!$M$4="尋獲魔寵",'魔寵資料'!B17,IF('坐騎召喚物'!$M$4="坐騎",'坐騎資料'!B17,"邪魔精魂")) -> 邪魔精魂 | F57: 邪魔召喚術 | G57: 惡魔Demon | H57: 魔鬼Devil | I57: 尤格羅斯魔Yugoloth | L57: 織布工具 | M57: 敏捷
B58: =IF($C$12>=2,"迷霧幻影","") | E58: 魔能火炮 | F58: 奇械師魔炮匠 | L58: 木雕工具 | M58: 敏捷
B59: =IF($C$12>=5,"融身入影","") | E59: 鋼鐵衛士 | F59: 奇械師戰地工匠 | L59: 易容工具 | M59: 魅力
B60: =IF($C$12>=2,"超凡跳躍","") | E60: =IF('坐騎召喚物'!$M$4="尋獲魔寵",'魔寵資料'!B18,IF('請先閱讀'!F34=true,"人工生命僕從","")) -> 人工生命僕從 | F60: =IF('請先閱讀'!F34=true,"人工生命僕從","") -> 人工生命僕從 | L60: 文書偽造工具 | M60: 敏捷
B61: 鋒刃魔契 | E61: =IF('坐騎召喚物'!$M$4="尋獲魔寵",'魔寵資料'!B19,IF('請先閱讀'!O31=true,"植物精魂","")) | F61: =IF('請先閱讀'!O31=true,"植物召喚術","") | G61: 繁花Blooming | H61: 橡木Oaken | I61: 荊棘Thorny | L61: 草藥工具 | M61: 智力
B62: 鎖鏈魔契 | E62: =IF('坐騎召喚物'!$M$4="尋獲魔寵",'魔寵資料'!B20,IF('請先閱讀'!O31=true,"海蛇精魂","")) | F62: =IF('請先閱讀'!O31=true,"深海精魂召喚術","") | G62: 巨口Enormous Mouth | H62: 發光燈籠Glowing Lantern | I62: 鱗翼Scaled Wings | L62: 領航工具 | M62: 感知
B63: 書卷魔契 | E63: =IF('請先閱讀'!O31=true,"血肉構裝體","") | F63: =IF('請先閱讀'!O31=true,"血肉剝離","") | L63: 製毒工具 | M63: 智力
B64: =IF($C$12>=2,"斥力衝擊","") | E64: =IF('請先閱讀'!O31=true,"害獸群","") | F64: =IF('請先閱讀'!O31=true,"鼠群之王遊俠","") | L64: 竊賊工具 | M64: 敏捷
B65: =IF(AND($C$12>=5,COUNTIF('職業能力選項'!$BE$3:$BE$12,B61)>0),"飢渴鋒刃","") | E65: =IF('請先閱讀'!O31=true,"原初守護者","") | F65: =IF('請先閱讀'!O31=true,"野蠻人原初精魂","") | G65: 天空Air | H65: 大地Land | I65: 海洋Water | L65: 賭具(通用) | M65: 感知
B66: =IF($C$12>=9,"穹宇盡視","") | E66: =IF('請先閱讀'!O31=true,"原初打擊者","") | L66: =IF('請先閱讀'!$O$30=true,"指紋採集工具","") | M66: 智力
B67: =IF($C$12>=7,"墳墓低語","") | E67: =IF('請先閱讀'!$O$30=true,"暗影精魂","") | F67: =IF('請先閱讀'!$O$30=true,"暗影召喚術","") | G67: 滲透者Infiltrator | H67: 暗殺者Assassin | L67: =IF('請先閱讀'!$O$30=true,"通靈版","") | M67: 魅力
B68: =IF($C$12>=11,"巫者視界","") | E68: 拳師獵犬 | F68: 拳師狗與獵犬

Sheet 物種
A1: 物種 | B1: 出處 | C1: 體型 | D1: 生物類型 | E1: 能力A | F1: 能力B | G1: 能力C | H1: 能力D | I1: 能力E | J1: 能力F | K1: 能力G | L1: 能力H
A2: 阿斯莫 Aasimar | B2: PHB | C2: 中型 | D2: 類人生物 | E2: 黑暗視覺 Darkvision | F2: =IF('角色卡'!$AP$7='索引資料'!P30,"費尼亞抗性 Fernian Resistance","天界抗性 Celestial Resistance") -> 天界抗性 Celestial Resistance | G2: 治癒之手 Healing Hands | H2: =IF('角色卡'!$AP$7='索引資料'!P30,"烈火掌者 Fire Bearer",IF('角色卡'!$AP$7='索引資料'!Q30,"亡者高呼 Herald of Death","光輝掌者 Light Bearer")) -> 光輝掌者 Light Bearer | I2: 天界啟示 Celestical Revelation
A3: 龍裔 Dragonborn | B3: PHB | C3: 中型 | D3: 類人生物 | E3: 黑暗視覺 Darkvision | F3: ="龍族血統："&'角色卡'!AP7&" Draconic Ancestry" -> 龍族血統： Draconic Ancestry | G3: 吐息武器 Breath Weapon | H3: 傷害抗性 Damage Resistance | I3: 龍族飛翼 Draconic Flight
A4: 矮人 Dwarf | B4: PHB | C4: 中型 | D4: 類人生物 | E4: 黑暗視覺 Darkvision | F4: 矮人體魄 Dwarven Resilience | G4: 矮人剛毅 Dwarven Toughness | H4: 岩石敏銳 Stonecunning
A5: 精靈 Elf | B5: PHB | C5: 中型 | D5: 類人生物 | E5: 黑暗視覺 Darkvision | F5: ="精靈血脈："&'角色卡'!AP7&" Elven Lineage" -> 精靈血脈： Elven Lineage | G5: 精類血統 Fey Ancestry | H5: 敏銳感官 Keen Senses | I5: 傳思 Trance
A6: 地侏 Gnome | B6: PHB | C6: 小型 | D6: 類人生物 | E6: 黑暗視覺 Darkvision | F6: 地侏狡黠 Gnome Cunning | G6: ="地侏血脈："&'角色卡'!AP7&" Elven Lineage" -> 地侏血脈： Elven Lineage
A7: 歌利亞 Goliath | B7: PHB | C7: 中型 | D7: 類人生物 | E7: ="巨人血統："&'角色卡'!AP7&" Giant Ancestry" -> 巨人血統： Giant Ancestry | F7: 大型形態 Large Form | G7: 身強力壯 Powerful Build
A8: 半身人 Halfling | B8: PHB | C8: 小型 | D8: 類人生物 | E8: 勇氣 Brave | F8: 半身人靈巧 Halfling Nimbleness | G8: 幸運 Lucky | H8: 天生善匿 Naturally Stealthy
A9: 人類 Human | B9: PHB | C9: 中型or小型 | D9: 類人生物 | E9: 創造力 Resourceful | F9: 技能熟練 Skillful | G9: 多才多藝 Versatile
A10: 獸人 Orc | B10: PHB | C10: 中型 | D10: 類人生物 | E10: 黑暗視覺 Darkvision | F10: 激昂衝鋒 Adrenaline Rush | G10: 堅韌不屈 Relentless Endurance
A11: 提夫林 Tiefling | B11: PHB | C11: 中型or小型 | D11: 類人生物 | E11: 黑暗視覺 Darkvision | F11: ="邪魔遺贈："&'角色卡'!AP7&" Fiendish Legacy" -> 邪魔遺贈： Fiendish Legacy | G11: 異界存在 Otherworldly Presence
A12: =if('請先閱讀'!F32=true,"博格特 Boggart","") -> 博格特 Boggart | B12: LFL | C12: 小型 | D12: 類人生物 | E12: 黑暗視覺 Darkvision | F12: 精類血統 Fey Ancestry | G12: 小個子怒火 Fury of the Small | H12: 迅捷逃逸 Nimble Escape
A13: =if('請先閱讀'!F32=true,"仙靈 Faerie","") -> 仙靈 Faerie | B13: LFL | C13: 小型 | D13: 精類 | E13: 仙靈魔法 Fairy Magic | F13: 飛行 Flight | G13: =IFNA(IF('角色卡'!AO7='索引資料'!P26,"黑暗視覺 Darkvision",""),"")
A14: =if('請先閱讀'!F32=true,"炎親 Flamekin","") -> 炎親 Flamekin | B14: LFL | C14: 中型or小型 | D14: 類人生物 | E14: 黑暗視覺 Darkvision | F14: 火焰抗性 Fire Resistance | G14: 列焰之觸 Reach to the Blaze
A15: =if('請先閱讀'!F32=true,"潔英 Kithkin","") -> 潔英 Kithkin | B15: LFL | C15: 小型 | D15: 類人生物 | E15: 勇氣 Brave | F15: 半身人靈巧 Halfling Nimbleness | G15: 幸運 Lucky | H15: 天生善匿 Naturally Stealthy | I15: =IFNA(IF('角色卡'!AO7='索引資料'!P27,"黑暗視覺 Darkvision",""),"")
A16: =if('請先閱讀'!F32=true,"洛溫幻身靈 Lorwyn Changeling","") -> 洛溫幻身靈 Lorwyn Changeling | B16: LFL | C16: 中型or小型 | D16: 精類 | E16: 黑暗視覺 Darkvision | F16: 變換自身 Shape Self | G16: 歡笑模仿 Delightful Imitator
A17: =if('請先閱讀'!F32=true,"霜親 Rimekin","") -> 霜親 Rimekin | B17: LFL | C17: 中型or小型 | D17: 類人生物 | E17: 黑暗視覺 Darkvision | F17: 冷燃魔法 Cold Fire Magic | G17: 寒冷抗性 Cold Resistance
A18: =if('請先閱讀'!F33=true,"半血裔 Dhampir","") -> 半血裔 Dhampir | B18: ABoH | C18: 中型or小型 | D18: 類人生物 | E18: 黑暗視覺 Darkvision | F18: 蛛行 Spider Climb | G18: 不死痕跡 Trace of Undeath | H18: 吸血啃咬 Vampiric Bite
A19: =if('請先閱讀'!$F$34=true,"幻身靈 Changeling","") -> 幻身靈 Changeling | B19: EFA | C19: 中型or小型 | D19: 精類 | E19: 幻身靈本能 Changeling Instincts | F19: 變形者 Shape-Shifter
A20: =if('請先閱讀'!$F$34=true,"離夢人 Kalashtar","") -> 離夢人 Kalashtar | B20: EFA | C20: 中型 | D20: 異怪 | E20: 雙重意識 Dual Mind | F20: 心靈紀律 Mental Discipline | G20: 心靈連接 Mind Link | H20: 隔離夢境 Severed from Dreams
A21: =if('請先閱讀'!$F$34=true,"混血精靈 Khoravar","") -> 混血精靈 Khoravar | B21: EFA | C21: 中型or小型 | D21: 類人生物 | E21: 精類血統 Fey Ancestry | F21: 妖精餽贈 Fey Gift | G21: 昏睡韌性 Lethargy Resilience | H21: 才華橫溢 Skill Versatility
A22: =if('請先閱讀'!$F$34=true,"化獸者 Shifter","") -> 化獸者 Shifter | B22: EFA | C22: 中型or小型 | D22: 類人生物 | E22: 黑暗視覺 Darkvision | F22: 獸性本能 Bestial Instincts | G22: 化形 Shifting
A23: =if('請先閱讀'!$F$34=true,"戰俑 Warforged","") -> 戰俑 Warforged | B23: EFA | C23: 中型or小型 | D23: 構裝體 | E23: 構裝韌性 Construct Resilience | F23: 一體化防護 Integrated Protection | G23: 哨兵式休息 Sentry's Rest | H23: 特化設計 Specialized Design | I23: 不倦 Tireless
A24: =IF('請先閱讀'!$O$27=true,"灰燼裔 Ashborn","") | B24: ='請先閱讀'!M$27 -> TCM | C24: 小型 | D24: 邪魔 | E24: 灰燼遺贈 Ashen Legacy | F24: 黑暗視覺 Darkvision | G24: 邪魔幸運 Fiendish Fortune | H24: 蠍刺 Scorpion Sting
A25: =IF('請先閱讀'!$O$27=true,"蒼羽裔 Azureborn","") | B25: ='請先閱讀'!M$27 -> TCM | C25: 中型 | D25: 類人生物 | E25: 蒼羽遺贈 Azure Legacy | F25: 黑暗視覺 Darkvision | G25: 窺視命運 Glimpse Fate | H25: 魔法之風 Winds of Magic
A26: =IF('請先閱讀'!$O$27=true,"沼澤裔 Ashborn","") | B26: ='請先閱讀'!M$27 -> TCM | C26: 中型 | D26: 巨人 | E26: 沼澤巨體 Bog Bulk | F26: 黑暗視覺 Darkvision | G26: 引導連結 Guiding Bond | H26: 敏銳感官 Keen Senses | I26: 再生 Regeneration
A27: =IF('請先閱讀'!$O$27=true,"咒狼裔 Curseborn","") | B27: ='請先閱讀'!M$27 -> TCM | C27: 中型 | D27: 類人生物 | E27: 詛咒利爪 Cursed Claws | F27: 黑暗視覺 Darkvision | G27: 灰厄平衡 Grey Balance | H27: 狼族感官 Lupine Sense
A28: =IF('請先閱讀'!$O$27=true,"深潛裔 Deepborn","") | B28: ='請先閱讀'!M$27 -> TCM | C28: 中型 | D28: 異怪 | E28: 兩棲 Amphibious | F28: 黑暗視覺 Darkvision | G28: 異界亂語 Eldritch Gibbering | H28: 無盡食慾 Endless Hunger
A29: =IF('請先閱讀'!$O$27=true,"詭木裔 Gnarlborn","") | B29: ='請先閱讀'!M$27 -> TCM | C29: 中型 | D29: 植物 | E29: 根深蒂固 Deep Roots | F29: 神木低語 Elderwood Whispers | G29: 纏枝 Grasping Branches | H29: 樹根感知 Root Sense | I29: 參天之姿 Towering Size
A30: =IF('請先閱讀'!$O$27=true,"霜墓裔 Graveborn","") | B30: ='請先閱讀'!M$27 -> TCM | C30: 中型 | D30: 不死生物 | E30: 黑暗視覺 Darkvision | F30: 吞食屍體 Devour Corpse | G30: 無懼霜寒 Frozen Waste | H30: 駐魔龍鋼 Infused Drakkonite
A31: =IF('請先閱讀'!$O$27=true,"豐收裔 Harvestborn","") | B31: ='請先閱讀'!M$27 -> TCM | C31: 中型 | D31: 構裝體 | E31: 剔除 Culling | F31: 翠綠贈禮 Gift of the Green | G31: 南瓜燈 Jack-O-Lantern | H31: 稻草人本質 Scarecrow Nature | I31: 守望休憩 Watchful Rest
A32: =IF('請先閱讀'!$O$27=true,"疫鼠裔 Plagueborn","") | B32: ='請先閱讀'!M$27 -> TCM | C32: 中型 | D32: 類人生物 | E32: 汙穢之子 Born in Filth | F32: 黑暗視覺 Darkvision | G32: 染疫狡詐 Infected Cunning | H32: 帶原體 Plague Bearer
A33: =IF('請先閱讀'!$O$27=true,"遺骷裔 Relicborn","") | B33: ='請先閱讀'!M$27 -> TCM | C33: 中型 | D33: 不死生物 | E33: 死亡之舞 Dance of Death | F33: 永恆派對 Eternal Party | G33: 紀念之刻 Moment of Remembrance | H33: 狂歡之魂 Soul of Revelry
A34: =IF('請先閱讀'!$O$27=true,"絲蛛裔 Silkborn","") | B34: ='請先閱讀'!M$27 -> TCM | C34: 中型 | D34: 類人生物 | E34: 珠寶甲殼 Bejeweled Carapace | F34: 黑暗視覺 Darkvision | G34: 蛛絲遺贈 Silken Legacy | H34: 蛛行 Spider Climb
A35: =IF('請先閱讀'!$O$27=true,"石像裔 Stoneborn","") | B35: ='請先閱讀'!M$27 -> TCM | C35: 中型or小型 | D35: 構裝體 | E35: 銀輝 Argent Gleam | F35: 白銀壁壘 Silver Bulwark | G35: 守望感官 Watchful Senses
A36: =IF('請先閱讀'!$O$27=true,"絲偶裔 Threadborn","") | B36: ='請先閱讀'!M$27 -> TCM | C36: 中型 | D36: 構裝體 | E36: 球形關節 Ball-Jointed | F36: 純潔心智 Innocent Mind | G36: 絲線天性 Sewn Nature | H36: 撫慰之心 Soothing Heart | I36: 常伴左右 You've Got a Friend
A37: =IF('請先閱讀'!O28=true,"吉佩廷 Geppettin","") | B37: VSS:PP | C37: 中型or小型 | D37: 構裝體 | E37: 黑暗視覺 Darkvision | F37: 構裝天性 Construct Nature | G37: 精緻手工 Handcrafted Quality | H37: ="吉佩廷構造："&'角色卡'!AP7&" Gepettin Construction" -> 吉佩廷構造： Gepettin Construction
A38: =IF('請先閱讀'!O28=true,"曼德拉 Mandrake","") | B38: VSS:PP | C38: 中型 | D38: 植物 | E38: 植物天性 Plant Nature | F38: 自然連結 Natural Connection | G38: 根源魔法 Root Magic | H38: 纏繞藤蔓 Entangling Vines
A39: =IF('請先閱讀'!$O$31=true,"GH龍裔 Dragonborn","") | B39: GH | C39: 中型 | D39: 類人生物 | E39: 吐息武器 Breath Weapon | F39: 傷害抗性 Damage Resistance | G39: 威攝咆哮 Menacing Roar | H39: 黑暗視覺 Darkvision | I39: 野外行動 Natural Movement | J39: 強力體格 Powerful Build | K39: 堅定威儀 Firm Influence | L39: 信仰感召 Moved by Faith
A40: =IF('請先閱讀'!$O$31=true,"GH矮人 Dwarf","") | B40: GH | C40: 中型 | D40: 類人生物 | E40: 傷害抗性(毒) Damage Resistance | F40: 剛毅 Toughness | G40: 武器天賦 Weapon Aptitude | H40: 黑暗視覺 Darkvision | I40: 毒素韌性 Poison Resilience | J40: 盤石 Steady | K40: 匠人專精 Artisanal Focus | L40: 工匠之眼 Crafter's Eye
A41: =IF('請先閱讀'!$O$31=true,"GH精靈 Elf","") | B41: GH | C41: 中型 | D41: 類人生物 | E41: 啟蒙心靈 Awakened Mind | F41: 專注精神 Focused Mind | G41: 武器天賦 Weapon Aptitude | H41: 黑暗視覺 Darkvision | I41: 冥想休憩 Meditative Rest | J41: 荒野庇護 Shroud of the Wild | K41: 天生覺察 Inborn Perception | L41: 魔法領悟(任意戲法) Magical Savvy
A42: =IF('請先閱讀'!$O$31=true,"GH地侏 Gnome","") | B42: GH | C42: 小型 | D42: 類人生物 | E42: 魔法壁壘 Magical Fortification | F42: 快速翻滾 Quick turnover | G42: 工藝專精 Artifice Expertise | H42: 黑暗視覺 Darkvision | I42: 消失無蹤 Fade Away | J42: 魔法領悟 Magical Savvy | K42: 卓越天賦 Masterful Aptitude | L42: 自然之聲 Nature's Voice
A43: =IF('請先閱讀'!$O$31=true,"GH半身人 Halfling","") | B43: GH | C43: 小型 | D43: 類人生物 | E43: 勇敢 Brave | F43: 生物掩護 Creature Cover | G43: 幸運 Lucky | H43: 援手 Helping Hand | I43: 穿梭 Pass Through | J43: 深度小憩 Power Nap | K43: 匠人專精 Artisanal Focus | L43: 擁抱過去 Embrace the Past
A44: =IF('請先閱讀'!$O$31=true,"GH人類 Human","") | B44: GH | C44: 中型 | D44: 類人生物 | E44: 驚世重擊 Awesome Critical | F44: 先發制人 First Strike | G44: 武器天賦 Weapon Aptitude | H44: 援手 Helping Hand | I44: 天生直覺 Intrinsic Orientation | J44: 匠人專精 Artisanal Focus | K44: 精明倖存者 Keen Survivor | L44: 高超技巧 Skill Prowess
A45: =IF('請先閱讀'!$O$31=true,"夢行者 Dreamer","") | B45: GH | C45: 中型 | D45: 類人生物 | E45: 快攻 Quick Initiative | F45: 堅毅儲備 Stalwart Reserves | G45: 黑暗視覺 Darkvision | H45: 援手 Helping Hand | I45: 深度小憩 Power Nap | J45: 夢行 Dreamwalking | K45: 即興創作 Improviser | L45: 天生覺察 Inborn Perception
A46: =IF('請先閱讀'!$O$31=true,"怨恨 Grudgel","") | B46: GH | C46: 中型 | D46: 類人生物 | E46: 戰場掌控 Battlefield Control | F46: 全集中 Centered | G46: 黑暗視覺 Darkvision | H46: 身強力壯 Powerful Build | I46: 不倦 Tireless | J46: 匠人專精 Artisanal Focus | K46: 即興巧匠 Impromptu Artisan | L46: 魔法領悟(任意戲法) Magical Savvy
A47: =IF('請先閱讀'!$O$31=true,"溟族 Laneshi","") | B47: GH | C47: 中型 | D47: 類人生物 | E47: 啟蒙心靈 Awakened Mind | F47: 心靈魂體 Psychic Spirit | G47: 兩棲 Amphibious | H47: 黑暗視覺 Darkvision | I47: 游泳 Swimmer | J47: 動物朋友 Animal Friend | K47: 魔法領悟(任意死靈戲法) Magical Savvy | L47: 自然之聲 Nature's Voice
A48: =IF('請先閱讀'!$O$31=true,"食人魔族 Ogresh","") | B48: GH | C48: 中型 | D48: 類人生物 | E48: 乘勢制敵 Enemy in Motion | F48: 專注精神 Focused Mind | G48: 環境感知 Environmental Awareness | H48: 野外行動 Natural Movement | I48: 身強力壯 Powerful Build | J48: 心機聽眾 Calculating Listener | K48: 威嚴洞察 Commanding Insight | L48: 說服竅門 Persuasive Knack
A49: =IF('請先閱讀'!$O$31=true,"咒縛者 Accursed","") | B49: GH | C49: 中型or小型 | D49: 類人生物
A50: =IF('請先閱讀'!$O$31=true,"復生人 Arisen","") | B50: GH | C50: 中型or小型 | D50: 類人生物 | E50: 魔法壁壘 Magical Fortification | F50: 頑強 Tenacious | G50: 剛毅 Toughness | H50: 人造形態 Artificial Form | I50: 環境耐受 Inured to the Elements | J50: 擁抱過去 Embrace the Past | K50: 魔法洞察 Magical Insight | L50: 超自然醫者 Unnatural Healer
A51: =IF('請先閱讀'!$O$31=true,"GH半血裔 Dhampir","") | B51: GH | C51: 中型or小型 | D51: 類人生物 | E51: 吸取攻擊 Draining Attack | F51: 天生武器(獠牙) Natural Attack | G51: 完善保護 Well Protected | H51: 攀爬者 Climber | I51: 黑暗視覺 Darkvision | J51: 熱情騙子 Eager Deceiver | K51: 魔法專家(魅惑人類) Magical Savant | L51: 魔法領悟(交友術) Magical Savvy
A52: =IF('請先閱讀'!$O$31=true,"靈體化者 Disembodied","") | B52: GH | C52: 中型or小型 | D52: 類人生物 | E52: 魔法壁壘 Magical Fortification | F52: 分心大師 Master of Distraction | G52: 相位偏移 Out of Phase | H52: 乙太淡化 Ethereal Fade | I52: 環境耐受 Inured to the Elements | J52: 魔法洞察 Magical Insight | K52: 魔法專家(羽落術) Magical Savant | L52: 魔法領悟(舞光術) Magical Savvy
A53: =IF('請先閱讀'!$O$31=true,"放逐者 Downcast","") | B53: GH | C53: 中型 | D53: 類人生物 | E53: 神聖操血術 Divine Sangromancy | F53: 生命之觸 Touch of Life | G53: 環境耐受 Inured to the Elements | H53: 冥想休憩 Meditative Rest | I53: 不倦 Tireless | J53: 魔法專家(限牧師法術) Magical Savant | K53: 魔法領悟(奇術) Magical Savvy | L53: 信仰感召 Moved by Faith
A54: =IF('請先閱讀'!$O$31=true,"易魂者 Wechselkind","") | B54: GH | C54: 小型 | D54: 類人生物 | E54: 生物掩護 Creature Cover | F54: 魔法壁壘 Magical Fortification | G54: 人造形態 Artificial Form | H54: 援手 Helping Hand | I54: 穿梭 Pass Through | J54: 魔法專家(易容術) Magical Savant | K54: 魔法領悟(次級幻象) Magical Savvy | L54: 直覺雜技 Intuitive Acrobat
A55: =IF('請先閱讀'!$O$31=true,"狼人 Wulven","") | B55: GH | C55: 中型or小型 | D55: 類人生物 | E55: 獵人直覺 Hunter's Instinct | F55: 天生武器(利爪) Natural Attack | G55: 群體獵手 Pack Hunter | H55: 爆發衝刺 Burst of Speed | I55: 攀爬者 Climber | J55: 運動家之魂 Athlete's Spirit | K55: 天生覺察 Inborn Perception | L55: 自然之聲 Nature's Voice
A56: =IF('請先閱讀'!$O$32=true,"雪裔 Snowborn","") | B56: OSW:HAP | C56: 中型or小型 | D56: 構裝體 | E56: 寒冷體質 Chilled Anatomy | F56: 壓雪 Compacted Snow | G56: 極寒構裝 Frigid Construct | H56: 冰川型態 Glacial Form
A57: =IF('請先閱讀'!$O$32=true,"馴鹿人 Tarandus","") | B57: OSW:HAP | C57: 中型 | D57: 類人生物 | E57: 引導之光 Guiding Light | F57: 鹿角防禦 Antler Defence | G57: 腳蹄 Hooves | H57: 為導航生 Born to Navigate
A58: =IF('請先閱讀'!$O$32=true,"常春人 Hederan","") | B58: OSW:HAP | C58: 中型or小型 | D58: 類人生物 | E58: 黑暗視覺 Darkvision | F58: 荒野適應 Outdoor Adept | G58: 自然庇護 Protected by Nature | H58: 走獸之友 Friend of Fauna
A59: =IF('請先閱讀'!$O$32=true,"卡尼薩 Canisar","") | B59: OSW:HAP | C59: 小型 | D59: 類人生物 | E59: 黑暗視覺 Darkvision | F59: 後肢衝刺 Hind Leg Dash | G59: 獠牙利顎 Fanged Jaws | H59: 狩獵採集者 Hunter Gatherer | I59: 先祖祝福 Ancestral Blessing
A60: =IF('請先閱讀'!$O$33=true,"Dhakaani Ghaal'dar (大哥布林)","") | B60: EE | C60: 中型 | D60: 類人生物 | E60: 黑暗視覺 Darkvision | F60: 軍紀 Discipline | G60: 團結力量大 Strength in Unity | H60: 戰爭與和平 War and Peace
A61: =IF('請先閱讀'!$O$33=true,"Dhakaani Guul'dar (熊地精)","") | B61: EE | C61: 中型 | D61: 類人生物 | E61: 黑暗視覺 Darkvision | F61: 勇氣 Brave | G61: 長臂 Long-Limbed | H61: 身強力壯 Powerful Build | I61: 與強者為伍 Stand by the Strong
A62: =IF('請先閱讀'!$O$33=true,"Dhakanni Golin'dar (哥布林)","") | B62: EE | C62: 中型 | D62: 類人生物 | E62: 黑暗視覺 Darkvision | F62: 軍紀 Discipline | G62: 天生善匿 Naturally Stealthy | H62: 小子靈巧 Nimbleness
A63: =IF('請先閱讀'!$O$33=true,"豺狼人","") | B63: EE | C63: 中型 | D63: 類人生物 | E63: 黑暗視覺 Darkvision | F63: 啃咬 Bite | G63: 獵人感官 Hunter's Senses | H63: 大鬧一番 Rampage
A64: =IF('請先閱讀'!$O$33=true,"Jhorgun'taal (半獸人)","") | B64: EE | C64: 中型 | D64: 類人生物 | E64: 黑暗視覺 Darkvision | F64: 堅韌不屈 Relentless Endurance | G64: 多才多藝 Versatile
A65: =IF('請先閱讀'!$O$33=true,"卡拉默陸行者 (人魚)","") | B65: EE | C65: 中型 | D65: 類人生物 | E65: 黑暗視覺 Darkvision | F65: 兩棲 Amphibious | G65: 海洋祝福 Blessing of the Sea | H65: 卡拉卡拉軼聞 Karakala Lore
A66: =IF('請先閱讀'!$O$33=true,"腐化宿主 Ruinbound","") | B66: EE | C66: 中型or小型 | D66: 類人生物 | E66: 黑暗視覺 Darkvision | F66: 伴生共生體 Personal Symbiont | G66: 精通共生 Symbiont Mastery | H66: 超自然韌性 Unnatural Resilience
A67: =IF('請先閱讀'!$O$33=true,"沙華魚人 Sahuagin","") | B67: EE | C67: 中型 | D67: 類人生物 | E67: 黑暗視覺 Darkvision | F67: 急速泳者 Swift Swimmer | G67: 鮮血狂熱 Blood Frenzy | H67: 天生護甲 Natural Armor | I67: 有限兩棲 Limited Amphibiousness
A68: =IF('請先閱讀'!$O$35=true,"羽裔 Feathren","") | B68: TGS1 | C68: 中型 | D68: 類人生物 | E68: 黑暗視覺 Darkvision | F68: ="羽族血統："&'角色卡'!AP7&" Feathren Ancestry" -> 羽族血統： Feathren Ancestry | G68: 族親之語 Kindred Speech | H68: 天生造物者 Natural Creator | I68: 利爪 Talons
A69: =IF('請先閱讀'!$O$36=true,"甲龍人 Ankylier","") | B69: DDDD | C69: 中型 | D69: 類人生物 / 恐龍 | E69: 額外語言 Bonus Languages | F69: 健壯肌肉 Musclebound | G69: 尾槌 Clubbed Tail | H69: 金屬工匠 Metalworker | I69: 皮內成骨 Osteoderms
A70: =IF('請先閱讀'!$O$36=true,"賽特之子 Child of Seth","") | B70: DDDD | C70: 中型 | D70: 類人生物 / 恐龍 / 翼龍 | E70: 額外語言 Bonus Languages | F70: 飛行 Flight | G70: 環球遷徙 Global Migrators | H70: 口述文明 Verbal Culture | I70: 見多識廣 Well-Travelled
A71: =IF('請先閱讀'!$O$36=true,"熱河龍人 Jeholrak","") | B71: DDDD | C71: 小型 | D71: 類人生物 / 恐龍 | E71: 額外語言 Bonus Languages | F71: 說服之力 Power of Persuasion | G71: 割喉社會 Cutthroat Society
A72: =IF('請先閱讀'!$O$36=true,"泥潭龍人 Limukin","") | B72: DDDD | C72: 中型or小型 | D72: 類人生物 / 恐龍 | E72: 額外語言 Bonus Languages | F72: 狩獵採集者 Hunter-Gatherer | G72: 淬毒武器 Envenomed Weapons | H72: 守望者之眼 Watcher's Eyes | I72: 先天毒物抗性 Innate Toxicology
A73: =IF('請先閱讀'!$O$36=true,"多角龍人 Manyhorn","") | B73: DDDD | C73: 中型or小型 | D73: 類人生物 / 恐龍 | E73: 額外語言 Bonus Languages | F73: 健壯肌肉 Musclebound | G73: 工會人脈 Guild Connections | H73: 頭冠 Head Crest | I73: 犄角反擊 Horned Repose
A74: =IF('請先閱讀'!$O$36=true,"羽龍人 Pluvenn","") | B74: DDDD | C74: 中型or小型 | D74: 類人生物 / 恐龍 | E74: 額外語言 Bonus Languages | F74: 利牙 Razormaw | G74: 擒拿鉤爪 Grappleclaws | H74: 晝夜習性 Nocturnal/Diurnal | I74: 骨骼氣腔化與覆羽 Pneumatised and Feathered

Sheet 子職業能力
A1: 職業等級 | B1: 子職業類型 | C1: 能力A | D1: 能力B | E1: 能力C | F1: 能力D | G1: 能力E | H1: 能力F | I1: 能力G | J1: 能力H
A2: ='職業能力'!B2 -> 0 | B2: 狂戰士道途 | C2: =IF(A2>=1,"狂怒("&IF(A2>=16,"4d6",IF(A2>=9,"3d6","2d6"))&")","") | D2: =IF($A$2>=6,"無我狂暴","") | E2: =IF($A$2>=10,"復仇","") | F2: =IF($A$2>=14,"威攝之姿","")
A3: 野蠻人 | B3: 荒野之心道途 | C3: =IF($A$2>=3,"動物語者","") | D3: =IF($A$2>=3,"獸性狂暴","") | E3: =IF($A$2>=6,"獸體形貌"&'職業能力選項'!F3,"") | F3: =IF($A$2>=10,"自然語者","") | G3: =IF($A$2>=14,"獸力威能","")
B4: 世界樹道途 | C4: =IF($A$2>=3,"聖樹活力","") | D4: =IF($A$2>=6,"靈樹枝枒","") | E4: =IF($A$2>=10,"根擊千鈞","") | F4: =IF($A$2>=14,"世界樹奇旅","")
B5: 狂熱者道途 | C5: =IF($A$2>=3,"神性之怒","") | D5: =IF($A$2>=3,"諸神勇士","") | E5: =IF($A$2>=6,"狂熱專注","") | F5: =IF($A$2>=10,"狂熱威儀","") | G5: =IF($A$2>=14,"神祗狂暴","")
B6: 實驗道途 | C6: =IF($A$2>=3,"煉金實驗","") | D6: =IF($A$2>=3,"不穩定血清","") | E6: =IF($A$2>=6,"強化化合物","") | F6: =IF($A$2>=10,"應激催化","") | G6: =IF($A$2>=14,"生化混合","")
B7: 肌肉魔法使道途 | C7: =IF($A$2>=3,"無'法'反駁","") | D7: =IF($A$2>=3,"「戲法」","") | E7: =IF($A$2>=3,"「法術」","") | F7: =IF($A$2>=3,"魔法抗性","") | G7: =IF($A$2>=3,"我施放拳頭","")
B8: 蔑法道途 | C8: =IF($A$2>=3,"本能預知","") | D8: =IF($A$2>=3,"破法槌","") | E8: =IF($A$2>=3,"吸法盾","") | F8: =IF($A$2>=6,"撕裂魔網","") | G8: =IF($A$2>=10,"振奮咆哮","") | H8: =IF($A$2>=14,"次元決鬥","")
B9: 分裂道途 | C9: =IF($A$2>=3,"狂怒面容","") | D9: =IF($A$2>=3,"文明面具","") | E9: =IF($A$2>=6,"智慧與力量","") | F9: =IF($A$2>=10,"狡詐與殘暴","") | G9: =IF($A$2>=14,"另一個我","")
B10: 原初精魂道途 | C10: =IF($A$2>=3,"原初夥伴","") | D10: =IF($A$2>=3,"共享狂暴","") | E10: =IF($A$2>=3,"野獸親族","") | F10: =IF($A$2>=3,"獸魂附體","") | G10: =IF($A$2>=3,"荒野之形","")
B11: 憤怒亡靈道途 | C11: =IF($A$2>=3,"亡靈之怒","") | D11: =IF($A$2>=3,"終夜宣洩"&'職業能力選項'!F6,"") | E11: =IF($A$2>=6,"重演黑暗厄運","") | F11: =IF($A$2>=10,"死亡不過是一扇門","") | G11: =IF($A$2>=14,"悲愴驅動","")
B12: 冰川道途 | C12: =IF($A$2>=3,"原初霜寒","") | D12: =IF($A$2>=3,"霜噬","") | E12: =IF($A$2>=3,"寒霜壁壘","") | F12: =IF($A$2>=3,"深度睡眠","") | G12: =IF($A$2>=3,"雪崩踏步","")
A24: ='職業能力'!C2 -> 0 | B24: 舞蹈學院 | C24: =IF($A$24>=3,"炫目舞步","") | D24: =IF($A$24>=6,"激勵移動","") | E24: =IF($A$24>=6,"協同舞步","") | F24: =IF($A$24>=14,"引導閃避","")
A25: 吟遊詩人 | B25: 迷惑學院 | C25: =IF($A$24>=3,"惑心魔法","") | D25: =IF($A$24>=3,"鼓舞領域","") | E25: =IF($A$24>=6,"威嚴領域","") | F25: =IF($A$24>=14,"絕對威儀","")
B26: 軼聞學院 | C26: =IF($A$24>=3,"額外熟練","") | D26: =IF($A$24>=3,"語出驚人","") | E26: =IF($A$24>=6,"魔法發現","") | F26: =IF($A$24>=14,"絕代技能","")
B27: 勇氣學院 | C27: =IF($A$24>=3,"戰鬥激勵","") | D27: =IF($A$24>=3,"武術訓練","") | E27: =IF($A$24>=6,"額外攻擊","") | F27: =IF($A$24>=14,"戰鬥魔法","")
B28: 月亮學院 | C28: =IF($A$24>=3,"明月激勵","") | D28: =IF($A$24>=3,"原初軼聞","") | E28: =IF($A$24>=6,"月光祝福","") | F28: =IF($A$24>=14,"暮光輝映","")
B29: 靈哨學院 | C29: =IF($A$24>=3,"助人鬼祟","") | D29: =IF($A$24>=3,"吹哨漫遊者","") | E29: =IF($A$24>=6,"歸鄉之路","") | F29: =IF($A$24>=6,"軌道疾行","") | G29: =IF($A$24>=14,"終點站","")
B30: 戲劇學院 | C30: =IF($A$24>=3,"悲劇英雄","") | D30: =IF($A$24>=3,"百面人生","") | E30: =IF($A$24>=6,"舞台指導","") | F30: =IF($A$24>=6,"眾星登場","") | G30: =IF($A$24>=14,"壓軸好戲","")
B31: 冒險者學院 | C31: =IF($A$24>=3,"冒險者天賦("&IF(A91>=14,"3項",IF(A91>=6,"2項","1項"))&")","") | D31: =IF($A$24>=3,"團隊策劃","") | E31: =IF($A$24>=6,"面面俱到","") | F31: =IF($A$24>=14,"即興天賦","")
B32: 弄臣學院 | C32: =IF($A$24>=3,"丑態挑釁","") | D32: =IF($A$24>=3,"惡毒戲謔","") | E32: =IF($A$24>=6,"黑色幽默","") | F32: =IF($A$24>=14,"笑到最後","")
B33: 安魂學院 | C33: =IF($A$24>=3,"寒顫旋律","") | D33: =IF($A$24>=3,"撥動心弦","") | E33: =IF($A$24>=6,"舞動骸骨","") | F33: =IF($A$24>=14,"雙死","")
B34: 傳頌學院 | C34: =IF($A$24>=3,"廣泛激勵","") | D34: =IF($A$24>=3,"歷史守護者","") | E34: =IF($A$24>=6,"命令之聲","") | F34: =IF($A$24>=14,"戰鬥頌歌","")
B35: 織舞學院 | C35: =IF($A$24>=3,"快速移動","") | D35: =IF($A$24>=3,"激勵舞蹈","") | E35: =IF($A$24>=6,"迷人步伐","") | F35: =IF($A$24>=14,"無盡之舞","")
A46: ='職業能力'!D2 -> 0 | B46: 生命領域 | C46: =IF($A$46>=3,"生命領域法術","") | D46: =IF($A$46>=3,"生命門徒","") | E46: =IF($A$46>=3,"引導神力：維繫生命","") | F46: =IF($A$46>=6,"祝聖醫者","") | G46: =IF($A$46>=17,"極效治療","")
A47: 牧師 | B47: 光明領域 | C47: =IF($A$46>=3,"光明領域法術","") | D47: =IF($A$46>=3,"閃耀防護","") | E47: =IF($A$46>=3,"引導神力：黎明曙光","") | F47: =IF($A$46>=6,"強化閃耀防護","") | G47: =IF($A$46>=17,"日冕光輝","")
B48: 詭術領域 | C48: =IF($A$46>=3,"詭術領域法術","") | D48: =IF($A$46>=3,"詭術祝福","") | E48: =IF($A$46>=3,"引導神力：召喚分身","") | F48: =IF($A$46>=6,"詭詐換位","") | G48: =IF($A$46>=17,"強化分身","")
B49: 戰爭領域 | C49: =IF($A$46>=3,"戰爭領域法術","") | D49: =IF($A$46>=3,"戰爭祭司","") | E49: =IF($A$46>=3,"引導神力：導引打擊","") | F49: =IF($A$46>=6,"引導神力：戰神祝福","") | G49: =IF($A$46>=17,"戰爭化身","")
B50: 知識領域 | C50: =IF($A$46>=3,"知識領域法術","") | D50: =IF($A$46>=3,"知識祝福","") | E50: =IF($A$46>=3,"引導神力：思維魔法","") | F50: =IF($A$46>=6,"無拘思維","") | G50: =IF($A$46>=17,"神聖預知","")
B51: 豐收領域 | C51: =IF($A$46>=3,"豐收領域法術","") | D51: =IF($A$46>=3,"農民曆","") | E51: =IF($A$46>=3,"豐裕之角","") | F51: =IF($A$46>=3,"引導神力：五穀豐登","") | G51: =IF($A$46>=6,"四季祝福","") | H51: =IF($A$46>=17,"永恆之輪","")
B52: 天啟領域 | C52: =IF($A$46>=3,"天啟領域法術","") | D52: =IF($A$46>=3,"毀滅願景","") | E52: =IF($A$46>=3,"引導神力：末日之歌","") | F52: =IF($A$46>=6,"塵歸塵，土歸土","") | G52: =IF($A$46>=17,"浩劫餘生","")
B53: 怪異領域 | C53: =IF($A$46>=3,"怪異領域法術","") | D53: =IF($A$46>=3,"怪異蔓延","") | E53: =IF($A$46>=3,"引導神力：厄運預言","") | F53: =IF($A$46>=6,"超凡鎮定","") | G53: =IF($A$46>=17,"吟唱終末之歌","")
B54: 審判領域 | C54: =IF($A$46>=3,"審判領域法術","") | D54: =IF($A$46>=3,"獵巫打擊","") | E54: =IF($A$46>=3,"引導神力：法術護盾","") | F54: =IF($A$46>=6,"叱喝祈者","") | G54: =IF($A$46>=17,"至高守護","")
B55: 淨化領域 | C55: =IF($A$46>=3,"淨化領域法術","") | D55: =IF($A$46>=3,"以火淨化","") | E55: =IF($A$46>=3,"引導神力：不潔烙印","") | F55: =IF($A$46>=6,"防止腐化","") | G55: =IF($A$46>=17,"燒灼瑕疵","")
B56: 心靈領域 | C56: =IF($A$46>=3,"心靈領域法術","") | D56: =IF($A$46>=3,"精神之力","") | E56: =IF($A$46>=3,"引導神力：精神反饋","") | F56: =IF($A$46>=6,"格式塔定錨","") | G56: =IF($A$46>=17,"現實連結","")
B57: 星界領域 | C57: =IF($A$46>=3,"星界領域法術","") | D57: =IF($A$46>=3,"位面觸碰","") | E57: =IF($A$46>=3,"引導神力：創造虛空","") | F57: =IF($A$46>=6,"空間交換","") | G57: =IF($A$46>=17,"卓越替換","")
A68: ='職業能力'!E2 -> 0 | B68: 大地結社 | C68: =IF($A$68>=3,"大地結社法術"&'職業能力選項'!T3,"") | D68: =IF($A$68>=3,"大地援助","") | E68: =IF($A$68>=6,"自然恢復","") | F68: =IF($A$68>=10,"自然加護"&'職業能力選項'!U3,"") | G68: =IF($A$68>=14,"自然庇護","")
A69: 德魯伊 | B69: 月亮結社 | C69: =IF($A$68>=3,"月亮結社法術","") | D69: =IF($A$68>=3,"結社型態(CR"&ROUNDDOWN(A68/3,0)&")","") | E69: =IF($A$68>=6,"強化結社型態","") | F69: =IF($A$68>=10,"月光飛步","") | G69: =IF($A$68>=14,"月之儀態","")
B70: 海洋結社 | C70: =IF($A$68>=3,"海洋結社法術","") | D70: =IF($A$68>=3,"濤海狂怒","") | E70: =IF($A$68>=6,"水生親和","") | F70: =IF($A$68>=10,"風暴降生","") | G70: =IF($A$68>=14,"大洋餽贈","")
B71: 星辰結社 | C71: =IF($A$68>=3,"星圖","") | D71: =IF($A$68>=3,"星耀形態","") | E71: =IF($A$68>=6,"宇宙預兆"&'職業能力選項'!T6,"") | F71: =IF($A$68>=10,"閃耀星座","") | G71: =IF($A$68>=14,"燦若繁星","")
B72: 古道結社 | C72: =IF($A$68>=3,"古道結社法術","") | D72: =IF($A$68>=3,"主幹與分枝","") | E72: =IF($A$68>=6,"橡木與荊棘","") | F72: =IF($A$68>=10,"深林長者","") | G72: =IF($A$68>=14,"遠古守衛","")
B73: 柳條結社 | C73: =IF($A$68>=3,"柳條結社法術","") | D73: =IF($A$68>=3,"巫咒塑像","") | E73: =IF($A$68>=3,"柳條符咒","") | F73: =IF($A$68>=6,"蔥鬱柳條","") | G73: =IF($A$68>=10,"縛魂木偶","") | H73: =IF($A$68>=14,"插柳成蔭","")
B74: 共生結社 | C74: =IF($A$68>=3,"共生結社法術","") | D74: =IF($A$68>=3,"原初共生","") | E74: =IF($A$68>=6,"共生反射","") | F74: =IF($A$68>=10,"求生本能","") | G74: =IF($A$68>=14,"湧現生機","")
B75: 鮮血結社 | C75: =IF($A$68>=3,"鮮血結社法術","") | D75: =IF($A$68>=3,"血月儀式","") | E75: =IF($A$68>=6,"鮮血恩惠","") | F75: =IF($A$68>=10,"血欲","") | G75: =IF($A$68>=14,"生命抽取","")
B76: 熵力結社 | C76: =IF($A$68>=3,"災難之力"&'職業能力選項'!T9,"") | D76: =IF($A$68>=3,"毀滅化身","") | E76: =IF($A$68>=6,"萬途歸滅","") | F76: =IF($A$68>=10,"地動山搖","") | G76: =IF($A$68>=14,"熵之極致","")
B77: 突變結社 | C77: =IF($A$68>=3,"結社型態","") | D77: =IF($A$68>=3,"突變塑形","") | E77: =IF($A$68>=6,"反常且駭人","") | F77: =IF($A$68>=10,"無限演化","") | G77: =IF($A$68>=14,"頂級掠食者","")
B78: 鍛物結社 | C78: =IF($A$68>=3,"鍛物結社法術","") | D78: =IF($A$68>=3,"金屬外層","") | E78: =IF($A$68>=6,"元素灌注","") | F78: =IF($A$68>=10,"精金塗裝","") | G78: =IF($A$68>=14,"完善構裝","")
B79: 不朽結社 | C79: =IF($A$68>=3,"不朽結社法術","") | D79: =IF($A$68>=3,"強化像棍術","") | E79: =IF($A$68>=3,"荒野復甦","") | F79: =IF($A$68>=6,"像棍術專精","") | G79: =IF($A$68>=10,"戰爭德魯伊","") | H79: =IF($A$68>=14,"自然護甲","")
B80: 輪轉結社
A91: ='職業能力'!F2 -> 0 | B91: 戰鬥大師 | C91: =IF($A$91>=3,"卓越戰技("&IF(A91>=15,"9項",IF(A91>=10,"7項",IF(A91>=7,"5項","3項")))&"戰技/"&IF(A91>=15,"6枚",IF(A91>=7,"5枚","4枚"))&IF(A91>=18,"d12",IF(A91>=10,"d10","d8"))&")","") | D91: =IF($A$91>=3,"戰爭學徒","") | E91: =IF($A$91>=7,"知己知彼","") | F91: =IF($A$91>=15,"頑強","")
A92: 戰士 | B92: 勇士 | C92: =IF($A$91>=3,"強化重擊","") | D92: =IF($A$91>=3,"運動健將","") | E92: =IF($A$91>=7,"額外戰鬥風格","") | F92: =IF($A$91>=10,"百戰英傑","") | G92: =IF($A$91>=15,"卓越重擊","") | H92: =IF($A$91>=18,"百折不撓","")
B93: 魔能騎士 | C93: =IF($A$91>=3,"施法","") | D93: =IF($A$91>=3,"戰爭連結","") | E93: =IF($A$91>=7,"戰爭魔法","") | F93: =IF($A$91>=10,"魔能打擊","") | G93: =IF($A$91>=15,"祕法衝鋒","") | H93: =IF($A$91>=18,"強化戰爭魔法","")
B94: 靈能武士 | C94: =IF($A$91>=3,"靈能力量("&IF(A91>=17,"12枚",IF(A91>=13,"10枚",IF(A91>=9,"8枚",IF(A91>=5,"6枚","4枚"))))&IF(A91>=17,"d12",IF(A91>=11,"d10",IF(A91>=5,"d8","d6")))&")","") | D94: =IF($A$91>=7,"念力精通","") | E94: =IF($A$91>=10,"意念守護","") | F94: =IF($A$91>=15,"力場壁壘","") | G94: =IF($A$91>=18,"念力宗師","")
B95: 旗將 | C95: =IF($A$91>=3,"騎士使節","") | D95: =IF($A$91>=3,"群體回復","") | E95: =IF($A$91>=7,"團隊戰術","") | F95: =IF($A$91>=10,"湧動潮流","") | G95: =IF($A$91>=15,"分享堅韌","") | H95: =IF($A$91>=18,"統御指揮","")
B96: 陵墓守衛 | C96: =IF($A$91>=3,"死亡騎士","") | D96: =IF($A$91>=7,"汲取靈魂","") | E96: =IF($A$91>=10,"陵墓守御者","") | F96: =IF($A$91>=15,"墳墓領主","") | G96: =IF($A$91>=18,"亡靈之力","")
B97: 地城探險家 | C97: =IF($A$91>=3,"踹門","") | D97: =IF($A$91>=3,"英雄迷信","") | E97: =IF($A$91>=7,"地城預防措施","") | F97: =IF($A$91>=10,"怪物殺手","") | G97: =IF($A$91>=15,"迴避","") | H97: =IF($A$91>=18,"百戰英雄","")
B98: 英雄 | C98: =IF($A$91>=3,"激勵之儀","") | D98: =IF($A$91>=3,"英雄壯舉","") | E98: =IF($A$91>=7,"以身作則","") | F98: =IF($A$91>=10,"鼓舞之儀","") | G98: =IF($A$91>=15,"堅韌之儀","") | H98: =IF($A$91>=18,"超凡壯舉","")
B99: 壁壘衛士 | C99: =IF($A$91>=3,"保護嘲諷","") | D99: =IF($A$91>=3,"挺過風暴","") | E99: =IF($A$91>=7,"威嚇姿態","") | F99: =IF($A$91>=10,"以攻為守","") | G99: =IF($A$91>=15,"強化回氣","") | H99: =IF($A$91>=18,"阻斷攻勢","")
B100: 活體坩堝 | C100: =IF($A$91>=3,"化合物製造","") | D100: =IF($A$91>=3,"煉金學士","") | E100: =IF($A$91>=7,"活體鍋釜","") | F100: =IF($A$91>=10,"快速攝取","") | G100: =IF($A$91>=15,"毒素轉化","") | H100: =IF($A$91>=18,"活體觸媒","")
B101: 守夜人 | C101: =IF($A$91>=3,"幹練守衛","") | D101: =IF($A$91>=3,"時刻警戒","") | E101: =IF($A$91>=7,"打量對手","") | F101: =IF($A$91>=10,"夜行者","") | G101: =IF($A$91>=15,"蓄勢待發","") | H101: =IF($A$91>=18,"痛打一頓","")
B102: 羽蛇傳令 | C102: =IF($A$91>=3,"仁慈行者","") | D102: =IF($A$91>=3,"眾人之一","") | E102: =IF($A$91>=7,"和平使者","") | F102: =IF($A$91>=10,"沉穩心靈","") | G102: =IF($A$91>=15,"模範","") | H102: =IF($A$91>=18,"傳令執行官","")
B103: 雕骨師
A113: ='職業能力'!H2 -> 0 | B113: 命流武者 | C113: =IF($A$113>=3,"奪命之手","") | D113: =IF($A$113>=3,"予命之手","") | E113: =IF($A$113>=3,"掌握命流","") | F113: =IF($A$113>=6,"生死之觸","") | G113: =IF($A$113>=11,"活殺自在","") | H113: =IF($A$113>=17,"命極之手","")
A114: 武僧 | B114: 暗影武者 | C114: =IF($A$113>=3,"暗影技藝","") | D114: =IF($A$113>=6,"暗影步","") | E114: =IF($A$113>=11,"強化暗影步","") | F114: =IF($A$113>=17,"暗影斗篷","")
B115: 四象武者 | C115: =IF($A$113>=3,"四象同調","") | D115: =IF($A$113>=3,"操作四象","") | E115: =IF($A$113>=6,"四象爆破拳","") | F115: =IF($A$113>=11,"四象遁術","") | G115: =IF($A$113>=17,"四象神通","")
B116: 散打武者 | C116: =IF($A$113>=3,"散打技巧","") | D116: =IF($A$113>=6,"混元體","") | E116: =IF($A$113>=11,"流星步","") | F116: =IF($A$113>=17,"滲透勁","")
B117: 瘴癘武者 | C117: =IF($A$113>=3,"染疫之道","") | D117: =IF($A$113>=3,"疫病賜福","") | E117: =IF($A$113>=6,"強效瘟疫","") | F117: =IF($A$113>=6,"敲響喪鐘","") | G117: =IF($A$113>=11,"致病毒瘴","") | H117: =IF($A$113>=17,"傳染瘟疫","")
B118: 街頭武者 | C118: =IF($A$113>=3,"連擊","") | D118: =IF($A$113>=3,"鐵拳","") | E118: =IF($A$113>=6,"特殊招式","") | F118: =IF($A$113>=11,"空中衝刺","") | G118: =IF($A$113>=17,"K.O.","")
B119: 天衡武者 | C119: =IF($A$113>=3,"守道技藝","") | D119: =IF($A$113>=3,"探詢者","") | E119: =IF($A$113>=6,"均衡衛士","") | F119: =IF($A$113>=11,"寰宇復原","") | G119: =IF($A$113>=17,"邪祟封禁","")
B120: 鉛冕武者 | C120: =IF($A$113>=3,"無形之手","") | D120: =IF($A$113>=3,"靈能造詣","") | E120: =IF($A$113>=6,"顯形打擊","") | F120: =IF($A$113>=11,"心靈粉碎","") | G120: =IF($A$113>=17,"靈能神通","")
B121: 孤高武者 | C121: =IF($A$113>=3,"天方夜譚","") | D121: =IF($A$113>=3,"愈挫愈勇","") | E121: =IF($A$113>=3,"強橫攻勢","") | F121: =IF($A$113>=6,"睚眥必報","") | G121: =IF($A$113>=6,"倍加圖強","") | H121: =IF($A$113>=11,"傲骨不折","") | I121: =IF($A$113>=17,"惟我獨尊","")
B122: 悔恨武者 | C122: =IF($A$113>=3,"悔恨之影","") | D122: =IF($A$113>=3,"未行之路","") | E122: =IF($A$113>=6,"未施之援","") | F122: =IF($A$113>=11,"罪咎碾壓","") | G122: =IF($A$113>=17,"往日重現","")
B123: 活體武器武者 | C123: =IF($A$113>=3,"武術形態","") | D123: =IF($A$113>=3,"變幻莫測","") | E123: =IF($A$113>=6,"顯化之擊"&'職業能力選項'!AF3,"") | F123: =IF($A$113>=11,"本能適應","") | G123: =IF($A$113>=17,"完美型態","")
B124: 天界武者 | C124: =IF($A$113>=3,"天界連結","") | D124: =IF($A$113>=3,"索魂擊","") | E124: =IF($A$113>=6,"屏氣凝神","") | F124: =IF($A$113>=11,"天界使者","") | G124: =IF($A$113>=17,"天將神兵","")
A135: ='職業能力'!J2 -> 0 | B135: 奉獻之誓 | C135: =IF($A$135>=3,"奉獻之誓法術","") | D135: =IF($A$135>=3,"引導神力：聖潔武器","") | E135: =IF($A$135>=7,"奉獻靈光","") | F135: =IF($A$135>=15,"衛護斬","") | G135: =IF($A$135>=20,"至聖光輪","")
A136: 聖武士 | B136: 榮耀之誓 | C136: =IF($A$135>=3,"榮耀之誓法術","") | D136: =IF($A$135>=3,"引導神力：鼓舞斬","") | E136: =IF($A$135>=3,"引導神力：絕倫健將","") | F136: =IF($A$135>=7,"迅捷靈光","") | G136: =IF($A$135>=15,"輝煌防禦","") | H136: =IF($A$135>=20,"現世傳說","")
B137: 遠古之誓 | C137: =IF($A$135>=3,"遠古之誓法術","") | D137: =IF($A$135>=3,"引導神力：自然之怒","") | E137: =IF($A$135>=7,"守御靈光","") | F137: =IF($A$135>=15,"不朽衛士","") | G137: =IF($A$135>=20,"遠古鬥士","")
B138: 復仇之誓 | C138: =IF($A$135>=3,"復仇之誓法術","") | D138: =IF($A$135>=3,"引導神力：仇敵誓言","") | E138: =IF($A$135>=7,"堅韌復仇","") | F138: =IF($A$135>=15,"復仇之魂","") | G138: =IF($A$135>=20,"復仇天使","")
B139: 巨靈貴族之誓 | C139: =IF($A$135>=3,"巨靈貴族之誓法術","") | D139: =IF($A$135>=3,"引導神力：元素打擊","") | E139: =IF($A$135>=3,"巨靈榮譽","") | F139: =IF($A$135>=7,"元素守護靈光","") | G139: =IF($A$135>=15,"元素喝斥","") | H139: =IF($A$135>=20,"貴族使徒","")
B140: 懲戒之誓 | C140: =IF($A$135>=3,"瘟疫之誓法術","") | D140: =IF($A$135>=3,"引導神力：懲戒","") | E140: =IF($A$135>=3,"引導神力：審問","") | F140: =IF($A$135>=7,"火種靈光","") | G140: =IF($A$135>=15,"熾熱審判","") | H140: =IF($A$135>=20,"硫磺烈火","")
B141: 狂歡之誓 | C141: =IF($A$135>=3,"狂歡之誓法術","") | D141: =IF($A$135>=3,"引導神力：召喚飲料","") | E141: =IF($A$135>=7,"兄弟會靈光","") | F141: =IF($A$135>=15,"歡樂製造者","") | G141: =IF($A$135>=20,"派對動物","")
B142: 守護之誓 | C142: =IF($A$135>=3,"守護之誓法術","") | D142: =IF($A$135>=3,"引導神力：防護干預","") | E142: =IF($A$135>=3,"刻印打擊","") | F142: =IF($A$135>=7,"守護之儀","") | G142: =IF($A$135>=7,"振奮防禦","") | H142: =IF($A$135>=15,"守護衛士","") | I142: =IF($A$135>=20,"守護天使","")
B143: 瘟疫之誓 | C143: =IF($A$135>=3,"瘟疫之誓法術","") | D143: =IF($A$135>=3,"引導神力：熵能感染","") | E143: =IF($A$135>=3,"衰弱熱疫","") | F143: =IF($A$135>=7,"染病靈光","") | G143: =IF($A$135>=15,"穢惡堅韌","") | H143: =IF($A$135>=20,"瘟疫使者","")
B144: 屠戮之誓 | C144: =IF($A$135>=3,"屠戮之誓法術","") | D144: =IF($A$135>=3,"引導神力：狂亂屠戮","") | E144: =IF($A$135>=7,"嗜血靈光","") | F144: =IF($A$135>=15,"斬盡殺絕","") | G144: =IF($A$135>=20,"鮮血騎士","")
B145: 狂熱之誓 | C145: =IF($A$135>=3,"狂熱之誓法術","") | D145: =IF($A$135>=3,"引導神力：異端印記","") | E145: =IF($A$135>=7,"明目靈光","") | F145: =IF($A$135>=15,"強迫認罪","") | G145: =IF($A$135>=20,"啟示錄","")
B146: 爐火之誓 | C146: =IF($A$135>=3,"爐火之誓法術","") | D146: =IF($A$135>=3,"引導神力：燃燒武器","") | E146: =IF($A$135>=7,"溫暖靈光","") | F146: =IF($A$135>=15,"隔絕護壁","") | G146: =IF($A$135>=20,"燃燒之魂","")
A157: ='職業能力'!L2 -> 0 | B157: 獸王 | C157: =IF($A$157>=3,"原初動物夥伴"&'職業能力選項'!AR3,"") | D157: =IF($A$157>=7,"超絕夥伴","") | E157: =IF($A$157>=11,"獸性狂怒","") | F157: =IF($A$157>=15,"法術共享","")
A158: 遊俠 | B158: 妖精漫遊者 | C158: =IF($A$157>=3,"妖精漫遊者法術","") | D158: =IF($A$157>=3,"哀懼靈襲","") | E158: =IF($A$157>=3,"異界魅力","") | F158: =IF($A$157>=7,"扭轉迷惑","") | G158: =IF($A$157>=11,"精類增援","") | H158: =IF($A$157>=15,"霧行漫遊者","")
B159: 幽域追蹤者 | C159: =IF($A$157>=3,"幽域追蹤者法術","") | D159: =IF($A$157>=3,"懼怖伏兵","") | E159: =IF($A$157>=3,"幽影視覺","") | F159: =IF($A$157>=7,"鋼鐵心智","") | G159: =IF($A$157>=11,"追獵如風","") | H159: =IF($A$157>=15,"暗影閃避","")
B160: 獵人 | C160: =IF($A$157>=3,"獵人學識","") | D160: =IF($A$157>=3,"狩者獵物"&'職業能力選項'!AR6,"") | E160: =IF($A$157>=7,"防守戰術"&'職業能力選項'!AR9,"") | F160: =IF($A$157>=11,"進階狩者獵物","") | G160: =IF($A$157>=15,"進階防守戰術","")
B161: 惡兆先驅 | C161: =IF($A$157>=3,"惡兆先驅法術","") | D161: =IF($A$157>=3,"死兆","") | E161: =IF($A$157>=7,"死劫先驅","") | F161: =IF($A$157>=11,"墳墓連結","") | G161: =IF($A$157>=15,"宿命已定","")
B162: 凜冬行者 | C162: =IF($A$157>=3,"冬日行者法術","") | D162: =IF($A$157>=3,"寒霜探險家","") | E162: =IF($A$157>=3,"獵者霧淞","") | F162: =IF($A$157>=7,"堅韌靈魂","") | G162: =IF($A$157>=11,"寒顫報應","") | H162: =IF($A$157>=15,"極凍獵殺","")
B163: 荒徑守護者 | C163: =IF($A$157>=3,"荒徑守護者法術","") | D163: =IF($A$157>=3,"協同戰術","") | E163: =IF($A$157>=3,"引路","") | F163: =IF($A$157>=7,"戰術突襲","") | G163: =IF($A$157>=11,"協同奮戰","") | H163: =IF($A$157>=15,"群體突擊","")
B164: 綠林死神 | C164: =IF($A$157>=3,"綠林死神法術","") | D164: =IF($A$157>=3,"淬毒攻擊","") | E164: =IF($A$157>=3,"製毒工藝","") | F164: =IF($A$157>=7,"劇毒掌控","") | G164: =IF($A$157>=11,"千變萬毒","") | H164: =IF($A$157>=15,"痛苦耐受","")
B165: 原初射手 | C165: =IF($A$157>=3,"原初射手法術","") | D165: =IF($A$157>=3,"元素箭矢","") | E165: =IF($A$157>=3,"草藥學識","") | F165: =IF($A$157>=7,"編織元素","") | G165: =IF($A$157>=11,"巫術箭矢","") | H165: =IF($A$157>=15,"原初魔法","")
B166: 鼠群之王 | C166: =IF($A$157>=3,"鼠群之王法術","") | D166: =IF($A$157>=3,"害獸親族","") | E166: =IF($A$157>=3,"集群打擊","") | F166: =IF($A$157>=7,"污穢強韌","") | G166: =IF($A$157>=11,"感染擴散","") | H166: =IF($A$157>=15,"群集之力","")
B167: 凜冬陷阱師 | C167: =IF($A$157>=3,"凜冬陷阱師法術","") | D167: =IF($A$157>=3,"動彈不得","") | E167: =IF($A$157>=7,"極地掠食者","") | F167: =IF($A$157>=11,"魔法圈套","") | G167: =IF($A$157>=15,"絆倒防禦","")
B168: 大獸獵家 | C168: =IF($A$157>=3,"遠程特化","") | D168: =IF($A$157>=3,"遊戲狩獵","") | E168: =IF($A$157>=7,"進階拋石索",IF($A$157>=3,"拋石索","")) | F168: =IF($A$157>=11,"進階射擊技巧",IF($A$157>=7,"射擊技巧","")) | G168: =IF($A$157>=11,"精瞄","") | H168: =IF($A$157>=15,"頂級獵人","") | I168: =IF($A$157>=15,"掠食者直覺","") | J168: =IF($A$157>=15,"狩獵完成","")
A179: ='職業能力'!M2 -> 0 | B179: 詭術師 | C179: =IF($A$179>=3,"施法","") | D179: =IF($A$179>=3,"法師之手詐術","") | E179: =IF($A$179>=9,"詭術伏擊","") | F179: =IF($A$179>=13,"萬能詭術","") | G179: =IF($A$179>=17,"法術竊賊","")
A180: 盜賊 | B180: 刺客 | C180: =IF($A$179>=3,"暗殺","") | D180: =IF($A$179>=3,"刺客工具","") | E180: =IF($A$179>=9,"專業滲透","") | F180: =IF($A$179>=13,"淬毒武器","") | G180: =IF($A$179>=17,"死亡一擊","")
...

Sheet 職業能力
A1: =IF('請先閱讀'!F34=true,"奇械師-Artificer","") -> 奇械師-Artificer | B1: 野蠻人-Barbarian | C1: 吟遊詩人-Bard | D1: 牧師-Cleric | E1: 德魯伊-Druid | F1: 戰士-Fighter | G1: =IF('請先閱讀'!O29=true,"銃士-Gunslinger","") | H1: 武僧-Monk | I1: =IF('請先閱讀'!O31=true,"怪物獵人-Monster Hunter","") | J1: 聖騎士-Paladin | K1: =IF('請先閱讀'!O34=true,"拳鬥士-Pugilist","") | L1: 遊俠-Ranger | M1: 盜賊-Rogue | N1: 術士-Sorcerer | O1: 契術師-Warlock | P1: 法師-Wizard
A2: =IFNA(VLOOKUP(A1,'角色卡'!$AB$16:$AM$18,11,FALSE),0) -> 0 | B2: =IFNA(VLOOKUP(B1,'角色卡'!$AB$16:$AM$18,11,FALSE),0) -> 0 | C2: =IFNA(VLOOKUP(C1,'角色卡'!$AB$16:$AM$18,11,FALSE),0) -> 0 | D2: =IFNA(VLOOKUP(D1,'角色卡'!$AB$16:$AM$18,11,FALSE),0) -> 0 | E2: =IFNA(VLOOKUP(E1,'角色卡'!$AB$16:$AM$18,11,FALSE),0) -> 0 | F2: =IFNA(VLOOKUP(F1,'角色卡'!$AB$16:$AM$18,11,FALSE),0) -> 0 | G2: =IFNA(VLOOKUP(G1,'角色卡'!$AB$16:$AM$18,11,FALSE),0) -> 0 | H2: =IFNA(VLOOKUP(H1,'角色卡'!$AB$16:$AM$18,11,FALSE),0) -> 0 | ... P2: =IFNA(VLOOKUP(P1,'角色卡'!$AB$16:$AM$18,11,FALSE),0) -> 3
A3: =IF($A$2>=1,"施法","") | B3: =IF(B2>=1,"狂暴("&IF(B2>=16,"+4",IF(B2>=9,"+3","+2"))&"/"&IF(B2>=17,"6次",IF(B2>=12,"5次",IF(B2>=6,"4次",IF(B2>=3,"3次","2次"))))&")","") | C3: =IF(C2>=1,"吟遊激勵("&IF(C2>=15,"1d12",IF(C2>=10,"1d10",IF(C2>=5,"1d8","1d6")))&")","") | D3: =IF(D$2>=1,"施法","") | E3: =IF(E$2>=1,"施法","") | F3: =IF(F$2>=1,"戰鬥風格","") | G3: =IF(G$2>=1,"戰鬥風格","") | H3: =IF(H2>=1,"武藝("&IF(H2>=17,"1d12",IF(H2>=11,"1d10",IF(H2>=5,"1d8","1d6")))&")","") | I3: =IF(I$2>=1,"怪物寶典("&IF(I2>=13,"4",IF(H2>=6,"3","2"))&"種)","") | J3: =IF(J$2>=1,"聖療("&5*J2&"點)","") | K3: =IF(K$2>=1,"拳鬥("&IF(K$2>=17,"2d6",IF(K$2>=11,"1d12",IF(K$2>=5,"1d10","1d8")))&")","") | L3: =IF(L$2>=1,"施法","") | M3: =IF(M$2>=1,"專精"&IF(M2>=6,"(4種)","(2種)"),"") | N3: =IF(N$2>=1,"施法","") | O3: =IF(O$2>=1,"魔能祈喚"&IF(O2>=18,"(10項)",IF(O2>=15,"(9項)",IF(O2>=12,"(8項)",IF(O2>=9,"(7項)",IF(O2>=7,"(6項)",IF(O2>=5,"(5項)",IF(O2>=2,"(3項)","(1項)"))))))),"") | P3: =IF(P$2>=1,"施法","") -> 施法
A4: =IF($A$2>=1,"工藝魔法","") | B4: =IF(B2>=1,"無甲防禦","") | C4: =IF(C2>=1,"施法","") | D4: =IF(D2>=1,"聖職"&'職業能力選項'!N3,"") | E4: =IF(E$2>=1,"德魯伊語","") | F4: =IF(F2>=1,"回氣"&IF(F2>=10,"(4次)",IF(F2>=4,"(3次)","(2次)")),"") | G4: =IF(G$2>=1,"快速拔槍","") | H4: =IF(H$2>=1,"無甲防禦","") | I4: =IF(I$2>=1,"武器精通"&IF(I$2>=16,"(5種)",IF(I$2>=11,"(4種)",IF(I$2>=5,"(3種)","(2種)"))),"") | J4: =IF(J$2>=1,"施法","") | K4: =IF(K$2>=1,"硬骨頭","") | L4: =IF(L2>=1,"宿敵("&ROUNDUP(L2/4+1,0)&"次)","") | M4: =IF(M$2>=1,"偷襲("&ROUNDUP(M2/2,0)&"d6)","") | N4: =IF(N$2>=1,"先天術法","") | O4: =IF(O$2>=1,"契約魔法","") | P4: =IF(P$2>=1,"儀式學家","") -> 儀式學家
A5: =IF($A$2>=2,"再現魔法物品","") | B5: =IF(B2>=1,"武器精通"&IF(B2>=10,"(4種)",IF(B2>=4,"(3種)","(2種)")),"") | C5: =IF(C2>=2,"專精"&IF(C2>=9,"(4種)","(2種)"),"") | D5: =IF(D2>=2,"引導神力"&IF(D2>=18,"(4次)",IF(D2>=6,"(3次)","(2次)")),"") | E5: =IF(E$2>=1,"原初職責"&'職業能力選項'!R3,"") | F5: =IF(F2>=1,"武器精通"&IF(F2>=16,"(6種)",IF(F2>=10,"(5種)",IF(F2>=4,"(4種)","(3種)"))),"") | G5: =IF(G$2>=1,"武器精通"&IF(G$2>=10,"(4種)",IF(G$2>=4,"(3種)","(2種)")),"") | H5: =IF(H$2>=2,"武僧武功("&H2&"點)","") | I5: =IF(I$2>=2,"戰鬥風格","") | J5: =IF(J$2>=1,"武器精通(2種)","") | K5: =IF(K$2>=2,"膽識("&ROUNDDOWN(K2/2,0)+1+IF(K2>=19,1,0)&"點)","") | L5: =IF(L$2>=1,"武器精通(2種)","") | M5: =IF(M$2>=1,"竊賊黑話","") | N5: =IF(N$2>=2,"魔力泉湧("&N2&"點)","") | O5: =IF(O$2>=2,"祕法回流","") | P5: =IF(P$2>=1,"奧術恢復("&ROUNDUP(P2/2,0)&"個環位)","") -> 奧術恢復(2個環位)
A6: =IF($A$2>=2," - "&IF(A2>=18,"8個方案/6個物品",IF(A2>=14,"7個方案/5個物品",IF(A2>=10,"6個方案/4個物品",IF(A2>=6,"5個方案/3個物品","4個方案/2個物品")))),"") | B6: =IF(B2>=2,"險境感知","") | C6: =IF(C2>=2,"全能高手","") | D6: =IF(D2>=2,"-引導神力：神聖火花"&IF(D2>=18,"(4d8)",IF(D2>=13,"(3d8)",IF(D2>=7,"(2d8)","(1d8)"))),"") | E6: =IF(E$2>=2,"荒野型態"&IF(E2>=17,"(4次/",IF(E2>=6,"(3次/","(2次/"))&IF(E2>=8,"8種)",IF(E2>=4,"6種)","4種)")),"") | F6: =IF(F2>=2,"動作如潮"&IF(F2>=17,"(2次)","(1次)"),"") | G6: =IF(G$2>=2,"致命射擊","") | H6: =IF(H2>=2,"無甲移動(+"&IF(H2>=18,30,IF(H2>=14,25,IF(H2>=10,20,IF(H2>=6,15,10))))&"呎)","") | I6: =IF(I$2>=2,"研習應對","") | J6: =IF(J$2>=2,"戰鬥風格","") | K6: =IF(K$2>=2,"見血不屈","") | L6: =IF(L$2>=2,"熟練探險家","") | M6: =IF(M$2>=1,"武器精通","") | N6: =IF(N$2>=2,"超魔法("&IF(N2>=17,6,IF(N2>=10,4,2))&"項)","") | O6: =IF(O$2>=9,"聯繫宗主","") | P6: =IF(P$2>=2,"學者","") -> 學者
A7: =IF($A$2>=6,"魔法物品工藝","") | B7: =IF(B2>=2,"魯莽攻擊","") | C7: =IF(C2>=5,"激勵湧泉","") | D7: =IF(D2>=2,"-引導神力：驅散亡靈","") | E7: =IF(E$2>=2,"荒野夥伴","") | F7: =IF(F$2>=2,"戰術思維","") | G7: =IF(G$2>=2,"犯險","") | H7: =IF(H$2>=2,"運轉周天","") | I7: =IF(I$2>=5,"精準打擊","") | J7: =IF(J$2>=2,"聖騎士斬擊","") | K7: =IF(K$2>=2,"強運","") | L7: =IF(L$2>=2,"戰鬥風格","") | M7: =IF(M$2>=2,"靈巧動作","") | N7: =IF(N$2>=5,"術法復甦(恢復"&ROUNDDOWN(N2/2,0)&"點)","") | O7: =IF(O$2>=11,"玄奥秘法(6~"&IF(O2>=17,9,ROUNDUP(O2/2,0))&"環)","") | P7: =IF(P$2>=5,"記憶法術","")
A8: =IF($A$2>=7,"靈光一閃","") | B8: =IF(B2>=3,"原初學識","") | C8: =IF(C2>=7,"反制迷惑","") | D8: =IF(D2>=5,"灼淨亡靈","") | E8: =IF(E$2>=5,"荒野復甦","") | F8: =IF(F2>=5,"額外攻擊"&IF(F2>=20,"(三)",IF(F2>=11,"(二)","")),"") | G8: =IF(G$2>=5,"額外攻擊","") | H8: =IF(H$2>=3,"撥檔攻擊","") | I8: =IF(I$2>=6,"進階怪物寶典","") | J8: =IF(J2>=3,"引導神力"&IF(J2>=11,"(3次)","(2次)"),"") | K8: =IF(K$2>=3,"重拳出擊","") | L8: =IF(L$2>=5,"額外攻擊","") | M8: =IF(M$2>=3,"手穩就準","") | N8: =IF(N$2>=7,"術法化身","") | O8: =IF(O$2>=20,"魔能掌控","") | P8: =IF(P$2>=18,"法術精通","")
A9: =IF($A$2>=10,"魔法物品熟稔","") | B9: =IF(B2>=5,"額外攻擊","") | C9: =IF(C2>=10,"魔法秘密","") | D9: =IF(D2>=7,"受祝擊"&'職業能力選項'!N6,"") | E9: =IF(E$2>=7,"元素狂怒"&'職業能力選項'!R16,"") | F9: =IF(F$2>=5,"戰術位移","") | G9: =IF(G$2>=5,"內臟射擊","") | H9: =IF(H$2>=4,"輕身墜","") | I9: =IF(I$2>=9,"博學防禦","") | J9: =IF(J$2>=3,"-引導神力：神聖感知","") | K9: =IF(K$2>=4,"全力以赴","") | L9: =IF(L$2>=6,"越野","") | M9: =IF(M$2>=5,"詭詐打擊","") | N9: =IF(N$2>=20,"奧術登神","") | P9: =IF(P$2>=20,"招牌法術","")
A10: =IF($A$2>=11,"儲法物品","") | B10: =IF(B2>=5,"快速移動","") | C10: =IF(C2>=18,"卓越激勵","") | D10: =IF(D2>=10,"神力干預","") | E10: =IF(E$2>=15,"強化元素狂怒","") | F10: =IF(F2>=9,"不屈"&IF(F2>=17,"(3次)",IF(F2>=13,"(2次)","(1次)")),"") | G10: =IF(G$2>=7,"反射閃避","") | H10: =IF(H$2>=5,"額外攻擊","") | I10: =IF(I$2>=11,"額外攻擊","") | J10: =IF(J$2>=5,"額外攻擊","") | K10: =IF(K$2>=5,"強力一擊","") | L10: =IF(L$2>=9,"專精","") | M10: =IF(M$2>=5,"直覺閃避","")
A11: =IF($A$2>=14,"進階技藝","") | B11: =IF(B2>=7,"野性直覺","") | C11: =IF(C2>=20,"創造之言","") | D11: =IF(D2>=14,"強化受祝擊","") | E11: =IF(E$2>=18,"野獸施法","") | F11: =IF(F$2>=9,"戰術大師","") | G11: =IF(G$2>=11,"趕盡殺絕","") | H11: =IF(H$2>=5,"震懾拳","") | I11: =IF(I$2>=13,"高等怪物寶典","") | J11: =IF(J$2>=5,"虔誠坐騎","") | K11: =IF(K$2>=6,"壯膽之拳","") | L11: =IF(L$2>=10,"不知疲倦","") | M11: =IF(M$2>=7,"反射閃避","")
A12: =IF($A$2>=18,"魔法物品大師","") | B12: =IF(B2>=7,"直覺猛撲","") | D12: =IF(D2>=20,"進階神聖干預","") | E12: =IF(E$2>=20,"大德魯伊","") | F12: =IF(F$2>=13,"分析攻擊","") | G12: =IF(G$2>=13,"死亡欺詐","") | H12: =IF(H$2>=6,"真氣注拳","") | I12: =IF(I$2>=1,"巢穴感知","") | J12: =IF(J$2>=6,"守護靈光","") | K12: =IF(K$2>=7,"潦而不倒","") | L12: =IF(L$2>=13,"無盡追獵","") | M12: =IF(M$2>=7,"可靠才能","")
A13: =IF($A$2>=20,"技藝之魂","") | B13: =IF(B2>=9,"兇猛打擊","") | G13: =IF(G$2>=15,"險境博弈","") | H13: =IF(H$2>=7,"反射閃避","") | I13: =IF(I$2>=17,"屠戮者援助","") | J13: =IF(J$2>=9,"引導神力：斥退眾敵","") | K13: =IF(K$2>=9,"硬漢訓練","") | L13: =IF(L$2>=14,"自然面紗","") | M13: =IF(M$2>=11,"強化詭詐打擊","")
B14: =IF(B2>=11,"頑強狂暴","") | G14: =IF(G$2>=18,"靈巧戰技","") | H14: =IF(H$2>=9,"飛簷走壁","") | I14: =IF(I$2>=20,"送葬一擊","") | J14: =IF(J$2>=10,"勇氣靈光","") | K14: =IF(K$2>=10,"大力士","") | L14: =IF(L$2>=17,"致命獵殺","") | M14: =IF(M$2>=14,"凶狡打擊","")
B15: =IF(B2>=13,"強化兇猛打擊","") | G15: =IF(G$2>=20,"爆頭","") | H15: =IF(H$2>=10,"出神入化","") | J15: =IF(J$2>=11,"光耀打擊","") | K15: =IF(K$2>=10,"通通甩掉","") | L15: =IF(L$2>=18,"野性感官","") | M15: =IF(M$2>=15,"靈活心智","")
B16: =IF(B2>=15,"持久狂暴","") | H16: =IF(H$2>=10,"返本還元","") | J16: =IF(J$2>=14,"復原之觸","") | K16: =IF(K$2>=13,"推進極限","") | L16: =IF(L$2>=20,"眾敵屠戮","") | M16: =IF(M$2>=18,"捉摸不定","")
B17: =IF(B2>=17,"強化兇猛打擊","") | H17: =IF(H$2>=13,"撥檔能量","") | J17: =IF(J$2>=18,"靈光延展","") | K17: =IF(K$2>=14,"不可撼動","") | M17: =IF(M$2>=20,"幸運一擊","")
B18: =IF(B2>=18,"不屈勇武","") | H18: =IF(H$2>=14,"圓融自在","") | K18: =IF(K$2>=15,"好鬥","")
B19: =IF(B2>=20,"原初勇士","") | H19: =IF(H$2>=15,"明鏡止水","") | K19: =IF(K$2>=18,"鬥魂","")
H20: =IF(H$2>=18,"無懈可擊","") | K20: =IF(K$2>=20,"巔峰體格","")
H21: =IF(H$2>=20,"身心合一","")

Sheet 背景
A1: 背景 | B1: 出處 | C1: 屬性值提升 | F1: 專長 | G1: 技能熟練 | I1: 工具熟練
A2: 侍僧 Acolyte | B2: PHB | C2: 智力 | D2: 感知 | E2: 魅力 | F2: 魔法學徒(牧師) Magic Initiate | G2: 察言觀色 | H2: 宗教 | I2: 書法工具
A3: 工匠 Artisan | B3: PHB | C3: 力量 | D3: 敏捷 | E3: 智力 | F3: 匠心 Crafter | G3: 調查 | H3: 說服 | I3: 任一種工匠工具
A4: 詐欺師 Charlatan | B4: PHB | C4: 敏捷 | D4: 體魄 | E4: 魅力 | F4: 技巧嫻熟 Skilled | G4: 欺瞞 | H4: 巧手 | I4: 文書偽造工具
A5: 罪犯 Criminal | B5: PHB | C5: 敏捷 | D5: 體魄 | E5: 智力 | F5: 警覺 Alert | G5: 巧手 | H5: 隱匿 | I5: 竊賊工具
A6: 藝人 Entertainer | B6: PHB | C6: 力量 | D6: 敏捷 | E6: 魅力 | F6: 音樂家 Musician | G6: 特技動作 | H6: 表演 | I6: 任一種樂器
A7: 農夫 Farmer | B7: PHB | C7: 力量 | D7: 體魄 | E7: 感知 | F7: 健壯 Tough | G7: 動物馴服 | H7: 自然 | I7: 木匠工具
A8: 衛兵 Guard | B8: PHB | C8: 力量 | D8: 智力 | E8: 感知 | F8: 警覺 Alert | G8: 運動 | H8: 察覺 | I8: 任一種賭具
A9: 嚮導 Guide | B9: PHB | C9: 敏捷 | D9: 體魄 | E9: 感知 | F9: 魔法學徒(德魯伊) Magic Initiate | G9: 隱匿 | H9: 求生 | I9: 製圖工具
A10: 隱士 Hermit | B10: PHB | C10: 體魄 | D10: 感知 | E10: 魅力 | F10: 治療師 Healer | G10: 醫藥 | H10: 宗教 | I10: 草藥工具
A11: 商人 Merchant | B11: PHB | C11: 體魄 | D11: 智力 | E11: 魅力 | F11: 幸運 Lucky | G11: 動物馴服 | H11: 說服 | I11: 領航工具
A12: 貴族 Noble | B12: PHB | C12: 力量 | D12: 智力 | E12: 魅力 | F12: 技巧嫻熟 Skilled | G12: 歷史 | H12: 說服 | I12: 任一種賭具
A13: 學者 Sage | B13: PHB | C13: 體魄 | D13: 智力 | E13: 感知 | F13: 魔法學徒(法師) Magic Initiate | G13: 奧秘 | H13: 歷史 | I13: 書法工具
... A17: 遠行者 Wayfarer | B17: PHB | C17: 敏捷 | D17: 感知 | E17: 魅力 | F17: 幸運 Lucky | G17: 察言觀色 | H17: 隱匿 | I17: 竊賊工具
A18: 自定義背景 Custom | B18: DMG | C18: 自定義
A19: =if('請先閱讀'!$F$31=true,"瓊達斯浪人 Chondathan Freebooter","") -> 瓊達斯浪人 Chondathan Freebooter | B19: FRHoF | C19: 力量 | D19: 敏捷 | E19: 感知 | F19: 技巧嫻熟 Skilled | G19: 運動 | H19: 巧手 | I19: 紡織工具
A20: =if('請先閱讀'!$F$31=true,"死亡魔法住民 Dead Magic Dweller","") -> 死亡魔法住民 Dead Magic Dweller | B20: FRHoF | C20: 力量 | D20: 體魄 | E20: 感知 | F20: 治療師 Healer | G20: 醫藥 | H20: 求生 | I20: 皮匠工具
A21: =if('請先閱讀'!$F$31=true,"拜龍教徒 Dragon Cultist","") -> 拜龍教徒 Dragon Cultist | B21: FRHoF | C21: 敏捷 | D21: 體魄 | E21: 智力 | F21: 拜龍教新晉者 Cult of the Dragon Initiate | G21: 欺瞞 | H21: 隱匿 | I21: 書法工具
A22: =if('請先閱讀'!$F$31=true,"翠綠閑庭守門人 Emerald Enclave Caretaker","") -> 翠綠閑庭守門人 Emerald Enclave Caretaker | B22: FRHoF | C22: 體魄 | D22: 智力 | E22: 感知 | F22: 翠綠閑庭雛鳥 Emerald Enclave Fledgling | G22: 自然 | H22: 求生 | I22: 草藥工具
A23: =if('請先閱讀'!$F$31=true,"焰拳傭兵 Flaming Fist Mercenary","") -> 焰拳傭兵 Flaming Fist Mercenary | B23: FRHoF | C23: 力量 | D23: 體魄 | E23: 魅力 | F23: 健壯 Tough | G23: 威嚇 | H23: 察覺 | I23: 鐵匠工具
A24: =if('請先閱讀'!$F$31=true,"巨靈觸碰 Genie Touched","") -> 巨靈觸碰 Genie Touched | B24: FRHoF | C24: 敏捷 | D24: 感知 | E24: 魅力 | F24: 魔法學徒(法師) Magic Initiate | G24: 察覺 | H24: 說服 | I24: 玻璃匠工具
A25: =if('請先閱讀'!$F$31=true,"豎琴手 Harper","") -> 豎琴手 Harper | B25: FRHoF | C25: 敏捷 | D25: 智力 | E25: 魅力 | F25: 豎琴手特工 Harper Agent | G25: 表演 | H25: 巧手 | I25: 易容工具
A26: =if('請先閱讀'!$F$31=true,"冰釣者 Ice Fisher","") -> 冰釣者 Ice Fisher | B26: FRHoF | C26: 力量 | D26: 敏捷 | E26: 體魄 | F26: 警覺 Alert | G26: 動物馴服 | H26: 運動 | I26: 木雕工具
A27: =if('請先閱讀'!$F$31=true,"鐵腕騎士 Knight of the Gauntlet","") -> 鐵腕騎士 Knight of the Gauntlet | B27: FRHoF | C27: 力量 | D27: 智力 | E27: 感知 | F27: 鐵腕新手 Tyro of the Gauntlet | G27: 運動 | H27: 醫藥 | I27: 鐵匠工具
A28: =if('請先閱讀'!$F$31=true,"領主聯盟附庸 Lords' Alliance Vassal","") -> 領主聯盟附庸 Lords' Alliance Vassal | B28: FRHoF | C28: 力量 | D28: 智力 | E28: 魅力 | F28: 領主聯盟特工 Lords' Alliance Agent | G28: 察言觀色 | H28: 說服 | I28: 書法工具
A29: =if('請先閱讀'!$F$31=true,"月之井朝聖者 Moonwell Pilgrim","") -> 月之井朝聖者 Moonwell Pilgrim | B29: FRHoF | C29: 體魄 | D29: 感知 | E29: 魅力 | F29: 魔法學徒(德魯伊) Magic Initiate | G29: 自然 | H29: 表演 | I29: 畫家工具
A30: =if('請先閱讀'!$F$31=true,"穆爾霍蘭德盜墓者 Mulhorandi Tomb Raider","") -> 穆爾霍蘭德盜墓者 Mulhorandi Tomb Raider | B30: FRHoF | C30: 敏捷 | D30: 智力 | E30: 感知 | F30: 幸運 Lucky | G30: 調查 | H30: 宗教 | I30: 石匠工具
A31: =if('請先閱讀'!$F$31=true,"祕法守密人 Mythalkeeper","") -> 祕法守密人 Mythalkeeper | B31: FRHoF | C31: 智力 | D31: 感知 | E31: 魅力 | F31: 匠心 Crafter | G31: 奧秘 | H31: 歷史 | I31: 珠寶匠工具
A32: =if('請先閱讀'!$F$31=true,"紫龍禁衛軍 Purple Dragon Squire","") -> 紫龍禁衛軍 Purple Dragon Squire | B32: FRHoF | C32: 力量 | D32: 感知 | E32: 魅力 | F32: 紫龍堡壘 Purple Dragon Rook | G32: 動物馴服 | H32: 察言觀色 | I32: 領航工具
A33: =if('請先閱讀'!$F$31=true,"萊瑟曼漫遊者 Rashemi Wanderer","") -> 萊瑟曼漫遊者 Rashemi Wanderer | B33: FRHoF | C33: 力量 | D33: 體魄 | E33: 魅力 | F33: 健壯 Tough | G33: 威嚇 | H33: 察覺 | I33: 製圖工具
A34: =if('請先閱讀'!$F$31=true,"暗影大師流亡者 Shadowmasters Exile","") -> 暗影大師流亡者 Shadowmasters Exile | B34: FRHoF | C34: 敏捷 | D34: 智力 | E34: 魅力 | F34: 野蠻攻擊者 Savage Attacker | G34: 特技動作 | H34: 隱匿 | I34: 竊賊工具
A35: =if('請先閱讀'!$F$31=true,"咒火學徒 Spellfire Initiate","") -> 咒火學徒 Spellfire Initiate | B35: FRHoF | C35: 體魄 | D35: 智力 | E35: 魅力 | F35: 咒火火花 Spellfire Spark | G35: 奧秘 | H35: 察覺 | I35: 任一種賭具
A36: =if('請先閱讀'!$F$31=true,"散塔林傭兵 Zhentarim Mercenary","") -> 散塔林傭兵 Zhentarim Mercenary | B36: FRHoF | C36: 力量 | D36: 敏捷 | E36: 魅力 | F36: 散塔林暴徒 Zhentarim Ruffian | G36: 威嚇 | H36: 察覺 | I36: 文書偽造工具
A37: =if('請先閱讀'!F32=true,"洛溫專家 Lorwyn Expert","") -> 洛溫專家 Lorwyn Expert | B37: LFL | C37: 力量 | D37: 體魄 | E37: 感知 | F37: 太陽之子 Child of the Sun | G37: 運動 | H37: 自然 | I37: 製圖工具
A38: =if('請先閱讀'!F32=true,"闇影荒原專家 Shadowmoor Expert","") -> 闇影荒原專家 Shadowmoor Expert | B38: LFL | C38: 敏捷 | D38: 智力 | E38: 魅力 | F38: 闇影荒原咒術師 Shadowmoor Hexer | G38: 特技動作 | H38: 欺瞞 | I38: 玻璃匠工具
A39: =if('請先閱讀'!F33=true,"縱情者 Carouser","") -> 縱情者 Carouser | B39: ABoH | C39: 敏捷 | D39: 智力 | E39: 魅力 | F39: 不倦狂歡 Tireless Reveler | G39: 欺瞞 | H39: 說服 | I39: 任一賭具
A40: =if('請先閱讀'!F33=true,"吸血鬼信徒 Vampire Devotee","") -> 吸血鬼信徒 Vampire Devotee | B40: ABoH | C40: 力量 | D40: 體魄 | E40: 魅力 | F40: 吸血鬼玩物 Vampire's Plaything | G40: 說服 | H40: 隱匿 | I40: 廚師工具
A41: =if('請先閱讀'!F33=true,"吸血鬼倖存者 Vampire Survivor","") -> 吸血鬼倖存者 Vampire Survivor | B41: ABoH | C41: 敏捷 | D41: 體魄 | E41: 感知 | F41: 吸血鬼獵者 Vampire Hunter | G41: 察言觀色 | H41: 宗教 | I41: 木雕工具
A42: =if('請先閱讀'!$F$34=true,"異族繼承人 Aberrant Heir","") -> 異族繼承人 Aberrant Heir | B42: EFA | C42: 力量 | D42: 體魄 | E42: 魅力 | F42: 異族龍紋 Aberrant Dragonmark | G42: 歷史 | H42: 威嚇 | I42: 易容工具
A43: =if('請先閱讀'!$F$34=true,"考古學家 Archaeologist","") -> 考古學家 Archaeologist | B43: EFA | C43: 敏捷 | D43: 智力 | E43: 感知 | F43: 技巧嫻熟 Skilled | G43: 歷史 | H43: 求生 | I43: 製圖工具
A44: =if('請先閱讀'!$F$34=true,"家族特務 House Agent","") -> 家族特務 House Agent | B44: EFA | C44: 力量 | D44: 智力 | E44: 魅力 | F44: 幸運 Lucky | G44: 調查 | H44: 說服 | I44: 任一種工匠工具
A45: =if('請先閱讀'!$F$34=true,"坎尼斯家族繼承人 House Cannith Heir","") -> 坎尼斯家族繼承人 House Cannith Heir | B45: EFA | C45: 力量 | D45: 敏捷 | E45: 智力 | F45: 創造龍紋 Mark of Making | G45: 調查 | H45: 巧手 | I45: 任一種工匠工具
A46: =if('請先閱讀'!$F$34=true,"德恩奈家族繼承人 House Deneith Heir","") -> 德恩奈家族繼承人 House Deneith Heir | B46: EFA | C46: 力量 | D46: 體魄 | E46: 感知 | F46: 守護龍紋 Mark of Sentinel | G46: 察言觀色 | H46: 欺瞞 | I46: 任一種賭具
A47: =if('請先閱讀'!$F$34=true,"加蘭達家族繼承人 House Ghallanda Heir","") -> 加蘭達家族繼承人 House Ghallanda Heir | B47: EFA | C47: 敏捷 | D47: 感知 | E47: 魅力 | F47: 招待龍紋 Mark of Hospitality | G47: 察言觀色 | H47: 說服 | I47: 廚師工具
A48: =if('請先閱讀'!$F$34=true,"喬拉斯科家族繼承人 House Jorasco Heir","") -> 喬拉斯科家族繼承人 House Jorasco Heir | B48: EFA | C48: 敏捷 | D48: 體魄 | E48: 感知 | F48: 醫療龍紋 Mark of Healing | G48: 醫藥 | H48: 求生 | I48: 草藥工具
A49: =if('請先閱讀'!$F$34=true,"昆達拉克家族繼承人 House Kundarak Heir","") -> 昆達拉克家族繼承人 House Kundarak Heir | B49: EFA | C49: 力量 | D49: 體魄 | E49: 智力 | F49: 警戒龍紋 Mark of Warding | G49: 奧秘 | H49: 調查 | I49: 竊賊工具
A50: =if('請先閱讀'!$F$34=true,"萊蘭德家族繼承人 House Lyrandar Heir","") -> 萊蘭德家族繼承人 House Lyrandar Heir | B50: EFA | C50: 力量 | D50: 敏捷 | E50: 魅力 | F50: 暴風龍紋 Mark of Storm | G50: 特技動作 | H50: 自然 | I50: 領航工具
A51: =if('請先閱讀'!$F$34=true,"梅達尼家族繼承人 House Medani Heir","") -> 梅達尼家族繼承人 House Medani Heir | B51: EFA | C51: 敏捷 | D51: 智力 | E51: 感知 | F51: 偵測龍紋 Mark of Detection | G51: 察言觀色 | H51: 調查 | I51: 易容工具
A52: =if('請先閱讀'!$F$34=true,"歐瑞恩家族繼承人 House Orien Heir","") -> 歐瑞恩家族繼承人 House Orien Heir | B52: EFA | C52: 敏捷 | D52: 體魄 | E52: 智力 | F52: 通行龍紋 Mark of Passage | G52: 特技動作 | H52: 運動 | I52: 製圖工具
A53: =if('請先閱讀'!$F$34=true,"菲奧蘭家族繼承人 House Phiarlan Heir","") -> 菲奧蘭家族繼承人 House Phiarlan Heir | B53: EFA | C53: 敏捷 | D53: 感知 | E53: 魅力 | F53: 陰影龍紋 Mark of Shadow | G53: 欺瞞 | H53: 隱匿 | I53: 易容工具
A54: =if('請先閱讀'!$F$34=true,"西維斯家族繼承人 House Sivis Heir","") -> 西維斯家族繼承人 House Sivis Heir | B54: EFA | C54: 智力 | D54: 感知 | E54: 魅力 | F54: 抄錄龍紋 Mark of Scribing | G54: 歷史 | H54: 察覺 | I54: 書法工具
A55: =if('請先閱讀'!$F$34=true,"薩拉釋克家族繼承人 House Tharashk Heir","") -> 薩拉釋克家族繼承人 House Tharashk Heir | B55: EFA | C55: 體魄 | D55: 智力 | E55: 感知 | F55: 探索龍紋 Mark of Finding | G55: 察覺 | H55: 求生 | I55: 任一種賭具
A56: =if('請先閱讀'!$F$34=true,"圖蘭尼家族繼承人 House Thuranni Heir","") -> 圖蘭尼家族繼承人 House Thuranni Heir | B56: EFA | C56: 敏捷 | D56: 智力 | E56: 魅力 | F56: 陰影龍紋 Mark of Shadow | G56: 表演 | H56: 隱匿 | I56: 任一種樂器
A57: =if('請先閱讀'!$F$34=true,"瓦達利斯家族繼承人 House Vadalis Heir","") -> 瓦達利斯家族繼承人 House Vadalis Heir | B57: EFA | C57: 體魄 | D57: 感知 | E57: 魅力 | F57: 畜牧龍紋 Mark of Handling | G57: 動物馴服 | H57: 自然 | I57: 草藥工具
A58: =if('請先閱讀'!$F$34=true,"調查員 Inquisitive","") -> 調查員 Inquisitive | B58: EFA | C58: 體魄 | D58: 智力 | E58: 魅力 | F58: 警覺 Alert | G58: 察言觀色 | H58: 調查 | I58: 竊賊工具
A59: =if('請先閱讀'!$F$36=true,"契約尋者 Pact Seeker","") | B59: DDBD | C59: 體魄 | D59: 智力 | E59: 魅力 | F59: 任一位面契約專長 | G59: 奧秘 | H59: 說服 | I59: 書法工具
A60: =IF('請先閱讀'!$O$27=true,"失憶 Amnesiac","") | B60: ='請先閱讀'!M$27 -> TCM | C60: 自定義 | F60: 記憶飢渴 Memory Starved
A61: =IF('請先閱讀'!$O$27=true,"猩紅求道者 Crimson Aspirant","") | B61: ='請先閱讀'!M$27 -> TCM | C61: 自定義 | F61: 猩紅祭儀師 Crimson Ritualist | G61: 奧秘 | H61: 醫藥 | I61: 草藥工具
A62: =IF('請先閱讀'!$O$27=true,"十字路賭徒 Crossroads Gambler","") | B62: ='請先閱讀'!M$27 -> TCM | C62: 自定義 | F62: 命運賭徒 Fate Gambler | G62: 欺瞞 | H62: 察言觀色 | I62: 任一賭具
A63: =IF('請先閱讀'!$O$27=true,"密教徒 Cultist","") | B63: ='請先閱讀'!M$27 -> TCM | C63: 自定義 | F63: 教團新晉者 Cult Initiate | G63: 任意 | H63: 奧秘 | I63: 書法工具
A64: =IF('請先閱讀'!$O$27=true,"德魯斯肯瓦伊德居民 Druskenvald Dweller","") | B64: ='請先閱讀'!M$27 -> TCM | C64: 自定義 | F64: 任意起源專長 | G64: 任意 | H64: 求生 | I64: 任一種工具
A65: =IF('請先閱讀'!$O$27=true,"實驗體 Experiment","") | B65: ='請先閱讀'!M$27 -> TCM | C65: 自定義 | F65: 異變 Altered | G65: 威嚇 | H65: 醫藥 | I65: 煉金工具
A66: =IF('請先閱讀'!$O$27=true,"幽燈乘客 Ghostlight Passenger","") | B66: ='請先閱讀'!M$27 -> TCM | C66: 自定義 | F66: 幽燈靈媒 Ghostlight Medium | G66: 察言觀色 | H66: 說服 | I66: 鐵匠工具
A67: =IF('請先閱讀'!$O$27=true,"暗夜獵手 Night Stalker","") | B67: ='請先閱讀'!M$27 -> TCM | C67: 自定義 | F67: 獵狩獵手 Hunter of Hunters | G67: 隱匿 | H67: 擇一：奧秘/歷史/宗教/自然 | I67: 皮匠工具
A68: =IF('請先閱讀'!$O$27=true,"彷徨鏡影 Reflected Wanderer","") | B68: ='請先閱讀'!M$27 -> TCM | C68: 自定義 | F68: 無反射 Unreflected | G68: 欺瞞 | H68: 調查 | I68: 易容工具
A69: =IF('請先閱讀'!$O$27=true,"安魂守衛 Rest Warden","") | B69: ='請先閱讀'!M$27 -> TCM | C69: 自定義 | F69: 守墓人 Grave Keeper | G69: 宗教 | H69: 求生 | I69: 石匠工具
A70: =IF('請先閱讀'!$O$27=true,"狂歡者 Reveler","") | B70: ='請先閱讀'!M$27 -> TCM | C70: 自定義 | F70: 狂歡愚者 Reveling Fool | G70: 表演 | H70: 隱匿 | I70: 任一種樂器
A71: =IF('請先閱讀'!$O$27=true,"禁忌學者 Scholar of the Forbidden","") | B71: ='請先閱讀'!M$27 -> TCM | C71: 自定義 | F71: 恐懼密言 Dread Speech | G71: 奧秘 | H71: 威嚇 | I71: 書法工具
A72: =IF('請先閱讀'!$O$27=true,"柳條織工 Wicker Weaver","") | B72: ='請先閱讀'!M$27 -> TCM | C72: 自定義 | F72: 護符編織者 Charm Twister | G72: 察言觀色 | H72: 自然 | I72: 織布工具
A73: =IF('請先閱讀'!$O$30=true,"神話調查員 Mythos Investigator","") | B73: CBT | C73: 自定義
A74: =IF('請先閱讀'!$O$31=true,"奧古斯丁代理人 Agent of Augustine","") | B74: GH | C74: 智力 | D74: 體魄 | E74: 魅力 | F74: 慧眼收藏家 Insightful Collector | G74: 歷史 | H74: 說服 | I74: 文書偽造工具
A75: =IF('請先閱讀'!$O$31=true,"古文物家 Antiquarian","") | B75: GH | C75: 敏捷 | D75: 體魄 | E75: 智力 | F75: 技巧嫻熟 Skilled | G75: 奧秘 | H75: 歷史 | I75: 修理工具
A76: =IF('請先閱讀'!$O$31=true,"野獸獵人 Beast Hunter","") | B76: GH | C76: 力量 | D76: 敏捷 | E76: 體魄 | F76: 尋血犬 Blood Hound | G76: 動物馴服 | H76: 求生 | I76: 皮匠工具
A77: =IF('請先閱讀'!$O$31=true,"乞丐 Beggar","") | B77: GH | C77: 力量 | D77: 敏捷 | E77: 感知 | F77: 倖存者 Survivor | G77: 察言觀色 | H77: 說服 | I77: 易容工具
A78: =IF('請先閱讀'!$O$31=true,"章節騎士 Chapter Knight","") | B78: GH | C78: 力量 | D78: 感知 | E78: 魅力 | F78: 野蠻攻擊者 Savage Attacker | G78: 動物馴服 | H78: 運動 | I78: 任一種樂器
A79: =IF('請先閱讀'!$O$31=true,"議員 Courtier","") | B79: GH | C79: 智力 | D79: 感知 | E79: 魅力 | F79: 技巧嫻熟 Skilled | G79: 察言觀色 | H79: 說服 | I79: 任一種樂器或工匠工具
A80: =IF('請先閱讀'!$O$31=true,"惡名昭彰 Disgraced Raider","") | B80: GH | C80: 力量 | D80: 體魄 | E80: 感知 | F80: 野蠻攻擊者 Savage Attacker | G80: 運動 | H80: 自然 | I80: 領航工具
A81: =IF('請先閱讀'!$O$31=true,"使節 Envoy","") | B81: GH | C81: 力量 | D81: 體魄 | E81: 魅力 | F81: 技巧嫻熟 Skilled | G81: 察言觀色 | H81: 說服 | I81: 書法工具
A82: =IF('請先閱讀'!$O$31=true,"劊子手 Executioner","") | B82: GH | C82: 力量 | D82: 體魄 | E82: 智力 | F82: 與死亡為伍 Deathbound | G82: 運動 | H82: 醫藥 | I82: 鐵匠工具
A83: =IF('請先閱讀'!$O$31=true,"探索者 Explorer","") | B83: GH | C83: 力量 | D83: 體魄 | E83: 感知 | F83: 警覺 Alert | G83: 運動 | H83: 求生 | I83: 領航工具
A84: =IF('請先閱讀'!$O$31=true,"滅蟲專家 Exterminator","") | B84: GH | C84: 敏捷 | D84: 體魄 | E84: 智力 | F84: 魔法學徒(德魯伊) Magic Initiate | G84: 動物馴服 | H84: 醫藥 | I84: 製毒工具
A85: =IF('請先閱讀'!$O$31=true,"精類祝福 Fey-Blessed","") | B85: GH | C85: 敏捷 | D85: 體魄 | E85: 魅力 | F85: 魔法學徒(法師) Magic Initiate | G85: 奧秘 | H85: 表演 | I85: 任一種樂器
A86: =IF('請先閱讀'!$O$31=true,"自由劍傭兵 Free Swords Mercenary","") | B86: GH | C86: 力量 | D86: 敏捷 | E86: 體魄 | F86: 自由劍傭兵的意志 Free Sword Mercenary's Will | G86: 特技動作 | H86: 運動 | I86: 任一種賭具
A87: =IF('請先閱讀'!$O$31=true,"異教徒 Heretic","") | B87: GH | C87: 力量 | D87: 敏捷 | E87: 感知 | F87: 魔法學徒(牧師) Magic Initiate | G87: 欺瞞 | H87: 宗教 | I87: 易容工具
A88: =IF('請先閱讀'!$O$31=true,"虔信者審判官 Inquisitor of the Faithful","") | B88: GH | C88: 力量 | D88: 感知 | E88: 魅力 | F88: 威信審判官 Convincing Inquisitor | G88: 威嚇 | H88: 宗教 | I88: 草藥工具
A89: =IF('請先閱讀'!$O$31=true,"失職審判官 Lapsed Inquisitor","") | B89: GH | C89: 力量 | D89: 感知 | E89: 魅力 | F89: 威信審判官 Convincing Inquisitor | G89: 說服 | H89: 宗教 | I89: 領航工具
A90: =IF('請先閱讀'!$O$31=true,"神隱之人 One of the Taken","") | B90: GH | C90: 敏捷 | D90: 感知 | E90: 魅力 | F90: 魔法學徒(德魯伊) Magic Initiate | G90: 奧秘 | H90: 自然 | I90: 木雕工具
A91: =IF('請先閱讀'!$O$31=true,"醫師 Physician","") | B91: GH | C91: 敏捷 | D91: 智力 | E91: 感知 | F91: 急救專家 Triage Expert | G91: 醫藥 | H91: 自然 | I91: 草藥工具
A92: =IF('請先閱讀'!$O$31=true,"先驅者 Pioneer","") | B92: GH | C92: 力量 | D92: 體魄 | E92: 感知 | F92: 倖存者 Survivor | G92: 運動 | H92: 求生 | I92: 木匠工具或石匠工具
A93: =IF('請先閱讀'!$O$31=true,"格鬥士 Pit Fighter","") | B93: GH | C93: 力量 | D93: 敏捷 | E93: 魅力 | F93: 野蠻攻擊者 Savage Attacker | G93: 運動 | H93: 表演 | I93: 任一種賭具
A94: =IF('請先閱讀'!$O$31=true,"絕症纏身 Pox-Touched","") | B94: GH | C94: 體魄 | D94: 智力 | E94: 感知 | F94: 急救專家 Triage Expert | G94: 威嚇 | H94: 醫藥 | I94: 草藥工具
A95: =IF('請先閱讀'!$O$31=true,"囚徒 Prisoner","") | B95: GH | C95: 敏捷 | D95: 體魄 | E95: 魅力 | F95: 警覺 Alert | G95: 欺瞞 | H95: 巧手 | I95: 竊賊工具
A96: =IF('請先閱讀'!$O$31=true,"獲釋奴僕 Released Thrall","") | B96: GH | C96: 體魄 | D96: 智力 | E96: 感知 | F96: 倖存者 Survivor | G96: 察覺 | H96: 隱匿 | I96: 任一種工匠工具
A97: =IF('請先閱讀'!$O$31=true,"奇術師門徒 Scion of the Thaumaturge","") | B97: GH | C97: 智力 | D97: 感知 | E97: 魅力 | F97: 奇術師機運 Fortune of the Thaumaturge | G97: 奧秘 | H97: 察言觀色 | I97: 製圖工具
A98: =IF('請先閱讀'!$O$31=true,"幫派走私犯 Syndicate Smuggler","") | B98: GH | C98: 敏捷 | D98: 智力 | E98: 魅力 | F98: 幫派決心 Resolution of the Syndicate | G98: 歷史 | H98: 隱匿 | I98: 文書偽造工具
A99: =IF('請先閱讀'!$O$33=true,"幻身靈旅行者 Changeling Traveler","") | B99: EE | C99: 敏捷 | D99: 感知 | E99: 魅力 | F99: 焦點自我 Focused Personas | G99: 欺瞞 | H99: 巧手 | I99: 竊賊工具
A100: =IF('請先閱讀'!$O$33=true,"瑪倫提 Malenti","") | B100: EE | C100: 敏捷 | D100: 智力 | E100: 魅力 | F100: 海洋適應 Aquatic Adaptation | G100: 欺瞞 | H100: 察言觀色 | I100: 從竊賊工具、製毒工具、易容工具中選擇一項
A101: =IF('請先閱讀'!$O$33=true,"原石 Natural","") | B101: EE | C101: 敏捷 | D101: 感知 | E101: 魅力 | F101: 幸運 Lucky | G101: 察言觀色 | H101: 隱匿 | I101: 竊賊工具
A102: =IF('請先閱讀'!$O$33=true,"奇才 Savant","") | B102: EE | C102: 體魄 | D102: 智力 | E102: 感知 | F102: 魔法學徒(法師) Magic Initiate | G102: 奧秘 | H102: 歷史 | I102: 書法工具
A103: =IF('請先閱讀'!$O$33=true,"攻城技師 Siege Engineer","") | B103: EE | C103: 力量 | D103: 敏捷 | E103: 體魄 | F103: 野蠻攻擊者 Savage Attacker | G103: 運動 | H103: 威嚇 | I103: 任一賭具
...

Sheet 專長
A1: ~~~~起源專長 Origin Feat~~~~ | B1: 傳奇恩惠 Epic Boon Feat
A2: 警覺 Alert | B2: 英勇戰鬥之恩惠 Boon of Combat Prowess
A3: 匠心 Crafter | B3: 次元旅行之恩惠 Boon of Dimensional Travel
A4: 治療師 Healer | B4: 能量抗性之恩惠 Boon of Energy Resistance
A5: 幸運 Lucky | B5: 操弄幸運之恩惠 Boon of Fate
A6: 魔法學徒(法師) Magic Initiate | B6: 超凡強韌之恩惠 Boon of Fortitude
A7: 魔法學徒(牧師) Magic Initiate | B7: 無敵攻勢之恩惠 Boon of Irresistible Offense
A8: 魔法學徒(德魯伊) Magic Initiate | B8: 恢復活力之恩惠 Boon of Recovery
A9: 音樂家 Musician | B9: 多才多藝之恩惠 Boon of Skill
A10: 野蠻攻擊者 Savage Attacker | B10: 健步如飛之恩惠 Boon of Speed
A11: 技巧嫻熟 Skilled | B11: 術法復原之恩惠 Boon of Spell Recall
A12: 酒館拳王 Tavern Brawler | B12: 暗夜精魂之恩惠 Boon of the Night Spirit
A13: 健壯 Tough | B13: 真實視覺之恩惠 Boon of Truesight
A14: =if('請先閱讀'!$F$31=true,"拜龍教新晉者 Cult of the Dragon Initiate","") -> 拜龍教新晉者 Cult of the Dragon Initiate | B14: =if('請先閱讀'!$F$31=true,"無盡血戰之恩惠 Boon of Bloodshed","") -> 無盡血戰之恩惠 Boon of Bloodshed
A15: =if('請先閱讀'!$F$31=true,"翠綠閑庭雛鳥 Emerald Enclave Fledgling","") -> 翠綠閑庭雛鳥 Emerald Enclave Fledgling | B15: =if('請先閱讀'!$F$31=true,"豐碩生機之恩惠 Boon of Bountiful Health","") -> 豐碩生機之恩惠 Boon of Bountiful Health
A16: =if('請先閱讀'!$F$31=true,"豎琴手特工 Harper Agent","") -> 豎琴手特工 Harper Agent | B16: =if('請先閱讀'!$F$31=true,"萬語通曉之恩惠 Boon of Communication","") -> 萬語通曉之恩惠 Boon of Communication
A17: =if('請先閱讀'!$F$31=true,"領主聯盟特工 Lords' Alliance Agent","") -> 領主聯盟特工 Lords' Alliance Agent | B17: =if('請先閱讀'!$F$31=true,"絕境韌性之恩惠 Boon of Desperate Resilience","") -> 絕境韌性之恩惠 Boon of Desperate Resilience
A18: =if('請先閱讀'!$F$31=true,"紫龍堡壘 Purple Dragon Rook","") -> 紫龍堡壘 Purple Dragon Rook | B18: =if('請先閱讀'!$F$31=true,"至高光輝之恩惠 Boon of Exquisite Radiance","") -> 至高光輝之恩惠 Boon of Exquisite Radiance
A19: =if('請先閱讀'!$F$31=true,"咒火火花 Spellfire Spark","") -> 咒火火花 Spellfire Spark | B19: =if('請先閱讀'!$F$31=true,"變幻無常之恩惠 Boon of Fluid Forms","") -> 變幻無常之恩惠 Boon of Fluid Forms
A20: =if('請先閱讀'!$F$31=true,"鐵腕新手 Tyro of the Gauntlet","") -> 鐵腕新手 Tyro of the Gauntlet | B20: =if('請先閱讀'!$F$31=true,"命運賞賜之恩惠 Boon of Fortune's Favor","") -> 命運賞賜之恩惠 Boon of Fortune's Favor
A21: =if('請先閱讀'!$F$31=true,"散塔林暴徒 Zhentarim Ruffian","") -> 散塔林暴徒 Zhentarim Ruffian | B21: =if('請先閱讀'!$F$31=true,"劇毒專精之恩惠 Boon of Poison Mastery","") -> 劇毒專精之恩惠 Boon of Poison Mastery
A22: =if('請先閱讀'!F32=true,"太陽之子 Child of the Sun","") -> 太陽之子 Child of the Sun | B22: =if('請先閱讀'!$F$31=true,"歌頌狂歡之恩惠 Boon of Revelry","") -> 歌頌狂歡之恩惠 Boon of Revelry
A23: =if('請先閱讀'!F32=true,"闇影荒原咒術師 Shadowmoor Hexer","") -> 闇影荒原咒術師 Shadowmoor Hexer | B23: =if('請先閱讀'!$F$31=true,"驚駭顫慄之恩惠 Boon of Terror","") -> 驚駭顫慄之恩惠 Boon of Terror
A24: =if('請先閱讀'!$F$33=true,"不倦狂歡 Tireless Reveler","") -> 不倦狂歡 Tireless Reveler | B24: =if('請先閱讀'!$F$31=true,"耀光旭日之恩惠 Boon of the Bright Sun","") -> 耀光旭日之恩惠 Boon of the Bright Sun
A25: =if('請先閱讀'!$F$33=true,"吸血鬼獵者 Vampire Hunter","") -> 吸血鬼獵者 Vampire Hunter | B25: =if('請先閱讀'!$F$31=true,"風暴雷霆之恩惠 Boon of the Furious Storm","") -> 風暴雷霆之恩惠 Boon of the Furious Storm
A26: =if('請先閱讀'!$F$33=true,"吸血鬼玩物 Vampire's Plaything","") -> 吸血鬼玩物 Vampire's Plaything | B26: =if('請先閱讀'!$F$33=true,"熾烈黎明之恩惠 Boon of Blazing Dawn","") -> 熾烈黎明之恩惠 Boon of Blazing Dawn
A27: =if('請先閱讀'!$F$34=true,"異族龍紋 Aberrant Dragonmark","") -> 異族龍紋 Aberrant Dragonmark | B27: =if('請先閱讀'!$F$33=true,"潛伏陰影之恩惠 Boon of Looming Shadows","") -> 潛伏陰影之恩惠 Boon of Looming Shadows
A28: =if('請先閱讀'!$F$34=true,"偵測龍紋 Mark of Detection","") -> 偵測龍紋 Mark of Detection | B28: =if('請先閱讀'!$F$33=true,"迷霧脫身之恩惠 Boon of Misty Escape","") -> 迷霧脫身之恩惠 Boon of Misty Escape
A29: =if('請先閱讀'!$F$34=true,"探索龍紋 Mark of Finding","") -> 探索龍紋 Mark of Finding | B29: =if('請先閱讀'!$F$34=true,"西伯瑞斯之恩惠 Boon of Siberys","") -> 西伯瑞斯之恩惠 Boon of Siberys
A30: =if('請先閱讀'!$F$34=true,"畜牧龍紋 Mark of Handling","") -> 畜牧龍紋 Mark of Handling | B30: =IF('請先閱讀'!$O$31=true,"魔法抗性之恩惠 Boon of Magic Resistance","")
A31: =if('請先閱讀'!$F$34=true,"醫療龍紋 Mark of Healing","") -> 醫療龍紋 Mark of Healing | B31: =IF('請先閱讀'!$O$31=true,"馭天飛行之恩惠 Boon of Perfect Flight","")
A32: =if('請先閱讀'!$F$34=true,"招待龍紋 Mark of Hospitality","") -> 招待龍紋 Mark of Hospitality | B32: =IF('請先閱讀'!$O$31=true,"影鋼專精之恩惠 Boon of Shadowsteel Mastery","")
A33: =if('請先閱讀'!$F$34=true,"創造龍紋 Mark of Making","") -> 創造龍紋 Mark of Making | B33: =IF('請先閱讀'!$O$31=true,"至尊巫妖之恩惠 Boon of the Archlich","")
A34: =if('請先閱讀'!$F$34=true,"通行龍紋 Mark of Passage","") -> 通行龍紋 Mark of Passage | B34: =IF('請先閱讀'!$O$31=true,"飛昇血族之恩惠 Boon of the Ascended Vampire","")
A35: =if('請先閱讀'!$F$34=true,"抄錄龍紋 Mark of Scribing","") -> 抄錄龍紋 Mark of Scribing | B35: =IF('請先閱讀'!$O$31=true,"塵世羈絆之恩惠 Boon of the Earthly Tether","")
A36: =if('請先閱讀'!$F$34=true,"守護龍紋 Mark of Sentinel","") -> 守護龍紋 Mark of Sentinel | B36: =IF('請先閱讀'!$O$31=true,"上古妖精之恩惠 Boon of the Elder Fey","")
A37: =if('請先閱讀'!$F$34=true,"陰影龍紋 Mark of Shadow","") -> 陰影龍紋 Mark of Shadow | B37: =IF('請先閱讀'!$O$31=true,"上古邪魔之恩惠 Boon of the Elder Fiend","")
A38: =if('請先閱讀'!$F$34=true,"暴風龍紋 Mark of Storm","") -> 暴風龍紋 Mark of Storm | B38: =IF('請先閱讀'!$O$31=true,"上古駭物之恩惠 Boon of the Elder Horror","")
A39: =if('請先閱讀'!$F$34=true,"警戒龍紋 Mark of Warding","") -> 警戒龍紋 Mark of Warding | B39: =IF('請先閱讀'!$O$31=true,"元素調和之恩惠 Boon of the Elemental Temperance","")
A40: =IF('請先閱讀'!$O$27=true,"異變 Altered","") | B40: =IF('請先閱讀'!$O$31=true,"至高天使之恩惠 Boon of the High Seraph","")
A41: =IF('請先閱讀'!$O$27=true,"護符編織者 Charm Twister","") | B41: =IF('請先閱讀'!$O$31=true,"狂野獸性之恩惠 Boon of the Wilds","")
A42: =IF('請先閱讀'!$O$27=true,"猩紅祭儀師 Crimson Ritualist","")
A43: =IF('請先閱讀'!$O$27=true,"教團新晉者 Cult Initiate","")
A44: =IF('請先閱讀'!$O$27=true,"恐懼密言 Dread Speech","")
A45: =IF('請先閱讀'!$O$27=true,"命運賭徒 Fate Gambler","")
A46: =IF('請先閱讀'!$O$27=true,"幽燈靈媒 Ghostlight Medium","")
A47: =IF('請先閱讀'!$O$27=true,"守墓人 Grave Keeper","")
A48: =IF('請先閱讀'!$O$27=true,"獵狩獵手 Hunter of Hunters","")
A49: =IF('請先閱讀'!$O$27=true,"記憶飢渴 Memory Starved","")
A50: =IF('請先閱讀'!$O$27=true,"狂歡愚者 Reveling Fool","")
A51: =IF('請先閱讀'!$O$27=true,"無反射 Unreflected","")
A52: =IF('請先閱讀'!$O$30=true,"我曾戰後歸來 I Fought, I Lived","")
A53: =IF('請先閱讀'!$O$30=true,"我曾躲過懼佈 I Hid from the Terror","")
A54: =IF('請先閱讀'!$O$30=true,"我曾擊破幻象 I Pierced the Illusion","")
A55: =IF('請先閱讀'!$O$30=true,"我曾開啟門扉 I Opened the Gate","")
A56: =IF('請先閱讀'!$O$30=true,"我曾倖存而述 I Survived to Tell the Tale","")
A57: =IF('請先閱讀'!$O$31=true,"尋血犬 Blood Hound","")
A58: =IF('請先閱讀'!$O$31=true,"威信審判官 Convincing Inquisitor","")
A59: =IF('請先閱讀'!$O$31=true,"與死亡為伍 Deathbound","")
A60: =IF('請先閱讀'!$O$31=true,"奇術師機運 Fortune of the Thaumaturge","")
A61: =IF('請先閱讀'!$O$31=true,"自由劍傭兵的意志 Free Sword Mercenary's Will","")
A62: =IF('請先閱讀'!$O$31=true,"慧眼收藏家 Insightful Collector","")
A63: =IF('請先閱讀'!$O$31=true,"幫派決心 Resolution of the Syndicate","")
A64: =IF('請先閱讀'!$O$31=true,"倖存者 Survivor","")
A65: =IF('請先閱讀'!$O$31=true,"急救專家 Triage Expert","")
A66: =IF('請先閱讀'!$O$33=true,"艾瑞尼專家 Aereni Expertise","")
A67: =IF('請先閱讀'!$O$33=true,"海洋適應 Aquatic Adaptation","")
A68: =IF('請先閱讀'!$O$33=true,"整合工具 Envoy Specialist","")
A69: =IF('請先閱讀'!$O$33=true,"焦點自我 Focused Personas","")
A70: =IF('請先閱讀'!$O$33=true,"禁聲訓練 Khesh'dar Training","")
A71: =IF('請先閱讀'!$O$33=true,"思維歌手 Thoughtsinger","")
A72: =IF('請先閱讀'!$O$33=true,"達坎夢境 Uul Dhakaan","")
A73: =if('請先閱讀'!$F$36=true,"~~~~位面契約專長 PlanarPact Feat~~~~","")
A74: =if('請先閱讀'!$F$36=true,"妖精契約 Fey Pact","")
A75: =if('請先閱讀'!$F$36=true,"地獄契約 Infernal Pact","")
A76: ~~~~一般專長 General Feat~~~~
A77: 屬性值提升 Ability Score Improvement
A78: 演員 Actor
A79: 運動健將 Athlete
A80: 衝鋒手 Charger
A81: 大廚 Chef
A82: 強弩專家 Crossbow Expert
A83: 粉碎者 Crusher
A84: 防禦式決鬥 Defensive Duelist
A85: 雙持客 Dual Wielder
A86: 耐性 Durable
A87: 元素行家 Elemental Adept
... A119: 武器大師 Weapon Master
A120: =if('請先閱讀'!$F$31=true,"寒冰施法者 Cold Caster","") -> 寒冰施法者 Cold Caster
A121: =if('請先閱讀'!$F$31=true,"龍痕 Dragonscarred","") -> 龍痕 Dragonscarred
A122: =if('請先閱讀'!$F$31=true,"閑庭魔法 Enclave Magic","") -> 閑庭魔法 Enclave Magic
A123: =if('請先閱讀'!$F$31=true,"妖精魔術師 Fairy Trickster","") -> 妖精魔術師 Fairy Trickster
A124: =if('請先閱讀'!$F$31=true,"巨靈魔法 Genie Magic","") -> 巨靈魔法 Genie Magic
A125: =if('請先閱讀'!$F$31=true,"豎琴手團隊戰術 Harper Teamwork","") -> 豎琴手團隊戰術 Harper Teamwork
A126: =if('請先閱讀'!$F$31=true,"尊主決心 Lordly Resolve","") -> 尊主決心 Lordly Resolve
A127: =if('請先閱讀'!$F$31=true,"祕法觸碰 Mythal Touched","") -> 祕法觸碰 Mythal Touched
A128: =if('請先閱讀'!$F$31=true,"教團韌性 Order's Resilience","") -> 教團韌性 Order's Resilience
A129: =if('請先閱讀'!$F$31=true,"紫龍指揮官 Purple Dragon Commandant","") -> 紫龍指揮官 Purple Dragon Commandant
A130: =if('請先閱讀'!$F$31=true,"咒火行家 Spellfire Adept","") -> 咒火行家 Spellfire Adept
A131: =if('請先閱讀'!$F$31=true,"街頭正義 Street Justice","") -> 街頭正義 Street Justice
...

Sheet GH轉變
P2: 轉變種類 | R2: 第一階段選項
D3: 精類 | H3: I | P3: 異形恐怖 | R3: =IFNA(HLOOKUP($D$3,'GH轉變能力表'!$A$1:$M$29,3,FALSE),"") -> 精類形態
C4: 轉變種類： | G4: 階段： | P4: 精類 | R4: =IFNA(HLOOKUP($D$3,'GH轉變能力表'!$A$1:$M$29,4,FALSE),"") -> 春宮僕從
P5: 邪魔 | R5: =IFNA(HLOOKUP($D$3,'GH轉變能力表'!$A$1:$M$29,5,FALSE),"") -> 夏宮僕從
C6: 第一階段 | P6: 鬼婆 | R6: =IFNA(HLOOKUP($D$3,'GH轉變能力表'!$A$1:$M$29,6,FALSE),"") -> 秋宮僕從
C7: 類型 | D7: 名稱 | E7: 效果 | P7: 巫妖 | R7: =IFNA(HLOOKUP($D$3,'GH轉變能力表'!$A$1:$M$29,7,FALSE),"") -> 冬宮僕從
C8: 恩賜 1 | P8: 狼人
C9: 恩賜 2 | P9: 泥怪 | R9: 第二階段選項
C10: 缺陷 | D10: =IFNA(HLOOKUP($D$3,'GH轉變能力表'!$A$1:$M$29,8,FALSE),"") -> 位面束縛 | P10: 原初種 | R10: =IFNA(HLOOKUP($D$3,'GH轉變能力表'!$A$1:$M$29,10,FALSE),"") -> 兩面性
P11: 熾天使 | R11: =IFNA(HLOOKUP($D$3,'GH轉變能力表'!$A$1:$M$29,11,FALSE),"") -> 魔法把戲
C12: 第二階段 | P12: 影鋼石屍鬼 | R12: =IFNA(HLOOKUP($D$3,'GH轉變能力表'!$A$1:$M$29,12,FALSE),"")
C13: 類型 | D13: 名稱 | E13: 效果 | P13: 幽靈 | R13: =IFNA(HLOOKUP($D$3,'GH轉變能力表'!$A$1:$M$29,13,FALSE),"")
C14: 恩賜 1 | P14: 吸血鬼 | R14: =IFNA(HLOOKUP($D$3,'GH轉變能力表'!$A$1:$M$29,14,FALSE),"")
C15: 恩賜 2
C16: 缺陷 | D16: =IFNA(HLOOKUP($D$3,'GH轉變能力表'!$A$1:$M$29,15,FALSE),"") -> 女王的命令 | R16: 第三階段選項
R17: =IFNA(HLOOKUP($D$3,'GH轉變能力表'!$A$1:$M$29,17,FALSE),"") -> 幻象披風
C18: 第三階段 | R18: =IFNA(HLOOKUP($D$3,'GH轉變能力表'!$A$1:$M$29,18,FALSE),"") -> 獠牙與利爪
C19: 類型 | D19: 名稱 | E19: 效果 | R19: =IFNA(HLOOKUP($D$3,'GH轉變能力表'!$A$1:$M$29,19,FALSE),"") -> 幻夢與噩夢
C20: 恩賜 1 | R20: =IFNA(HLOOKUP($D$3,'GH轉變能力表'!$A$1:$M$29,20,FALSE),"")
C21: 恩賜 2 | R21: =IFNA(HLOOKUP($D$3,'GH轉變能力表'!$A$1:$M$29,21,FALSE),"")
C22: 缺陷 | D22: =IFNA(HLOOKUP($D$3,'GH轉變能力表'!$A$1:$M$29,22,FALSE),"") -> 體質衰弱
R23: 第四階段選項
C24: 第四階段 | R24: =IFNA(HLOOKUP($D$3,'GH轉變能力表'!$A$1:$M$29,24,FALSE),"") -> 高等魔法把戲
C25: 類型 | D25: 名稱 | E25: 效果 | R25: =IFNA(HLOOKUP($D$3,'GH轉變能力表'!$A$1:$M$29,25,FALSE),"") -> 暮光魅影
C26: 恩賜 1 | R26: =IFNA(HLOOKUP($D$3,'GH轉變能力表'!$A$1:$M$29,26,FALSE),"")
C27: 恩賜 2 | R27: =IFNA(HLOOKUP($D$3,'GH轉變能力表'!$A$1:$M$29,27,FALSE),"")
C28: 缺陷 | D28: =IFNA(HLOOKUP($D$3,'GH轉變能力表'!$A$1:$M$29,29,FALSE),"") -> 季節影響 | R28: =IFNA(HLOOKUP($D$3,'GH轉變能力表'!$A$1:$M$29,28,FALSE),"")

Sheet GH轉變能力表
B1: 異形恐怖 | C1: 精類 | D1: 邪魔 | E1: 鬼婆 | F1: 巫妖 | G1: 狼人 | H1: 泥怪 | I1: 原初種 | J1: 熾天使 | K1: 影鋼石屍鬼 | L1: 幽靈 | M1: 吸血鬼
A2: Stage:I
A3: 恩賜A | B3: 異怪形態 | C3: 精類形態 | D3: 邪魔靈魂 | E3: 鬼婆形態 | F3: 不死形態 | G3: 狼人形態 | H3: 泥怪形態 | I3: 原初形態 | J3: 天界形態 | K3: 影鋼詛咒師 | L3: 幽靈形態 | M3: 獠牙啃咬
A4: 恩賜B | B4: 異形突變 | C4: 春宮僕從 | D4: 煉獄打擊 | E4: 蒼綠姐妹會 | F4: 傳承巫妖 | G4: 熊人形態 | H4: 多變肉體 | I4: 元素親和 | J4: 天使之翼 | K4: 影鋼武裝 | L4: 鬼觸 | M4: 索曼血脈
A5: 恩賜C | C5: 夏宮僕從 | D5: 魔鬼契約者 | E5: 猩紅姊妹會 | F5: 巫妖秘法 | G5: 鼠人形態 | H5: 黏液表面 | J5: 神聖打擊 | L5: 虛化移動 | M5: 斯特里戈伊血脈
A6: 恩賜D | C6: 秋宮僕從 | E6: 海洋姐妹會 | M6: 弗澤格血脈
A7: 恩賜E | C7: 冬宮僕從
A8: 缺陷 | B8: 不穩形態 | C8: 位面束縛 | D8: 邪魔縛誓 | E8: 駭人容貌 | F8: 魂匣 | G8: 狩獵渴望 | H8: 遲緩 | I8: 位面束縛 | J8: 位面束縛 | K8: 衰弱魔法 | L8: 沉淪黑暗 | M8: 血族詛咒
A9: Stage:II
A10: 恩賜A | B10: 高效殺手 | C10: 兩面性 | D10: 惡魔烙印 | E10: 蒼綠姐妹會老手 | F10: 不死隨從 | G10: 獵人專注 | H10: 彈性肢體 | I10: 雙重本質 | J10: 神聖寬仁 | K10: 魔法抗性 | L10: 乙太相位 | M10: 黑夜之眼
A11: 恩賜B | B11: 蠕動觸肢 | C11: 魔法把戲 | D11: 強化契約 | E11: 猩紅姊妹會老手 | F11: 束縛詛咒 | G11: 鋼鐵獸皮 | H11: 黏稠耐力 | I11: 元素湧動 | J11: 神罰 | K11: 影鋼吸收 | L11: 索命飛行 | M11: 墓土之魂
A12: 恩賜C | D12: 邪魔形態 | E12: 海洋姐妹會老手 | F12: 腐化魔法 | G12: 親族形態 | K12: 影鋼施法者 | M12: 非人反射
A13: 恩賜D | K13: 影鋼武器大師 | M13: 不死韌性
A14: 恩賜E
A15: 缺陷 | B15: 駭人容貌 | C15: 女王的命令 | D15: 駭人容貌 | E15: 鐵質敏感 | F15: 駭人容貌 | G15: 銀質敏感 | H15: 溶解容貌 | I15: 翻騰元素 | J15: 炫目輝光 | K15: 孤家寡人 | L15: 生命脫節 | M15: 高等血族詛咒
A16: Stage:III
A17: 恩賜A | B17: 恐懼面容 | C17: 幻象披風 | D17: 地獄分包商 | E17: 蒼綠姐妹會大師 | F17: 魔能專注 | G17: 野性活力 | H17: 腐蝕膜 | I17: 覺醒光環 | J17: 淨化苦難 | K17: 詛咒爪 | L17: 精氣汲取 | M17: 迷惑騙術
A18: 恩賜B | B18: 束縛觸肢 | C18: 獠牙與利爪 | D18: 壓制烙印 | E18: 猩紅姊妹會大師 | F18: 不死主宰 | G18: 變形者蠻勁 | H18: 吞噬 | I18: 太古之軀 | J18: 守護之翼 | L18: 麻痺之觸 | M18: 強化獠牙咬噬
A19: 恩賜C | C19: 幻夢與噩夢 | E19: 海洋姐妹會大師 | F19: 不潔癒合 | I19: 萬物主宰 | J19: 天界裁決之弓 | M19: 迷霧形態
A20: 恩賜D | M20: 操血術專家
A21: 恩賜E
A22: 缺陷 | B22: 不穩存在 | C22: 體質衰弱 | D22: 下界引力 | E22: 淨化之痛 | F22: 死靈性萎縮 | G22: 混亂思緒 | H22: 生理退化 | I22: 元素失衡 | J22: 黑暗燈塔 | K22: 治癒抗性 | L22: 現實磨損 | M22: 至高血族詛咒
A23: Stage:IV
A24: 恩賜A | B24: 上古異形 | C24: 高等魔法把戲 | D24: 深淵抗性 | E24: 邪眼 | F24: 魔能全知 | G24: 混種形態親和 | H24: 軟泥軍團 | I24: 原初光環 | J24: 神聖肅清光環 | K24: 影鋼奧術法器 | L24: 瓦解呼喚 | M24: 再生
A25: 恩賜B | B25: 劇毒觸肢 | C25: 暮光魅影 | D25: 煉獄召喚 | E25: 祖母的詛咒 | F25: 碎魂攻擊 | G25: 野蠻本能 | H25: 擬態物品 | I25: 元素精通 | J25: 公義仁慈光環 | K25: 影鋼狂怒 | L25: 附身 | M25: 最終索曼血脈
A26: 恩賜C | D26: 終極烙印 | F26: 不死之王 | J26: 天界主宰之弓 | M26: 最終斯特里戈伊血脈
A27: 恩賜D | M27: 最終弗澤格血脈
A28: 恩賜E
A29: 缺陷 | B29: 熵能憎惡 | C29: 季節影響 | D29: 真名 | E29: 老巫嫗的飢渴 | F29: 歲月之重 | G29: 終極掠食者 | H29: 濕滑自我 | I29: 原初混沌 | J29: 最終轉變 | K29: 影鋼自爆 | L29: 湮滅引力 | M29: 終極終極血族詛咒

Sheet 裝備與物品
B2: 裝備與物品
B4: A | C4: 物品/放置處 | K4: # | M4: 重量 | O4: 總重 | R4: 物品/放置處 | Z4: # | AB4: 重量 | AD4: 總重 | AG4: 貨幣/寶藏 | AT4: 物品/放置處 | BA4: # | BC4: 重量 | BE4: 總重 | BH4: 物品/放置處 | BO4: # | BQ4: 重量 | BS4: 總重
B5: A | C5: 服裝/飾品 | R5: 背包 | Z5: FALSE | AB5: 5 | AD5: =AB5*Z5 -> 0 | AG5: 金幣(GP) | AK5: 銀幣(SP) | AO5: 銅幣(CP) | AT5: 次元袋 | BA5: FALSE | BC5: 15 | BE5: =BC5*BA5 -> 0 | BS5: =BO5*BQ5 -> 0
B6: A | C6: 穿戴護甲 | K6: 1 | M6: =SUMPRODUCT('角色卡'!CJ27:CL28) -> 0 | O6: =K6*M6 -> 0 | R6: 治療工具包 | AD6: =Z6*AB6 -> 0 | AG6: 490 | AK6: ='金錢紀錄'!AA3 -> 0 | AO6: ='金錢紀錄'!AB3 -> 0 | BE6: =BA6*BC6 -> 0 | BS6: =BO6*BQ6 -> 0
B7: A | C7: 武器與法器 | K7: 1 | M7: =SUMPRODUCT('角色卡'!AY37:AY42,'角色卡'!BB37:BB42) -> 0 | O7: =K7*M7 -> 0 | R7: 治療藥水 2d4 +2 | AD7: =Z7*AB7 -> 0 | AG7: 白金幣(PP) | AK7: 銀金幣(EP) | AO7: 總額(金) | BE7: =BA7*BC7 -> 0 | BS7: =BO7*BQ7 -> 0
B8: A | O8: =K8*M8 -> 0 | AD8: =Z8*AB8 -> 0 | AG8: ='金錢紀錄'!Z5 -> 0 | AK8: ='金錢紀錄'!AA5 -> 0 | AO8: =(AO6+AK6*10+AG6*100+AG8*1000+AK8*50)/100 -> 490 | BE8: =BA8*BC8 -> 0 | BS8: =BO8*BQ8 -> 0
B9: A | O9: =K9*M9 -> 0 | AD9: =Z9*AB9 -> 0 | AG9: 貨幣計重 | AM9: FALSE | AO9: =(AG6+AK6+AO6+AK8+AG8)*0.02 -> 9.8 | AQ9: =AO9*AM9 -> 0 | BE9: =BA9*BC9 -> 0 | BS9: =BO9*BQ9 -> 0
B10: A | O10: =K10*M10 -> 0 | AD10: =Z10*AB10 -> 0 | AG10: 貴重物 | AL10: 價值 | AO10: # | AQ10: 重量 | BE10: =BA10*BC10 -> 0 | BS10: =BO10*BQ10 -> 0
B11: A | O11: =K11*M11 -> 0 | AD11: =Z11*AB11 -> 0 | BE11: =BA11*BC11 -> 0 | BS11: =BO11*BQ11 -> 0
B12: A | O12: =K12*M12 -> 0 | AD12: =Z12*AB12 -> 0 | BE12: =BA12*BC12 -> 0 | BS12: =BO12*BQ12 -> 0
B13: A | C13: 囊袋 | K13: FALSE | M13: 1 | O13: =K13*M13 -> 0 | AD13: =Z13*AB13 -> 0 | BE13: =BA13*BC13 -> 0 | BS13: =BO13*BQ13 -> 0
B14: A | O14: =K14*M14 -> 0 | AD14: =Z14*AB14 -> 0 | BE14: =BA14*BC14 -> 0 | BS14: =BO14*BQ14 -> 0
B15: A | O15: =K15*M15 -> 0 | AD15: =Z15*AB15 -> 0 | BE15: =BA15*BC15 -> 0 | BS15: =BO15*BQ15 -> 0
B16: A | O16: =K16*M16 -> 0 | AD16: =Z16*AB16 -> 0 | BE16: =BA16*BC16 -> 0 | BS16: =BO16*BQ16 -> 0
B17: A | O17: =K17*M17 -> 0 | AD17: =Z17*AB17 -> 0 | BE17: =BA17*BC17 -> 0 | BS17: =BO17*BQ17 -> 0
B18: A | O18: =K18*M18 -> 0 | AD18: =Z18*AB18 -> 0 | BE18: =BA18*BC18 -> 0 | BS18: =BO18*BQ18 -> 0
B19: A | O19: =K19*M19 -> 0 | AD19: =Z19*AB19 -> 0 | BE19: =BA19*BC19 -> 0 | BS19: =BO19*BQ19 -> 0
B20: A | O20: =K20*M20 -> 0 | AD20: =Z20*AB20 -> 0 | BE20: =BA20*BC20 -> 0 | BS20: =BO20*BQ20 -> 0
B21: A | O21: =K21*M21 -> 0 | AD21: =Z21*AB21 -> 0 | BE21: =BA21*BC21 -> 0 | BS21: =BO21*BQ21 -> 0
B22: A | C22: 麻袋 | K22: FALSE | M22: 0.5 | O22: =K22*M22 -> 0 | AD22: =Z22*AB22 -> 0 | BE22: =BA22*BC22 -> 0 | BS22: =BO22*BQ22 -> 0
B23: A | O23: =K23*M23 -> 0 | AD23: =Z23*AB23 -> 0 | BE23: =BA23*BC23 -> 0 | BS23: =BO23*BQ23 -> 0
B24: A | O24: =K24*M24 -> 0 | AD24: =Z24*AB24 -> 0 | BE24: =BA24*BC24 -> 0 | BS24: =BO24*BQ24 -> 0
B25: A | O25: =K25*M25 -> 0 | AD25: =Z25*AB25 -> 0 | BE25: =BA25*BC25 -> 0 | BS25: =BO25*BQ25 -> 0
B26: A | O26: =K26*M26 -> 0 | AD26: =Z26*AB26 -> 0 | BE26: =BA26*BC26 -> 0 | BS26: =BO26*BQ26 -> 0
B27: A | O27: =K27*M27 -> 0 | AD27: =Z27*AB27 -> 0 | BE27: =BA27*BC27 -> 0 | BS27: =BO27*BQ27 -> 0
B28: A | O28: =K28*M28 -> 0 | AD28: =Z28*AB28 -> 0 | BE28: =BA28*BC28 -> 0 | BS28: =BO28*BQ28 -> 0
B29: A | O29: =K29*M29 -> 0 | AD29: =Z29*AB29 -> 0 | BE29: =BA29*BC29 -> 0 | BS29: =BO29*BQ29 -> 0
B30: A | O30: =K30*M30 -> 0 | AD30: =Z30*AB30 -> 0 | BE30: =BA30*BC30 -> 0 | BS30: =BO30*BQ30 -> 0
B31: A | C31: 箭袋/弩矢匣 | K31: FALSE | M31: 1 | O31: =K31*M31 -> 0 | AD31: =Z31*AB31 -> 0 | AG31: 負重 | BE31: =BA31*BC31 -> 0 | BS31: =BO31*BQ31 -> 0
B32: A | C32: ='角色卡'!BI27 -> 無 | K32: ='角色卡'!BF27 -> 0 | M32: =IF(C32="箭矢",K32*0.05,IF(C32="弩矢",K32*0.075,IF(C32="投石索彈丸",K32*0.075,IF(C32="吹箭",K32*0.02,IF(C32="火器彈藥",K32*0.2,IF(C32="現代彈藥",K32*0.1,IF(C32="能量電池",K32*0.3125,IF(C32="無",0)))))))) -> 0 | O32: =M32 -> 0 | AD32: =Z32*AB32 -> 0 | AG32: =IF(AG35=0,IF(AB34<='角色卡'!G15*15, "負重上限="&'角色卡'!G15*15&"磅"&char(10)& "現在負重="&AB34&"磅"&char(10)& "拖/抬/推上限="&'角色卡'!G15*30&"磅","超過上限"), IF(AG35=1,IF(AB34<='角色卡'!G15*15*2, "載負上限="&'角色卡'!G15*30&"磅"&char(10)& "現在負重="&AB34&"磅"&char(10)& "拖/抬/推上限="&'角色卡'!G15*60&"磅","超過上限"))) -> 負重上限=150磅 現在負重=0磅 拖/抬/推上限=300磅 | BE32: =BA32*BC32 -> 0 | BS32: =BO32*BQ32 -> 0
B33: A | C33: ='角色卡'!BI28 -> 無 | K33: ='角色卡'!BF28 -> 0 | M33: =IF(C33="箭矢",K33*0.05,IF(C33="弩矢",K33*0.075,IF(C33="投石索彈丸",K33*0.075,IF(C33="吹箭",K33*0.02,IF(C33="火器彈藥",K33*0.2,IF(C33="現代彈藥",K33*0.1,IF(C33="能量電池",K33*0.3125,IF(C33="無",0)))))))) -> 0 | O33: =M33 -> 0 | AD33: =Z33*AB33 -> 0 | BE33: =BA33*BC33 -> 0 | BS33: =BO33*BQ33 -> 0
B34: A | C34: ='角色卡'!BI29 -> 無 | K34: ='角色卡'!BF29 -> 0 | M34: =IF(C34="箭矢",K34*0.05,IF(C34="弩矢",K34*0.075,IF(C34="投石索彈丸",K34*0.075,IF(C34="吹箭",K34*0.02,IF(C34="火器彈藥",K34*0.2,IF(C34="現代彈藥",K34*0.1,IF(C34="能量電池",K34*0.3125,IF(C34="無",0)))))))) -> 0 | O34: =M34 -> 0 | R34: 裝備總重量 | AB34: =SUM(O6:P34,AD5:AE33,BE5,AQ9)+SUMPRODUCT(AQ11:AQ30,AO11:AO30) -> 0 | BE34: =BA34*BC34 -> 0 | BH34: 次元袋物品總重量 | BP34: =if(SUM(BE6:BF34,BS5:BT33)>500,"次元袋破裂",SUM(BE6:BF34,BS5:BT33)) -> 0
AG35: =IF(OR('角色卡'!Y7="歌利亞 Goliath"),1,0) -> 0 | AT35: =IF(ISNUMBER(MATCH("奇械師-Artificer", #REF!, 0)), "奇械同調", "") | BE35: =IF(ISNUMBER(MATCH("奇械師-Artificer", #REF!, 0)), "奇械同調", "") | BI35: =IF(ISNUMBER(MATCH("奇械師-Artificer", #REF!, 0)), "奇械同調", "") | BM35: =IF(ISNUMBER(MATCH("奇械師-Artificer", #REF!, 0)), "奇械同調", "")
B37: 魔法物品
C39: 同調魔法物品
C40: 物品名稱 | J40: 稀有度 | N40: 類型 | R40: 物品描述
B41: )
B42: )
B43: )
B44: )
B45: )
B46: )
C48: 其他魔法物品
C49: 物品名稱 | J49: 稀有度 | N49: 類型 | R49: 物品描述

Sheet 背景故事
B1: 5e的四大特徵在這裡
B2: 人物性格
C4: 角色個性 | W4: 個人理念 | AP4: 人際羈絆 | BI4: 人物缺點
B10: 背景故事
C12: 背景故事 | AP12: 角色外觀描述 | BK12: 所屬盟軍/組織
BK19: 派系聲望
AP21: 屬性值特質 | BK21: 組織徽章
AP22: 力量特質
AP23: 敏捷特質
AP24: 體魄特質
AP25: 智力特質
AP26: 感知特質
AP27: 魅力特質
AP29: 陣營特質
AP30: =IF(OR('角色卡'!AZ7="守序善良LG",'角色卡'!AZ7="中立善良NG",'角色卡'!AZ7="混亂善良CG"),"善良特質",IF(OR('角色卡'!AZ7="守序中立LN",'角色卡'!AZ7="絕對中立TN",'角色卡'!AZ7="混亂中立CN"),"中立特質",IF(OR('角色卡'!AZ7="守序邪惡LE",'角色卡'!AZ7="中立邪惡NE",'角色卡'!AZ7="混亂邪惡CE"),"邪惡特質","")))
AP31: =IF(OR('角色卡'!AZ7="守序善良LG",'角色卡'!AZ7="守序中立LN",'角色卡'!AZ7="守序邪惡LE"),"守序特質",IF(OR('角色卡'!AZ7="中立善良NG",'角色卡'!AZ7="絕對中立TN",'角色卡'!AZ7="中立邪惡NE"),"中立特質",IF(OR('角色卡'!AZ7="混亂善良CG",'角色卡'!AZ7="混亂中立CN",'角色卡'!AZ7="混亂邪惡CE"),"混亂特質","")))
B33: 想不到怎麼開始寫背景嗎？先來想想這些？
C35: 你是如何成為你指定的背景(比如嚮導)？ | AC35: 在該背景中發生過什麼特別有意義的經歷？ | BC35: 為什麼不好好過背景生活要出來冒險？
C41: 長遠的目標/追求是什麼？想怎麼執行？ | AC41: 未來希望自己有什麼樣的成長曲線？ | BC41: 如何接上要跑的劇本？

Sheet 武器&護甲
A1: 武器 | B1: 類型 | C1: 傷害 | D1: 距離 | E1: 屬性 | F1: 重量 | G1: 一般屬性 | H1: 精通屬性 | J1: 護甲 | K1: AC | L1: 重量
A2: 棍棒 | B2: 簡易近戰武器 | C2: 1d4 | D2: 觸及 | E2: 鈍擊 | F2: 2 | G2: 輕型 | H2: 緩速 Slow | J2: 皮甲 | K2: 11 | L2: 8
A3: 匕首 | B3: 簡易近戰武器 | C3: 1d4 | D3: 20/60 | E3: 穿刺 | F3: 1 | G3: 投擲、輕型、靈巧 | H3: 迅擊 Nick | J3: 棉甲 | K3: 11 | L3: 10
A4: 巨棍 | B4: 簡易近戰武器 | C4: 1d8 | D4: 觸及 | E4: 鈍擊 | F4: 10 | G4: 雙手 | H4: 推離 Push | J4: 鑲釘皮甲 | K4: 12 | L4: 13
A5: 手斧 | B5: 簡易近戰武器 | C5: 1d6 | D5: 20/60 | E5: 劈砍 | F5: 2 | G5: 投擲、輕型 | H5: 侵擾 Vex | J5: 生皮甲 | K5: 12 | L5: 12
A6: 標槍 | B6: 簡易近戰武器 | C6: 1d6 | D6: 30/120 | E6: 穿刺 | F6: 2 | G6: 投擲 | H6: 緩速 Slow | J6: 鍊甲衫 | K6: 13 | L6: 20
A7: 輕錘 | B7: 簡易近戰武器 | C7: 1d4 | D7: 20/60 | E7: 鈍擊 | F7: 2 | G7: 投擲、輕型 | H7: 迅擊 Nick | J7: 鱗甲 | K7: 14 | L7: 45
A8: 硬頭錘 | B8: 簡易近戰武器 | C8: 1d6 | D8: 觸及 | E8: 鈍擊 | F8: 4 | H8: 削弱 Sap | J8: 護胸甲 | K8: 14 | L8: 20
A9: 長棍 | B9: 簡易近戰武器 | C9: 1d6(1d8) | D9: 觸及 | E9: 鈍擊 | F9: 4 | G9: 可雙手 | H9: 失衡 Topple | J9: 半身板甲 | K9: 15 | L9: 40
A10: 鐮刀 | B10: 簡易近戰武器 | C10: 1d4 | D10: 觸及 | E10: 劈砍 | F10: 2 | G10: 輕型 | H10: 迅擊 Nick | J10: 環甲 | K10: 14 | L10: 40
A11: 矛 | B11: 簡易近戰武器 | C11: 1d6(1d8) | D11: 20/60 | E11: 穿刺 | F11: 3 | G11: 可雙手、投擲 | H11: 削弱 Sap | J11: 鎖子甲 | K11: 16 | L11: 55
A12: =IF('請先閱讀'!O34=true,"指虎","") | B12: 簡易近戰武器 | C12: 1d4 | D12: 觸及 | E12: 鈍擊 | F12: 1 | G12: 輕型 | H12: 推離 Push | J12: 條板甲 | K12: 17 | L12: 60
A13: =IF('請先閱讀'!O34=true,"手爪","") | B13: 簡易近戰武器 | C13: 1d4 | D13: 觸及 | E13: 劈砍 | F13: 2 | G13: 輕型、靈巧 | H13: 侵擾 Vex | J13: 全身板甲 | K13: 18 | L13: 65
A14: =IF('請先閱讀'!O34=true,"拳刃","") | B14: 簡易近戰武器 | C14: 1d4 | D14: 觸及 | E14: 穿刺 | F14: 3 | H14: 削弱 Sap
A15: 飛鏢 | B15: 簡易遠程武器 | C15: 1d4 | D15: 20/60 | E15: 穿刺 | F15: 0.25 | G15: 投擲、靈巧 | H15: 侵擾 Vex
A16: 輕弩 | B16: 簡易遠程武器 | C16: 1d8 | D16: 80/320 | E16: 穿刺 | F16: 5 | G16: 裝填、彈藥(弩矢)、雙手 | H16: 緩速 Slow
A17: 短弓 | B17: 簡易遠程武器 | C17: 1d6 | D17: 80/320 | E17: 穿刺 | F17: 2 | G17: 彈藥(箭矢)、雙手 | H17: 侵擾 Vex
A18: 投石索 | B18: 簡易遠程武器 | C18: 1d4 | D18: 30/120 | E18: 鈍擊 | F18: 0 | G18: 彈藥(投石索彈丸) | H18: 緩速 Slow
A19: 戰斧 | B19: 軍用近戰武器 | C19: 1d8(1d10) | D19: 觸及 | E19: 劈砍 | F19: 4 | G19: 可雙手 | H19: 失衡 Topple
A20: 連枷 | B20: 軍用近戰武器 | C20: 1d8 | D20: 觸及 | E20: 鈍擊 | F20: 2 | H20: 削弱 Sap
A21: 長柄刀 | B21: 軍用近戰武器 | C21: 1d10 | D21: 觸及(10呎) | E21: 劈砍 | F21: 6 | G21: 重型、觸及、雙手 | H21: 擦掠 Graze
A22: 巨斧 | B22: 軍用近戰武器 | C22: 1d12 | D22: 觸及 | E22: 劈砍 | F22: 7 | G22: 重型、雙手 | H22: 橫掃 Cleave
A23: 巨劍 | B23: 軍用近戰武器 | C23: 2d6 | D23: 觸及 | E23: 劈砍 | F23: 6 | G23: 重型、雙手 | H23: 擦掠 Graze
A24: 斧槍 | B24: 軍用近戰武器 | C24: 1d10 | D24: 觸及(10呎) | E24: 劈砍 | F24: 6 | G24: 重型、觸及、雙手 | H24: 橫掃 Cleave
A25: 騎槍 | B25: 軍用近戰武器 | C25: 1d10 | D25: 觸及(10呎) | E25: 穿刺 | F25: 6 | G25: 重型、觸及、雙手(除非騎乘) | H25: 失衡 Topple
A26: 長劍 | B26: 軍用近戰武器 | C26: 1d8(1d10) | D26: 觸及 | E26: 劈砍 | F26: 3 | G26: 可雙手 | H26: 削弱 Sap
A27: 巨錘 | B27: 軍用近戰武器 | C27: 2d6 | D27: 觸及 | E27: 鈍擊 | F27: 10 | G27: 重型、雙手 | H27: 失衡 Topple
A28: 釘頭錘 | B28: 軍用近戰武器 | C28: 1d8 | D28: 觸及 | E28: 穿刺 | F28: 4 | H28: 削弱 Sap
A29: 長柄槍 | B29: 軍用近戰武器 | C29: 1d10 | D29: 觸及(10呎) | E29: 穿刺 | F29: 18 | G29: 重型、雙手、觸及 | H29: 推離 Push
A30: 刺劍 | B30: 軍用近戰武器 | C30: 1d8 | D30: 觸及 | E30: 穿刺 | F30: 2 | G30: 靈巧 | H30: 侵擾 Vex
A31: 彎刀 | B31: 軍用近戰武器 | C31: 1d6 | D31: 觸及 | E31: 劈砍 | F31: 3 | G31: 輕型、靈巧 | H31: 迅擊 Nick
A32: 短劍 | B32: 軍用近戰武器 | C32: 1d6 | D32: 觸及 | E32: 穿刺 | F32: 2 | G32: 輕型、靈巧 | H32: 侵擾 Vex
A33: 三叉戟 | B33: 軍用近戰武器 | C33: 1d8(1d10) | D33: 20/60 | E33: 穿刺 | F33: 4 | G33: 投擲、可雙手 | H33: 失衡 Topple
A34: 戰錘 | B34: 軍用近戰武器 | C34: 1d8(1d10) | D34: 觸及 | E34: 鈍擊 | F34: 2 | G34: 可雙手 | H34: 推離 Push
A35: 戰鎬 | B35: 軍用近戰武器 | C35: 1d8(1d10) | D35: 觸及 | E35: 穿刺 | F35: 2 | G35: 可雙手 | H35: 削弱 Sap
A36: 鞭 | B36: 軍用近戰武器 | C36: 1d4 | D36: 觸及(10呎) | E36: 劈砍 | F36: 3 | G36: 觸及、靈巧 | H36: 緩速 Slow
A37: 吹箭筒 | B37: 軍用遠程武器 | C37: 1 | D37: 25/100 | E37: 穿刺 | F37: 1 | G37: 彈藥(吹箭)、裝填 | H37: 侵擾 Vex
A38: 手弩 | B38: 軍用遠程武器 | C38: 1d6 | D38: 30/120 | E38: 穿刺 | F38: 3 | G38: 彈藥(弩矢)、裝填、輕型 | H38: 侵擾 Vex
A39: 重弩 | B39: 軍用遠程武器 | C39: 1d10 | D39: 100/400 | E39: 穿刺 | F39: 18 | G39: 彈藥(弩矢)、重型、裝填、雙手 | H39: 推離 Push
A40: 長弓 | B40: 軍用遠程武器 | C40: 1d8 | D40: 150/600 | E40: 穿刺 | F40: 2 | G40: 彈藥(箭矢)、重型、雙手 | H40: 緩速 Slow
A41: =IF('請先閱讀'!O29=FALSE,"鳥銃","") -> 鳥銃 | B41: 軍用遠程武器 | C41: 1d12 | D41: 40/120 | E41: 穿刺 | F41: 10 | G41: 彈藥(子彈)、裝填、雙手 | H41: 緩速 Slow
A42: =IF('請先閱讀'!O29=FALSE,"手銃","") -> 手銃 | B42: 軍用遠程武器 | C42: 1d10 | D42: 30/90 | E42: 穿刺 | F42: 3 | G42: 彈藥(子彈)、裝填 | H42: 侵擾 Vex
A43: 法杖 | B43: 簡易近戰武器 | C43: 1d6(1d8) | D43: 觸及 | E43: 鈍擊 | F43: 4 | G43: 奧術法器 | H43: 失衡 Topple
A44: 權杖 | F44: 2 | G44: 奧術法器
A45: 魔杖 | F45: 1 | G45: 奧術法器
A46: 法球 | F46: 3 | G46: 奧術法器
A47: 水晶 | F47: 1 | G47: 奧術法器
A48: 法術書 | F48: 1 | G48: 奧術法器、法師法器
A49: 木質法杖 | B49: 簡易近戰武器 | C49: 1d6(1d8) | D49: 觸及 | E49: 鈍擊 | F49: 4 | G49: 德魯伊法器 | H49: 失衡 Topple
A50: 紫杉魔杖 | F50: 1 | G50: 德魯伊法器
A51: 圖騰 | F51: 0 | G51: 德魯伊法器
A52: 槲寄生枝 | F52: 0 | G52: 德魯伊法器
A53: 聖徽 | F53: 0 | G53: 聖徽
A54: 護符 | F54: 1 | G54: 聖徽
A55: 聖物匣 | F55: 2 | G55: 聖徽
A56: =IF('請先閱讀'!O29=true,"雷筒(文藝復興)","") | B56: 軍用遠程武器 | C56: 1d12 | D56: 20/60 | E56: 穿刺 | F56: 15 | G56: 彈藥(雷筒彈丸)、重型、裝填、雙手 | H56: 散射 Scatter
A57: =IF('請先閱讀'!O29=true,"鳥銃(文藝復興)","") | B57: 軍用遠程武器 | C57: 1d12 | D57: 40/120 | E57: 穿刺 | F57: 10 | G57: 彈藥(子彈)、裝填、雙手 | H57: 緩速 Slow
A58: =IF('請先閱讀'!O29=true,"手銃(文藝復興)","") | B58: 軍用遠程武器 | C58: 1d10 | D58: 30/90 | E58: 穿刺 | F58: 3 | G58: 彈藥(子彈)、裝填 | H58: 侵擾 Vex
A59: =IF('請先閱讀'!O$29=true,"雙管霰彈槍(工業革命)","") | B59: 簡易遠程武器 | C59: 2d6 | D59: 20/60 | E59: 穿刺 | F59: 8 | G59: 彈藥(霰彈)、火器、後座力、換彈(2發)、雙手 | H59: 散射 Scatter
A60: =IF('請先閱讀'!O$29=true,"獵槍(工業革命)","") | B60: 簡易遠程武器 | C60: 2d6 | D60: 80/320 | E60: 穿刺 | F60: 8 | G60: 彈藥(子彈)、火器、換彈(4發)、雙手 | H60: 瞄準 Sighted
A61: =IF('請先閱讀'!O$29=true,"袖珍手槍(工業革命)","") | B61: 簡易遠程武器 | C61: 2d4 | D61: 30/120 | E61: 穿刺 | F61: 1 | G61: 彈藥(子彈)、火器、輕型、換彈(2發) | H61: 侵擾 Vex
A62: =IF('請先閱讀'!O$29=true,"左輪手槍(工業革命)","") | B62: 簡易遠程武器 | C62: 2d6 | D62: 30/120 | E62: 穿刺 | F62: 3 | G62: 彈藥(子彈)、火器、後座力、換彈(6發) | H62: 緩速 Slow
A63: =IF('請先閱讀'!O$29=true,"加農砲(工業革命)","") | B63: 軍用遠程武器 | C63: 2d8 | D63: 100/400 | E63: 火焰 | F63: 225 | G63: 彈藥(砲彈)、火器、重型、裝填、雙手 | H63: 爆破 Explode
A64: =IF('請先閱讀'!O$29=true,"加特林機槍(工業革命)","") | B64: 軍用遠程武器 | C64: 2d6 | D64: 60/240 | E64: 穿刺 | F64: 125 | G64: 彈藥(子彈)、火器、重型、換彈(40發)、雙手 | H64: 自動 Automatic
A65: =IF('請先閱讀'!O$29=true,"麥格農(工業革命)","") | B65: 軍用遠程武器 | C65: 2d8 | D65: 30/120 | E65: 穿刺 | F65: 6 | G65: 彈藥(子彈)、火器、重型、後座力、換彈(6發) | H65: 緩速 Slow
A66: =IF('請先閱讀'!O$29=true,"信號槍(現代)","") | B66: 簡易遠程武器 | C66: 2d6 | D66: 30/120 | E66: 火焰 | F66: 1 | G66: 彈藥(信號彈)、火器、裝填 | H66: 緩速 Slow
A67: =IF('請先閱讀'!O$29=true,"手槍(現代)","") | B67: 簡易遠程武器 | C67: 2d4 | D67: 30/120 | E67: 穿刺 | F67: 3 | G67: 彈藥(子彈)、火器、輕型、換彈(10發) | H67: 侵擾 Vex
A68: =IF('請先閱讀'!O$29=true,"突擊步槍(現代)","") | B68: 軍用遠程武器 | C68: 2d6 | D68: 80/320 | E68: 穿刺 | F68: 7 | G68: 彈藥(子彈)、火器、換彈(20發) | H68: 自動 Automatic
A69: 自動步槍(現代) | B69: 軍用遠程武器 | C69: 2d8 | D69: 80/240 | E69: 穿刺 | F69: 8 | G69: 彈藥(子彈)、掃射、換彈(30發)、雙手 | H69: 緩速 Slow
A70: 獵槍(現代) | B70: 軍用遠程武器 | C70: 2d10 | D70: 80/240 | E70: 穿刺 | F70: 8 | G70: 彈藥(子彈)、換彈(5發)、雙手 | H70: 緩速 Slow
A71: =IF('請先閱讀'!O$29=true,"泵動式霰彈槍(現代)","") | B71: 軍用遠程武器 | C71: 2d8 | D71: 20/60 | E71: 穿刺 | F71: 7 | G71: 彈藥(霰彈)、火器、重型、後座力、換彈(8發)、雙手 | H71: 散射 Scatter
A72: 左輪手槍(現代) | B72: 軍用遠程武器 | C72: 2d8 | D72: 40/120 | E72: 穿刺 | F72: 3 | G72: 彈藥(子彈)、換彈(6發) | H72: 削弱 Sap
A73: 半自動手槍(現代) | B73: 軍用遠程武器 | C73: 2d6 | D73: 50/150 | E73: 穿刺 | F73: 3 | G73: 彈藥(子彈)、換彈(15發) | H73: 侵擾 Vex
A74: 霰彈槍(現代) | B74: 軍用遠程武器 | C74: 2d8 | D74: 30/90 | E74: 穿刺 | F74: 7 | G74: 彈藥(子彈)、換彈(2發)、雙手 | H74: 推離 Push
A75: =IF('請先閱讀'!O$29=true,"狙擊槍(現代)","") | B75: 軍用遠程武器 | C75: 2d8 | D75: 100/400 | E75: 穿刺 | F75: 8 | G75: 彈藥(子彈)、火器、重型、裝填、雙手 | H75: 瞄準 Sighted
A76: =IF('請先閱讀'!O$29=true,"輕機槍(現代)","") | B76: 軍用遠程武器 | C76: 2d4 | D76: 20/60 | E76: 穿刺 | F76: 6 | G76: 彈藥(子彈)、火器、輕型、換彈(16發) | H76: 自動 Automatic
A77: 反物質步槍(未來) | B77: 軍用遠程武器 | C77: 6d8 | D77: 120/360 | E77: 暗蝕 | F77: 10 | G77: 彈藥(能量匣)、換彈(2發)、雙手 | H77: 削弱 Sap
A78: 雷射手槍(未來) | B78: 軍用遠程武器 | C78: 3d6 | D78: 40/120 | E78: 光耀 | F78: 2 | G78: 彈藥(能量匣)、換彈(50發) | H78: 侵擾 Vex
A79: 雷射步槍(未來) | B79: 軍用遠程武器 | C79: 3d8 | D79: 100/300 | E79: 光耀 | F79: 7 | G79: 彈藥(能量匣)、換彈(30發)、雙手 | H79: 緩速 Slow
A80: =IF('請先閱讀'!$O$31=true,"補杖","") | B80: 進階近戰武器 | C80: 1d6 | D80: 觸及(10呎) | E80: 穿刺 | F80: 5 | G80: 裝柄、觸及、雙手 | H80: 捉拿 Entangling
A81: =IF('請先閱讀'!$O$31=true,"騎兵連枷","") | B81: 進階近戰武器 | C81: 1d8(1d12) | D81: 觸及 | E81: 鈍擊 | F81: 3 | G81: 動能 | H81: 迅捷 Swift
A82: =IF('請先閱讀'!$O$31=true,"騎兵鐵鎚","") | B82: 進階近戰武器 | C82: 1d8(1d12) | D82: 觸及 | E82: 鈍擊 | F82: 3 | G82: 穿甲、動能 | H82: 緩速 Slow
A83: =IF('請先閱讀'!$O$31=true,"騎兵鎬","") | B83: 進階近戰武器 | C83: 1d8(1d12) | D83: 觸及 | E83: 穿刺 | F83: 3 | G83: 穿甲、動能 | H83: 削弱 Sap
A84: =IF('請先閱讀'!$O$31=true,"飛輪","") | B84: 進階近戰武器 | C84: 1d6 | D84: 30/120 | E84: 劈砍 | F84: 1 | G84: 投擲、輕型、靈巧 | H84: 迴旋 Returning
A85: =IF('請先閱讀'!$O$31=true,"闊刃大劍","") | B85: 進階近戰武器 | C85: 2d6 | D85: 觸及 | E85: 劈砍 | F85: 7 | G85: 重型、雙手 | H85: 兇殘 Brutal
A86: =IF('請先閱讀'!$O$31=true,"雙頭刃","") | B86: 進階近戰武器 | C86: 1d6(1d10) | D86: 觸及 | E86: 劈砍 | F86: 5 | G86: 雙頭、動能、雙手 | H86: 預備 Set
A87: =IF('請先閱讀'!$O$31=true,"雙頭矛","") | B87: 進階近戰武器 | C87: 1d6(1d10) | D87: 觸及 | E87: 穿刺 | F87: 4 | G87: 雙頭、動能、雙手 | H87: 預備 Set
A88: =IF('請先閱讀'!$O$31=true,"菁英刺劍","") | B88: 進階近戰武器 | C88: 1d8 | D88: 觸及 | E88: 穿刺 | F88: 2 | G88: 靈巧 | H88: 迅捷 Swift
A89: =IF('請先閱讀'!$O$31=true,"戰鬥鏈","") | B89: 進階近戰武器 | C89: 1d4 | D89: 觸及 | E89: 鈍擊 | F89: 3 | G89: 雙頭、靈巧、觸及、雙手 | H89: 繳械 Disarming
A90: =IF('請先閱讀'!$O$31=true,"戰鬥鏈：兇殘","") | B90: 進階近戰武器 | C90: 1d6 | D90: 觸及 | E90: 劈砍 | F90: 6 | G90: 雙頭、靈巧、觸及、雙手 | H90: 兇殘 Brutal
A91: =IF('請先閱讀'!$O$31=true,"戰鬥鏈：爪鉤","") | B91: 進階近戰武器 | C91: 1d4 | D91: 觸及 | E91: 鈍擊、穿刺 | F91: 3 | G91: 雙頭、靈巧、觸及、雙手 | H91: 捉拿 Entangling
A92: =IF('請先閱讀'!$O$31=true,"戰鬥鏈：鎖鐮","") | B92: 進階近戰武器 | C92: 1d4 | D92: 觸及 | E92: 鈍擊、劈砍 | F92: 3 | G92: 雙頭、靈巧、觸及、雙手 | H92: 捉拿 Entangling
A93: =IF('請先閱讀'!$O$31=true,"角鬥士補網","") | B93: 進階近戰武器 | C93: 1d6 | D93: 46325 | E93: 鈍擊 | F93: 5 | G93: 投擲 | H93: 捉拿 Entangling
A94: =IF('請先閱讀'!$O$31=true,"衛士長柄斧","") | B94: 進階近戰武器 | C94: 1d10 | D94: 觸及 | E94: 劈砍、穿刺 | F94: 9 | G94: 裝柄、重型、觸及、雙手 | H94: 預備 Set
A95: =IF('請先閱讀'!$O$31=true,"騎士騎槍","") | B95: 進階近戰武器 | C95: 2d6(2d10) | D95: 觸及 | E95: 穿刺 | F95: 6 | G95: 動能、觸及、雙手 | H95: 預備 Set
A96: =IF('請先閱讀'!$O$31=true,"騎士配劍","") | B96: 進階近戰武器 | C96: 1d8(1d10) | D96: 觸及 | E96: 劈砍 | F96: 3 | G96: 可雙手 | H96: 防禦 Defending
A97: =IF('請先閱讀'!$O$31=true,"軍叉","") | B97: 進階近戰武器 | C97: 2d6 | D97: 觸及 | E97: 穿刺 | F97: 8 | G97: 裝柄、重型、觸及、雙手 | H97: 繳械 Disarming
A98: =IF('請先閱讀'!$O$31=true,"格擋匕首","") | B98: 進階近戰武器 | C98: 1d6 | D98: 30/120 | E98: 劈砍 | F98: 1 | G98: 投擲、輕型、靈巧 | H98: 迴旋 Returning
A99: =IF('請先閱讀'!$O$31=true,"長柄矛","") | B99: 進階近戰武器 | C99: 1d12 | D99: 觸及 | E99: 穿刺 | F99: 12 | G99: 裝柄、重型、觸及、雙手 | H99: 預備 Set
A100: =IF('請先閱讀'!$O$31=true,"拳刃","") | B100: 進階近戰武器 | C100: 1d4 | D100: 觸及 | E100: 穿刺 | F100: 1 | G100: 穿甲、輕型、靈巧 | H100: 防禦 Defending
...

Sheet 職業套組複製區
B2: 竊賊套裝 Burglar's Pack | J2: # | L2: 重量 | O2: 大使套裝 Diplomat's Pack | W2: # | Y2: 重量 | AB2: 學者套裝 Scholar's Pack | AJ2: # | AL2: 重量
B3: 滾珠(一袋1,000粒) | J3: 1 | L3: 2 | O3: 箱子 | W3: 1 | Y3: 25 | AB3: 書 | AJ3: 1 | AL3: 5
B4: 鈴鐺 | J4: 1 | L4: 0 | O4: 高級服裝 | W4: 1 | Y4: 6 | AB4: 墨水 | AJ4: 1 | AL4: 0
B5: 蠟燭 | J5: 10 | L5: 0 | O5: 墨水 | W5: 1 | Y5: 0 | AB5: 墨水筆 | AJ5: 1 | AL5: 0
B6: 撬棍 | J6: 1 | L6: 5 | O6: 墨水筆 | W6: 5 | Y6: 0 | AB6: 油燈 | AJ6: 1 | AL6: 1
B7: 附蓋提燈 | J7: 1 | L7: 2 | O7: 油燈 | W7: 1 | Y7: 1 | AB7: 燈油 | AJ7: 10 | AL7: 1
B8: 燈油 | J8: 7 | L8: 1 | O8: 燈油 | W8: 4 | Y8: 1 | AB8: 羊皮紙 | AJ8: 10 | AL8: 0
B9: 口糧 | J9: 5 | L9: 2 | O9: 地圖或卷軸筒 | W9: 2 | Y9: 1 | AB9: 打火匣 | AJ9: 1 | AL9: 1
B10: 繩子 | J10: 1 | L10: 5 | O10: 紙 | W10: 5 | Y10: 0
B11: 打火匣 | J11: 1 | L11: 1 | O11: 羊皮紙 | W11: 5 | Y11: 0 | AB11: 祭司套裝 Priest's Pack | AJ11: # | AL11: 重量
B12: 水袋 | J12: 1 | L12: 5 | O12: 香水 | W12: 1 | Y12: 0 | AB12: 毛毯 | AJ12: 1 | AL12: 3
O13: 打火匣 | W13: 1 | Y13: 1 | AB13: 聖水 | AJ13: 1 | AL13: 1
B14: 表演家套裝 Entertainer's Pack | J14: # | L14: 重量 | AB14: 油燈 | AJ14: 1 | AL14: 1
B15: 睡袋 | J15: 1 | L15: 7 | O15: 地城探險家套裝 Dungeoneer's Pack | W15: # | Y15: 重量 | AB15: 口糧 | AJ15: 7 | AL15: 2
B16: 鈴鐺 | J16: 1 | L16: 0 | O16: 鐵蒺藜 | W16: 1 | Y16: 2 | AB16: 長袍 | AJ16: 1 | AL16: 4
B17: 牛眼提燈 | J17: 1 | L17: 2 | O17: 撬棍 | W17: 1 | Y17: 5 | AB17: 打火匣 | AJ17: 1 | AL17: 1
B18: 燈油 | J18: 8 | L18: 1 | O18: 燈油 | W18: 2 | Y18: 1
B19: 鏡子 | J19: 1 | L19: 0.5 | O19: 口糧 | W19: 10 | Y19: 2 | AB19: 探索者套裝 Explorer's Pack | AJ19: # | AL19: 重量
B20: 戲服 | J20: 3 | L20: 4 | O20: 繩子 | W20: 1 | Y20: 5 | AB20: 睡袋 | AJ20: 1 | AL20: 7
B21: 口糧 | J21: 9 | L21: 2 | O21: 打火匣 | W21: 1 | Y21: 1 | AB21: 燈油 | AJ21: 2 | AL21: 1
B22: 打火匣 | J22: 1 | L22: 1 | O22: 火把 | W22: 10 | Y22: 2 | AB22: 口糧 | AJ22: 10 | AL22: 2
B23: 水袋 | J23: 1 | L23: 5 | O23: 水袋 | W23: 1 | Y23: 5 | AB23: 繩子 | AJ23: 1 | AL23: 5
AB24: 打火匣 | AJ24: 1 | AL24: 1
AB25: 火把 | AJ25: 10 | AL25: 2
AB26: 水袋 | AJ26: 1 | AL26: 5

Sheet 角色扮演特質
B2: 力量特質 | C2: 敏捷特質 | D2: 體魄特質 | E2: 智力特質 | F2: 感知特質 | G2: 魅力特質
B3: 肌肉發達Muscular | C3: 輕盈Lithe | D3: 精力充沛Energetic | E3: 果斷Decisive | F3: 平靜祥和Serene | G3: 迷人Charming
B4: 強健Sinewy | C4: 活潑Dynamic | D4: 身強體壯Hale | E4: 邏輯性強Logical | F4: 體貼Considerate | G4: 威嚴Commanding
B5: 安全感Protective | C5: 好動Fidgety | D5: 熱情Hearty | E5: 博學多聞Informative | F5: 細心Attentive | G5: 幽默風趣Hilarious
B6: 直率Direct | C6: 沉著Poised | D6: 沉穩Stable | E6: 凡事好奇Curious | F6: 警覺Wary | G6: 鼓舞人心Inspiring
B7: --高低區分線-- | C7: --高低區分線-- | D7: --高低區分線-- | E7: --高低區分線-- | F7: --高低區分線-- | G7: --高低區分線--
B8: 虛弱Weak | C8: 緊張不安Jittery | D8: 體弱多病Frail | E8: 單蠢Artless | F8: 草率Rash | G8: 迂腐Pedantic
B9: 纖細Slight | C9: 笨拙Clumsy | D9: 神經質Squeamish | E9: 沒邏輯Illogical | F9: 容易分心Distracted | G9: 缺乏幽默Humorless
B10: 侷促Self-conscious | C10: 優柔寡斷Hesitant | D10: 無精打采Lethargic | E10: 沒見識Uninformed | F10: 冷漠Oblivious | G10: 內向拘謹Reserved
B11: 不坦率Indirect | C11: 陰晴不定Unsteady | D11: 情感脆弱Fragile | E11: 輕浮Frivolous | F11: 天真Naive | G11: 無禮Tactless
B13: 善良特質 | C13: 邪惡特質 | D13: 中立特質 | E13: 守序特質 | F13: 混亂特質 | H13: =IF(OR('角色卡'!AZ7="守序善良LG",'角色卡'!AZ7="中立善良NG",'角色卡'!AZ7="混亂善良CG"),"善良特質",IF(OR('角色卡'!AZ7="守序中立LN",'角色卡'!AZ7="絕對中立TN",'角色卡'!AZ7="混亂中立CN"),"中立特質",IF(OR('角色卡'!AZ7="守序邪惡LE",'角色卡'!AZ7="中立邪惡NE",'角色卡'!AZ7="混亂邪惡CE"),"邪惡特質",""))) | I13: =IF(OR('角色卡'!AZ7="守序善良LG",'角色卡'!AZ7="守序中立LN",'角色卡'!AZ7="守序邪惡LE"),"守序特質",IF(OR('角色卡'!AZ7="中立善良NG",'角色卡'!AZ7="絕對中立TN",'角色卡'!AZ7="中立邪惡NE"),"中立特質",IF(OR('角色卡'!AZ7="混亂善良CG",'角色卡'!AZ7="混亂中立CN",'角色卡'!AZ7="混亂邪惡CE"),"混亂特質","")))
B14: 富同情心Compassionate | C14: 說謊成性Dishonest | D14: 自私Selfish | E14: 善於合作Cooperative | F14: 大頭症Boastful | H14: =IFNA(HLOOKUP(H13,$B$13:$F$17,2,FALSE),"") | I14: =IFNA(HLOOKUP(I13,$B$13:$F$17,2,FALSE),"")
B15: 樂於助人Helpful | C15: 報復心強Vengeful | D15: 公正客觀Disinterested | E15: 忠誠Loyal | F15: 衝動Impulsive | H15: =IFNA(HLOOKUP(H13,$B$13:$F$17,3,FALSE),"") | I15: =IFNA(HLOOKUP(I13,$B$13:$F$17,3,FALSE),"")
B16: 誠懇Honest | C16: 殘忍Cruel | D16: 簡潔Laconic | E16: 嚴以待人Judgemental | F16: 叛逆Rebellious | H16: =IFNA(HLOOKUP(H13,$B$13:$F$17,4,FALSE),"") | I16: =IFNA(HLOOKUP(I13,$B$13:$F$17,4,FALSE),"")
B17: 親切Kind | C17: 貪婪Greedy | D17: 務實Pragmatic | E17: 有條不紊Methodical | F17: 自我中心Self-absorbed | H17: =IFNA(HLOOKUP(H13,$B$13:$F$17,5,FALSE),"") | I17: =IFNA(HLOOKUP(I13,$B$13:$F$17,5,FALSE),"")

Sheet 法術表
B4: 法術表
C6: 準備法術 | F6: 每日法術環
C7: =IF('角色卡'!AB16="","職業I",'角色卡'!AB16) -> 法師-Wizard | D7: =IFNA(HLOOKUP(C7,'準備法術'!C1:M22,IFNA(HLOOKUP(C7,'準備法術'!C1:M2,2,FALSE),0)+2,FALSE),0) -> 6 | F7: 一環 | G7: FALSE | H7: FALSE | I7: FALSE | J7: FALSE | K7: 六環 | L7: FALSE | M7: FALSE
C8: =IF('角色卡'!AB17="","職業II",'角色卡'!AB17) -> 職業II | D8: =IFNA(HLOOKUP(C8,'準備法術'!C1:M22,IFNA(HLOOKUP(C8,'準備法術'!C1:M2,2,FALSE),0)+2,FALSE),0) -> 0 | F8: 二環 | G8: FALSE | H8: FALSE | I8: FALSE | K8: 七環 | L8: FALSE | M8: FALSE | N8: 職業Ⅰ 法術豁免DC | O8: =IF('角色卡'!AB16="野蠻人-Barbarian",0, IF('角色卡'!AB16="法師-Wizard",8+Prof+IntMod, IF('角色卡'!AB16="術士-Sorcerer",8+Prof+ChaMod, IF('角色卡'!AB16="聖騎士-Paladin",8+Prof+ChaMod, IF('角色卡'!AB16="武僧-Monk",0, IF('角色卡'!AB16="契術師-Warlock",8+Prof+ChaMod, IF('角色卡'!AB16="吟遊詩人-Bard",8+Prof+ChaMod, IF('角色卡'!AB16="牧師-Cleric",8+Prof+WisMod, IF('角色卡'!AB16="德魯伊-Druid",8+Prof+WisMod, IF('角色卡'!AB16="遊俠-Ranger",8+Prof+WisMod, IF('角色卡'!AB16="戰士-Fighter",8+Prof+IntMod, IF('角色卡'!AB16="盜賊-Rogue",8+Prof+IntMod, IF('角色卡'!AB16="奇械師-Artificer",8+Prof+IntMod, IF('角色卡'!AB16="銃士-Gunslinger",8+Prof+IntMod, IF('角色卡'!AB16="",0,))))))))))))))) -> 13 | P8: 職業Ⅰ 法術攻擊調整值 | V8: =IF('角色卡'!AB16="野蠻人-Barbarian", 0, IF('角色卡'!AB16="法師-Wizard" ,Prof+IntMod, IF('角色卡'!AB16="術士-Sorcerer",Prof+ChaMod, IF('角色卡'!AB16="聖騎士-Paladin",Prof+ChaMod, IF('角色卡'!AB16="吟遊詩人-Bard",Prof+ChaMod, IF('角色卡'!AB16="契術師-Warlock",Prof+ChaMod, IF('角色卡'!AB16="武僧-Monk",0, IF('角色卡'!AB16="牧師-Cleric",Prof+WisMod, IF('角色卡'!AB16="德魯伊-Druid",Prof+WisMod, IF('角色卡'!AB16="遊俠-Ranger",Prof+WisMod, IF('角色卡'!AB16="戰士-Fighter",Prof+IntMod, IF('角色卡'!AB16="盜賊-Rogue",Prof+IntMod, IF('角色卡'!AB16="奇械師-Artificer" ,Prof+IntMod, IF('角色卡'!AB16="銃士-Gunslinger" ,Prof+IntMod, IF('角色卡'!AB16="",0,))))))))))))))) -> 5
C9: =IF('角色卡'!AB18="","職業III",'角色卡'!AB18) -> 職業III | D9: =IFNA(HLOOKUP(C9,'準備法術'!C1:M22,IFNA(HLOOKUP(C9,'準備法術'!C1:M2,2,FALSE),0)+2,FALSE),0) -> 0 | F9: 三環 | G9: FALSE | H9: FALSE | I9: FALSE | K9: 八環 | L9: FALSE
F10: 四環 | G10: FALSE | H10: FALSE | I10: FALSE | K10: 九環 | L10: FALSE | N10: 職業Ⅱ 法術豁免DC | O10: =IF('角色卡'!AB17="野蠻人-Barbarian",0, IF('角色卡'!AB17="法師-Wizard",8+Prof+IntMod, IF('角色卡'!AB17="術士-Sorcerer",8+Prof+ChaMod, IF('角色卡'!AB17="聖騎士-Paladin",8+Prof+ChaMod, IF('角色卡'!AB17="武僧-Monk",0, IF('角色卡'!AB17="契術師-Warlock",8+Prof+ChaMod, IF('角色卡'!AB17="吟遊詩人-Bard",8+Prof+ChaMod, IF('角色卡'!AB17="牧師-Cleric",8+Prof+WisMod, IF('角色卡'!AB17="德魯伊-Druid",8+Prof+WisMod, IF('角色卡'!AB17="遊俠-Ranger",8+Prof+WisMod, IF('角色卡'!AB17="戰士-Fighter",8+Prof+IntMod, IF('角色卡'!AB17="盜賊-Rogue",8+Prof+IntMod, IF('角色卡'!AB17="奇械師-Artificer",8+Prof+IntMod, IF('角色卡'!AB17="銃士-Gunslinger",8+Prof+IntMod, IF('角色卡'!AB17="",0,))))))))))))))) -> 0 | P10: 職業Ⅱ 法術攻擊調整值 | V10: =IF('角色卡'!AB17="野蠻人-Barbarian", 0,IF('角色卡'!AB17="法師-Wizard" ,Prof+IntMod,IF('角色卡'!AB17="術士-Sorcerer",Prof+ChaMod,IF('角色卡'!AB17="聖騎士-Paladin",Prof+ChaMod,IF('角色卡'!AB17="吟遊詩人-Bard",Prof+ChaMod,IF('角色卡'!AB17="契術師-Warlock",Prof+ChaMod,IF('角色卡'!AB17="武僧-Monk",0,IF('角色卡'!AB17="牧師-Cleric",Prof+WisMod,IF('角色卡'!AB17="德魯伊-Druid",Prof+WisMod,IF('角色卡'!AB17="遊俠-Ranger",Prof+WisMod,IF('角色卡'!AB17="戰士-Fighter",Prof+IntMod,IF('角色卡'!AB17="盜賊-Rogue",Prof+IntMod,IF('角色卡'!AB17="奇械師-Artificer" ,Prof+IntMod,IF('角色卡'!AB17="銃士-Gunslinger" ,Prof+IntMod,IF('角色卡'!AB17="",0,))))))))))))))) -> 0
C11: 施法等級 | F11: 五環 | G11: FALSE | H11: FALSE | I11: FALSE
C12: 施法 | D12: ='索引資料'!C13 -> 3 | N12: 職業Ⅲ 法術豁免DC | O12: =IF('角色卡'!AB18="野蠻人-Barbarian",0, IF('角色卡'!AB18="法師-Wizard",8+Prof+IntMod, IF('角色卡'!AB18="術士-Sorcerer",8+Prof+ChaMod, IF('角色卡'!AB18="聖騎士-Paladin",8+Prof+ChaMod, IF('角色卡'!AB18="武僧-Monk",0, IF('角色卡'!AB18="契術師-Warlock",8+Prof+ChaMod, IF('角色卡'!AB18="吟遊詩人-Bard",8+Prof+ChaMod, IF('角色卡'!AB18="牧師-Cleric",8+Prof+WisMod, IF('角色卡'!AB18="德魯伊-Druid",8+Prof+WisMod, IF('角色卡'!AB18="遊俠-Ranger",8+Prof+WisMod, IF('角色卡'!AB18="戰士-Fighter",8+Prof+IntMod, IF('角色卡'!AB18="盜賊-Rogue",8+Prof+IntMod, IF('角色卡'!AB18="奇械師-Artificer",8+Prof+IntMod, IF('角色卡'!AB18="銃士-Gunslinger",8+Prof+IntMod, IF('角色卡'!AB18="",0,))))))))))))))) -> 0 | P12: 職業Ⅲ 法術攻擊調整值 | V12: =IF('角色卡'!AB18="野蠻人-Barbarian",0,IF('角色卡'!AB18="法師-Wizard" ,Prof+IntMod,IF('角色卡'!AB18="術士-Sorcerer",Prof+ChaMod,IF('角色卡'!AB18="聖騎士-Paladin",Prof+ChaMod,IF('角色卡'!AB18="吟遊詩人-Bard",Prof+ChaMod,IF('角色卡'!AB18="契術師-Warlock",Prof+ChaMod,IF('角色卡'!AB18="武僧-Monk",0,IF('角色卡'!AB18="牧師-Cleric",Prof+WisMod,IF('角色卡'!AB18="德魯伊-Druid",Prof+WisMod,IF('角色卡'!AB18="遊俠-Ranger",Prof+WisMod,IF('角色卡'!AB18="戰士-Fighter",Prof+IntMod,IF('角色卡'!AB18="盜賊-Rogue",Prof+IntMod,IF('角色卡'!AB18="奇械師-Artificer" ,Prof+IntMod,IF('角色卡'!AB18="銃士-Gunslinger" ,Prof+IntMod,IF('角色卡'!AB18="",0,))))))))))))))) -> 0
C13: 契約魔法 | D13: ='索引資料'!C14 -> 0 | F13: 契約法術環 | H13: =IF('索引資料'!C14>=9,"五環",IF('索引資料'!C14>=7,"四環",IF('索引資料'!C14>=5,"三環",IF('索引資料'!C14>=3,"二環","一環")))) -> 一環 | J13: FALSE | K13: FALSE | L13: FALSE | M13: FALSE
C15: 戲法
C16: 已準備 | D16: 來源 | E16: 法術名稱 | H16: 學派 | I16: 施法時間 | L16: 法術射程 | N16: 法術效果 | P16: 持續時間 | Q16: 專注 | R16: 儀式 | S16: 構材 | V16: 花費材料
S17: 聲音 | T17: 姿勢 | U17: 材料
C18: FALSE | E18: 冷凍射線 | H18: =IFNA(VLOOKUP($E18,'法術資料'!$K$2:$X$805,4,FALSE),"") -> 塑能 | I18: =IFNA(VLOOKUP($E18,'法術資料'!$K$2:$X$805,7,FALSE),"") -> 動作 | L18: =IFNA(VLOOKUP($E18,'法術資料'!$K$2:$X$805,8,FALSE),"") -> 60 呎 | N18: =IFNA(VLOOKUP($E18,'法術資料'!$K$2:$X$805,14,FALSE),"") -> 一道冰冷的藍白色光線朝施法距離內的一名生物射去。對目標進行一次遠程法術攻擊。若命中，則目標受到1d8點寒冷傷害，並且直到你的下一輪開始，速度減少10呎。 戲法升級：當你到達特定等級時，其傷害增加1d8（5級2d8、11級3d8、17級4d8）。 | P18: =IFNA(VLOOKUP($E18,'法術資料'!$K$2:$X$805,13,FALSE),"") -> 即效 | Q18: =IFNA(VLOOKUP($E18,'法術資料'!$K$2:$X$805,5,FALSE),"") -> FALSE | R18: =IFNA(VLOOKUP($E18,'法術資料'!$K$2:$X$805,6,FALSE),"") -> FALSE | S18: =IFNA(VLOOKUP($E18,'法術資料'!$K$2:$X$805,9,FALSE),"") -> TRUE | T18: =IFNA(VLOOKUP($E18,'法術資料'!$K$2:$X$805,10,FALSE),"") -> TRUE | U18: =IFNA(VLOOKUP($E18,'法術資料'!$K$2:$X$805,11,FALSE),"") -> FALSE | V18: =IFNA(VLOOKUP($E18,'法術資料'!$K$2:$W$805,12,FALSE),"")
C19: FALSE | E19: 電爪 | H19: =IFNA(VLOOKUP($E19,'法術資料'!$K$2:$X$805,4,FALSE),"") -> 塑能 | I19: =IFNA(VLOOKUP($E19,'法術資料'!$K$2:$X$805,7,FALSE),"") -> 動作 | L19: =IFNA(VLOOKUP($E19,'法術資料'!$K$2:$X$805,8,FALSE),"") -> 觸碰 | N19: =IFNA(VLOOKUP($E19,'法術資料'!$K$2:$X$805,14,FALSE),"") -> 你放出閃電，擊向一名你試圖觸碰的生物。對目標發動一次近戰法術攻擊。若命中，則目標受到1d8 點閃電傷害，且在其下一輪開始前不能執行借機攻擊。 戲法升級：此法術的傷害會在你達到下列等級時增加1d8：5級（2d8），11 級（3d8），17 級1d8（4d8）。 | P19: =IFNA(VLOOKUP($E19,'法術資料'!$K$2:$X$805,13,FALSE),"") -> 即效 | Q19: =IFNA(VLOOKUP($E19,'法術資料'!$K$2:$X$805,5,FALSE),"") -> FALSE | R19: =IFNA(VLOOKUP($E19,'法術資料'!$K$2:$X$805,6,FALSE),"") -> FALSE | S19: =IFNA(VLOOKUP($E19,'法術資料'!$K$2:$X$805,9,FALSE),"") -> TRUE | T19: =IFNA(VLOOKUP($E19,'法術資料'!$K$2:$X$805,10,FALSE),"") -> TRUE | U19: =IFNA(VLOOKUP($E19,'法術資料'!$K$2:$X$805,11,FALSE),"") -> FALSE | V19: =IFNA(VLOOKUP($E19,'法術資料'!$K$2:$W$805,12,FALSE),"")
C20: FALSE | E20: 光亮術 | H20: =IFNA(VLOOKUP($E20,'法術資料'!$K$2:$X$805,4,FALSE),"") -> 塑能 | I20: =IFNA(VLOOKUP($E20,'法術資料'!$K$2:$X$805,7,FALSE),"") -> 動作 | L20: =IFNA(VLOOKUP($E20,'法術資料'!$K$2:$X$805,8,FALSE),"") -> 觸碰 | N20: =IFNA(VLOOKUP($E20,'法術資料'!$K$2:$X$805,14,FALSE),"") -> 你觸碰一個大型或更小，且未被他人攜帶或穿著的物件。在法術終止前，物件將在其20 呎半徑範圍內發出明亮光照，並在其外20 呎範圍發出微光光照。光的顏色由你決定。 當物體被不透明的東西完全遮蓋時，其光照被遮蔽。如果你再次施展該法術，則該法術終止。 | P20: =IFNA(VLOOKUP($E20,'法術資料'!$K$2:$X$805,13,FALSE),"") -> 1 小時 | Q20: =IFNA(VLOOKUP($E20,'法術資料'!$K$2:$X$805,5,FALSE),"") -> FALSE | R20: =IFNA(VLOOKUP($E20,'法術資料'!$K$2:$X$805,6,FALSE),"") -> FALSE | S20: =IFNA(VLOOKUP($E20,'法術資料'!$K$2:$X$805,9,FALSE),"") -> TRUE | T20: =IFNA(VLOOKUP($E20,'法術資料'!$K$2:$X$805,10,FALSE),"") -> FALSE | U20: =IFNA(VLOOKUP($E20,'法術資料'!$K$2:$X$805,11,FALSE),"") -> TRUE | V20: =IFNA(VLOOKUP($E20,'法術資料'!$K$2:$W$805,12,FALSE),"") -> 一隻螢火蟲或一片磷光苔蘚
C21: FALSE | E21: 毒氣噴灑 | H21: =IFNA(VLOOKUP($E21,'法術資料'!$K$2:$X$805,4,FALSE),"") -> 死靈 | I21: =IFNA(VLOOKUP($E21,'法術資料'!$K$2:$X$805,7,FALSE),"") -> 動作 | L21: =IFNA(VLOOKUP($E21,'法術資料'!$K$2:$X$805,8,FALSE),"") -> 30 呎 | N21: =IFNA(VLOOKUP($E21,'法術資料'!$K$2:$X$805,14,FALSE),"") -> 你向施法距離內一個你可見的生物噴出一股毒氣。對目標進行一次遠程法術攻擊。命中，則目標受1d12點毒素傷害。 戲法升級：當你到達特定等級時，其傷害增加1d12（5級2d12、11級3d12、17級4d12）。 | P21: =IFNA(VLOOKUP($E21,'法術資料'!$K$2:$X$805,13,FALSE),"") -> 即效 | Q21: =IFNA(VLOOKUP($E21,'法術資料'!$K$2:$X$805,5,FALSE),"") -> FALSE | R21: =IFNA(VLOOKUP($E21,'法術資料'!$K$2:$X$805,6,FALSE),"") -> FALSE | S21: =IFNA(VLOOKUP($E21,'法術資料'!$K$2:$X$805,9,FALSE),"") -> TRUE | T21: =IFNA(VLOOKUP($E21,'法術資料'!$K$2:$X$805,10,FALSE),"") -> TRUE | U21: =IFNA(VLOOKUP($E21,'法術資料'!$K$2:$X$805,11,FALSE),"") -> FALSE | V21: =IFNA(VLOOKUP($E21,'法術資料'!$K$2:$W$805,12,FALSE),"")
C22: FALSE | E22: 酸液濺爆 | H22: =IFNA(VLOOKUP($E22,'法術資料'!$K$2:$X$805,4,FALSE),"") -> 塑能 | I22: =IFNA(VLOOKUP($E22,'法術資料'!$K$2:$X$805,7,FALSE),"") -> 動作 | L22: =IFNA(VLOOKUP($E22,'法術資料'!$K$2:$X$805,8,FALSE),"") -> 60 呎 | N22: =IFNA(VLOOKUP($E22,'法術資料'!$K$2:$X$805,14,FALSE),"") -> 你在施法距離內一點創造出一顆酸液泡，在該點5呎球狀範圍內爆發。該球狀區域內的每個生物必須通過敏捷豁免，否則受到1d6強酸傷害。 戲法升級。此法術的傷害會在你達到下列等級時提升1d6：5級（2d6）、11級（3d6）以及17級（4d6）。 | P22: =IFNA(VLOOKUP($E22,'法術資料'!$K$2:$X$805,13,FALSE),"") -> 即效 | Q22: =IFNA(VLOOKUP($E22,'法術資料'!$K$2:$X$805,5,FALSE),"") -> FALSE | R22: =IFNA(VLOOKUP($E22,'法術資料'!$K$2:$X$805,6,FALSE),"") -> FALSE | S22: =IFNA(VLOOKUP($E22,'法術資料'!$K$2:$X$805,9,FALSE),"") -> TRUE | T22: =IFNA(VLOOKUP($E22,'法術資料'!$K$2:$X$805,10,FALSE),"") -> TRUE | U22: =IFNA(VLOOKUP($E22,'法術資料'!$K$2:$X$805,11,FALSE),"") -> FALSE | V22: =IFNA(VLOOKUP($E22,'法術資料'!$K$2:$W$805,12,FALSE),"")
C23: FALSE | H23: =IFNA(VLOOKUP($E23,'法術資料'!$K$2:$X$805,4,FALSE),"") | I23: =IFNA(VLOOKUP($E23,'法術資料'!$K$2:$X$805,7,FALSE),"") | L23: =IFNA(VLOOKUP($E23,'法術資料'!$K$2:$X$805,8,FALSE),"") | N23: =IFNA(VLOOKUP($E23,'法術資料'!$K$2:$X$805,14,FALSE),"") | P23: =IFNA(VLOOKUP($E23,'法術資料'!$K$2:$X$805,13,FALSE),"") | Q23: =IFNA(VLOOKUP($E23,'法術資料'!$K$2:$X$805,5,FALSE),"") | R23: =IFNA(VLOOKUP($E23,'法術資料'!$K$2:$X$805,6,FALSE),"") | S23: =IFNA(VLOOKUP($E23,'法術資料'!$K$2:$X$805,9,FALSE),"") | T23: =IFNA(VLOOKUP($E23,'法術資料'!$K$2:$X$805,10,FALSE),"") | U23: =IFNA(VLOOKUP($E23,'法術資料'!$K$2:$X$805,11,FALSE),"") | V23: =IFNA(VLOOKUP($E23,'法術資料'!$K$2:$W$805,12,FALSE),"")
C24: FALSE | H24: =IFNA(VLOOKUP($E24,'法術資料'!$K$2:$X$805,4,FALSE),"") | I24: =IFNA(VLOOKUP($E24,'法術資料'!$K$2:$X$805,7,FALSE),"") | L24: =IFNA(VLOOKUP($E24,'法術資料'!$K$2:$X$805,8,FALSE),"") | N24: =IFNA(VLOOKUP($E24,'法術資料'!$K$2:$X$805,14,FALSE),"") | P24: =IFNA(VLOOKUP($E24,'法術資料'!$K$2:$X$805,13,FALSE),"") | Q24: =IFNA(VLOOKUP($E24,'法術資料'!$K$2:$X$805,5,FALSE),"") | R24: =IFNA(VLOOKUP($E24,'法術資料'!$K$2:$X$805,6,FALSE),"") | S24: =IFNA(VLOOKUP($E24,'法術資料'!$K$2:$X$805,9,FALSE),"") | T24: =IFNA(VLOOKUP($E24,'法術資料'!$K$2:$X$805,10,FALSE),"") | U24: =IFNA(VLOOKUP($E24,'法術資料'!$K$2:$X$805,11,FALSE),"") | V24: =IFNA(VLOOKUP($E24,'法術資料'!$K$2:$W$805,12,FALSE),"")
C25: FALSE | H25: =IFNA(VLOOKUP($E25,'法術資料'!$K$2:$X$805,4,FALSE),"") | I25: =IFNA(VLOOKUP($E25,'法術資料'!$K$2:$X$805,7,FALSE),"") | L25: =IFNA(VLOOKUP($E25,'法術資料'!$K$2:$X$805,8,FALSE),"") | N25: =IFNA(VLOOKUP($E25,'法術資料'!$K$2:$X$805,14,FALSE),"") | P25: =IFNA(VLOOKUP($E25,'法術資料'!$K$2:$X$805,13,FALSE),"") | Q25: =IFNA(VLOOKUP($E25,'法術資料'!$K$2:$X$805,5,FALSE),"") | R25: =IFNA(VLOOKUP($E25,'法術資料'!$K$2:$X$805,6,FALSE),"") | S25: =IFNA(VLOOKUP($E25,'法術資料'!$K$2:$X$805,9,FALSE),"") | T25: =IFNA(VLOOKUP($E25,'法術資料'!$K$2:$X$805,10,FALSE),"") | U25: =IFNA(VLOOKUP($E25,'法術資料'!$K$2:$X$805,11,FALSE),"") | V25: =IFNA(VLOOKUP($E25,'法術資料'!$K$2:$W$805,12,FALSE),"")
C26: FALSE | H26: =IFNA(VLOOKUP($E26,'法術資料'!$K$2:$X$805,4,FALSE),"") | I26: =IFNA(VLOOKUP($E26,'法術資料'!$K$2:$X$805,7,FALSE),"") | L26: =IFNA(VLOOKUP($E26,'法術資料'!$K$2:$X$805,8,FALSE),"") | N26: =IFNA(VLOOKUP($E26,'法術資料'!$K$2:$X$805,14,FALSE),"") | P26: =IFNA(VLOOKUP($E26,'法術資料'!$K$2:$X$805,13,FALSE),"") | Q26: =IFNA(VLOOKUP($E26,'法術資料'!$K$2:$X$805,5,FALSE),"") | R26: =IFNA(VLOOKUP($E26,'法術資料'!$K$2:$X$805,6,FALSE),"") | S26: =IFNA(VLOOKUP($E26,'法術資料'!$K$2:$X$805,9,FALSE),"") | T26: =IFNA(VLOOKUP($E26,'法術資料'!$K$2:$X$805,10,FALSE),"") | U26: =IFNA(VLOOKUP($E26,'法術資料'!$K$2:$X$805,11,FALSE),"") | V26: =IFNA(VLOOKUP($E26,'法術資料'!$K$2:$W$805,12,FALSE),"")
C27: FALSE | H27: =IFNA(VLOOKUP($E27,'法術資料'!$K$2:$X$805,4,FALSE),"") | I27: =IFNA(VLOOKUP($E27,'法術資料'!$K$2:$X$805,7,FALSE),"") | L27: =IFNA(VLOOKUP($E27,'法術資料'!$K$2:$X$805,8,FALSE),"") | N27: =IFNA(VLOOKUP($E27,'法術資料'!$K$2:$X$805,14,FALSE),"") | P27: =IFNA(VLOOKUP($E27,'法術資料'!$K$2:$X$805,13,FALSE),"") | Q27: =IFNA(VLOOKUP($E27,'法術資料'!$K$2:$X$805,5,FALSE),"") | R27: =IFNA(VLOOKUP($E27,'法術資料'!$K$2:$X$805,6,FALSE),"") | S27: =IFNA(VLOOKUP($E27,'法術資料'!$K$2:$X$805,9,FALSE),"") | T27: =IFNA(VLOOKUP($E27,'法術資料'!$K$2:$X$805,10,FALSE),"") | U27: =IFNA(VLOOKUP($E27,'法術資料'!$K$2:$X$805,11,FALSE),"") | V27: =IFNA(VLOOKUP($E27,'法術資料'!$K$2:$W$805,12,FALSE),"")
C30: 一環
C31: 已準備 | D31: 來源 | E31: 法術名稱 | H31: 學派 | I31: 施法時間 | L31: 法術射程 | N31: 法術效果 | P31: 持續時間 | Q31: 專注 | R31: 儀式 | S31: 構材 | V31: 花費材料
S32: 聲音 | T32: 姿勢 | U32: 材料
C33: FALSE | E33: 法師護甲 | H33: =IFNA(VLOOKUP($E33,'法術資料'!$K$2:$X$805,4,FALSE),"") -> 防護 | I33: =IFNA(VLOOKUP($E33,'法術資料'!$K$2:$X$805,7,FALSE),"") -> 動作 | L33: =IFNA(VLOOKUP($E33,'法術資料'!$K$2:$X$805,8,FALSE),"") -> 觸碰 | N33: =IFNA(VLOOKUP($E33,'法術資料'!$K$2:$X$805,14,FALSE),"") -> 你觸碰一個未著裝護甲的自願生物。直到法術終止前，目標的基礎AC 變成13+它的敏捷調整值。目標著裝護甲則法術提前終止。 | P33: =IFNA(VLOOKUP($E33,'法術資料'!$K$2:$X$805,13,FALSE),"") -> 8 小時 | Q33: =IFNA(VLOOKUP($E33,'法術資料'!$K$2:$X$805,5,FALSE),"") -> FALSE | R33: =IFNA(VLOOKUP($E33,'法術資料'!$K$2:$X$805,6,FALSE),"") -> FALSE | S33: =IFNA(VLOOKUP($E33,'法術資料'!$K$2:$X$805,9,FALSE),"") -> TRUE | T33: =IFNA(VLOOKUP($E33,'法術資料'!$K$2:$X$805,10,FALSE),"") -> TRUE | U33: =IFNA(VLOOKUP($E33,'法術資料'!$K$2:$X$805,11,FALSE),"") -> TRUE | V33: =IFNA(VLOOKUP($E33,'法術資料'!$K$2:$W$805,12,FALSE),"") -> 一塊鞣製過的皮革
C34: FALSE | E34: 護盾術 | H34: =IFNA(VLOOKUP($E34,'法術資料'!$K$2:$X$805,4,FALSE),"") -> 防護 | I34: =IFNA(VLOOKUP($E34,'法術資料'!$K$2:$X$805,7,FALSE),"") -> 反應，當你被攻擊命中或被作為魔法飛彈法術的目標時 | L34: =IFNA(VLOOKUP($E34,'法術資料'!$K$2:$X$805,8,FALSE),"") -> 自身 | N34: =IFNA(VLOOKUP($E34,'法術資料'!$K$2:$X$805,14,FALSE),"") -> 一道看不見的力場製護盾浮現在你身旁，保護著你。在你的下一回合開始前，你的AC 有+5 加值（在觸發該法術的攻擊之前生效），並且不會受到魔法導彈的傷害。 | P34: =IFNA(VLOOKUP($E34,'法術資料'!$K$2:$X$805,13,FALSE),"") -> 1 輪 | Q34: =IFNA(VLOOKUP($E34,'法術資料'!$K$2:$X$805,5,FALSE),"") -> FALSE | R34: =IFNA(VLOOKUP($E34,'法術資料'!$K$2:$X$805,6,FALSE),"") -> FALSE | S34: =IFNA(VLOOKUP($E34,'法術資料'!$K$2:$X$805,9,FALSE),"") -> TRUE | T34: =IFNA(VLOOKUP($E34,'法術資料'!$K$2:$X$805,10,FALSE),"") -> TRUE | U34: =IFNA(VLOOKUP($E34,'法術資料'!$K$2:$X$805,11,FALSE),"") -> FALSE | V34: =IFNA(VLOOKUP($E34,'法術資料'!$K$2:$W$805,12,FALSE),"")
C35: FALSE | E35: 睡眠術 | H35: =IFNA(VLOOKUP($E35,'法術資料'!$K$2:$X$805,4,FALSE),"") -> 惑控 | I35: =IFNA(VLOOKUP($E35,'法術資料'!$K$2:$X$805,7,FALSE),"") -> 動作 | L35: =IFNA(VLOOKUP($E35,'法術資料'!$K$2:$X$805,8,FALSE),"") -> 60 呎 | N35: =IFNA(VLOOKUP($E35,'法術資料'!$K$2:$X$805,14,FALSE),"") -> 以施法距離內一點為源點，5呎半徑球狀區域內每個你選擇的生物都必須成功通過一次感知豁免否則直到其下個回合結束陷入失能狀態。在其下個回合結束時，它必須重複此豁免。如果目標第二次豁免失敗，目標在持續時間內陷入昏迷狀態。如果目標受到傷害，或其5呎內有人用一個動作將它搖醒，目標身上的法術結束。 不會睡眠的生物，例如精靈或免疫力竭Exhaustion狀態的生物自動成功通過對抗此法術的豁免。 | P35: =IFNA(VLOOKUP($E35,'法術資料'!$K$2:$X$805,13,FALSE),"") -> 最多 1 分鐘 | Q35: =IFNA(VLOOKUP($E35,'法術資料'!$K$2:$X$805,5,FALSE),"") -> TRUE | R35: =IFNA(VLOOKUP($E35,'法術資料'!$K$2:$X$805,6,FALSE),"") -> FALSE | S35: =IFNA(VLOOKUP($E35,'法術資料'!$K$2:$X$805,9,FALSE),"") -> TRUE | T35: =IFNA(VLOOKUP($E35,'法術資料'!$K$2:$X$805,10,FALSE),"") -> TRUE | U35: =IFNA(VLOOKUP($E35,'法術資料'!$K$2:$X$805,11,FALSE),"") -> TRUE | V35: =IFNA(VLOOKUP($E35,'法術資料'!$K$2:$W$805,12,FALSE),"") -> 一把細沙或玫瑰花瓣
C36: FALSE | E36: 巫術箭 | H36: =IFNA(VLOOKUP($E36,'法術資料'!$K$2:$X$805,4,FALSE),"") -> 塑能 | I36: =IFNA(VLOOKUP($E36,'法術資料'!$K$2:$X$805,7,FALSE),"") -> 動作 | L36: =IFNA(VLOOKUP($E36,'法術資料'!$K$2:$X$805,8,FALSE),"") -> 60 呎 | N36: =IFNA(VLOOKUP($E36,'法術資料'!$K$2:$X$805,14,FALSE),"") -> 一支纏繞著碎裂魔力的藍色能量長矛射向施法距離內的一個生物，並在你與目標之間生成一道持久的閃電弧。對目標進行一次遠程法術攻擊。若命中，目標受到2d12 點閃電傷害。 在你接下來的每個回合中，即使首次攻擊打失，你仍可以用附贈動作直接對目標造成1d12點閃電傷害。 此外，如果目標離開法術的施法距離或相對你處於全身掩護狀態，法術也會隨即終止。 升環施法效應：使用的法術位每比一環高一環，初始傷害就提高1d12。 | P36: =IFNA(VLOOKUP($E36,'法術資料'!$K$2:$X$805,13,FALSE),"") -> 最多 1 分鐘 | Q36: =IFNA(VLOOKUP($E36,'法術資料'!$K$2:$X$805,5,FALSE),"") -> TRUE | R36: =IFNA(VLOOKUP($E36,'法術資料'!$K$2:$X$805,6,FALSE),"") -> FALSE | S36: =IFNA(VLOOKUP($E36,'法術資料'!$K$2:$X$805,9,FALSE),"") -> TRUE | T36: =IFNA(VLOOKUP($E36,'法術資料'!$K$2:$X$805,10,FALSE),"") -> TRUE | U36: =IFNA(VLOOKUP($E36,'法術資料'!$K$2:$X$805,11,FALSE),"") -> TRUE | V36: =IFNA(VLOOKUP($E36,'法術資料'!$K$2:$W$805,12,FALSE),"") -> 一根被閃電擊中的樹枝
C37: FALSE | E37: 跳躍術 | H37: =IFNA(VLOOKUP($E37,'法術資料'!$K$2:$X$805,4,FALSE),"") -> 變化 | I37: =IFNA(VLOOKUP($E37,'法術資料'!$K$2:$X$805,7,FALSE),"") -> 附贈動作 | L37: =IFNA(VLOOKUP($E37,'法術資料'!$K$2:$X$805,8,FALSE),"") -> 觸碰 | N37: =IFNA(VLOOKUP($E37,'法術資料'!$K$2:$X$805,14,FALSE),"") -> 你觸碰一個自願生物。在法術結束前，每個他的回合內一次該生物可以消耗10呎移動力來跳躍30呎。 升環施法效應：使用二環或更高法術位施展該法術時，你使用的法術位每比一環高一環，就可以額外指定一個生物作為目標。 | P37: =IFNA(VLOOKUP($E37,'法術資料'!$K$2:$X$805,13,FALSE),"") -> 1 分鐘 | Q37: =IFNA(VLOOKUP($E37,'法術資料'!$K$2:$X$805,5,FALSE),"") -> FALSE | R37: =IFNA(VLOOKUP($E37,'法術資料'!$K$2:$X$805,6,FALSE),"") -> FALSE | S37: =IFNA(VLOOKUP($E37,'法術資料'!$K$2:$X$805,9,FALSE),"") -> TRUE | T37: =IFNA(VLOOKUP($E37,'法術資料'!$K$2:$X$805,10,FALSE),"") -> TRUE | U37: =IFNA(VLOOKUP($E37,'法術資料'!$K$2:$X$805,11,FALSE),"") -> TRUE | V37: =IFNA(VLOOKUP($E37,'法術資料'!$K$2:$W$805,12,FALSE),"") -> 一支蚱蜢的後腿
C38: FALSE | H38: =IFNA(VLOOKUP($E38,'法術資料'!$K$2:$X$805,4,FALSE),"") | I38: =IFNA(VLOOKUP($E38,'法術資料'!$K$2:$X$805,7,FALSE),"") | L38: =IFNA(VLOOKUP($E38,'法術資料'!$K$2:$X$805,8,FALSE),"") | N38: =IFNA(VLOOKUP($E38,'法術資料'!$K$2:$X$805,14,FALSE),"") | P38: =IFNA(VLOOKUP($E38,'法術資料'!$K$2:$X$805,13,FALSE),"") | Q38: =IFNA(VLOOKUP($E38,'法術資料'!$K$2:$X$805,5,FALSE),"") | R38: =IFNA(VLOOKUP($E38,'法術資料'!$K$2:$X$805,6,FALSE),"") | S38: =IFNA(VLOOKUP($E38,'法術資料'!$K$2:$X$805,9,FALSE),"") | T38: =IFNA(VLOOKUP($E38,'法術資料'!$K$2:$X$805,10,FALSE),"") | U38: =IFNA(VLOOKUP($E38,'法術資料'!$K$2:$X$805,11,FALSE),"") | V38: =IFNA(VLOOKUP($E38,'法術資料'!$K$2:$W$805,12,FALSE),"")
C39: FALSE | H39: =IFNA(VLOOKUP($E39,'法術資料'!$K$2:$X$805,4,FALSE),"") | I39: =IFNA(VLOOKUP($E39,'法術資料'!$K$2:$X$805,7,FALSE),"") | L39: =IFNA(VLOOKUP($E39,'法術資料'!$K$2:$X$805,8,FALSE),"") | N39: =IFNA(VLOOKUP($E39,'法術資料'!$K$2:$X$805,14,FALSE),"") | P39: =IFNA(VLOOKUP($E39,'法術資料'!$K$2:$X$805,13,FALSE),"") | Q39: =IFNA(VLOOKUP($E39,'法術資料'!$K$2:$X$805,5,FALSE),"") | R39: =IFNA(VLOOKUP($E39,'法術資料'!$K$2:$X$805,6,FALSE),"") | S39: =IFNA(VLOOKUP($E39,'法術資料'!$K$2:$X$805,9,FALSE),"") | T39: =IFNA(VLOOKUP($E39,'法術資料'!$K$2:$X$805,10,FALSE),"") | U39: =IFNA(VLOOKUP($E39,'法術資料'!$K$2:$X$805,11,FALSE),"") | V39: =IFNA(VLOOKUP($E39,'法術資料'!$K$2:$W$805,12,FALSE),"")
C40: FALSE | H40: =IFNA(VLOOKUP($E40,'法術資料'!$K$2:$X$805,4,FALSE),"") | I40: =IFNA(VLOOKUP($E40,'法術資料'!$K$2:$X$805,7,FALSE),"") | L40: =IFNA(VLOOKUP($E40,'法術資料'!$K$2:$X$805,8,FALSE),"") | N40: =IFNA(VLOOKUP($E40,'法術資料'!$K$2:$X$805,14,FALSE),"") | P40: =IFNA(VLOOKUP($E40,'法術資料'!$K$2:$X$805,13,FALSE),"") | Q40: =IFNA(VLOOKUP($E40,'法術資料'!$K$2:$X$805,5,FALSE),"") | R40: =IFNA(VLOOKUP($E40,'法術資料'!$K$2:$X$805,6,FALSE),"") | S40: =IFNA(VLOOKUP($E40,'法術資料'!$K$2:$X$805,9,FALSE),"") | T40: =IFNA(VLOOKUP($E40,'法術資料'!$K$2:$X$805,10,FALSE),"") | U40: =IFNA(VLOOKUP($E40,'法術資料'!$K$2:$X$805,11,FALSE),"") | V40: =IFNA(VLOOKUP($E40,'法術資料'!$K$2:$W$805,12,FALSE),"")
C41: FALSE | H41: =IFNA(VLOOKUP($E41,'法術資料'!$K$2:$X$805,4,FALSE),"") | I41: =IFNA(VLOOKUP($E41,'法術資料'!$K$2:$X$805,7,FALSE),"") | L41: =IFNA(VLOOKUP($E41,'法術資料'!$K$2:$X$805,8,FALSE),"") | N41: =IFNA(VLOOKUP($E41,'法術資料'!$K$2:$X$805,14,FALSE),"") | P41: =IFNA(VLOOKUP($E41,'法術資料'!$K$2:$X$805,13,FALSE),"") | Q41: =IFNA(VLOOKUP($E41,'法術資料'!$K$2:$X$805,5,FALSE),"") | R41: =IFNA(VLOOKUP($E41,'法術資料'!$K$2:$X$805,6,FALSE),"") | S41: =IFNA(VLOOKUP($E41,'法術資料'!$K$2:$X$805,9,FALSE),"") | T41: =IFNA(VLOOKUP($E41,'法術資料'!$K$2:$X$805,10,FALSE),"") | U41: =IFNA(VLOOKUP($E41,'法術資料'!$K$2:$X$805,11,FALSE),"") | V41: =IFNA(VLOOKUP($E41,'法術資料'!$K$2:$W$805,12,FALSE),"")
C42: FALSE | H42: =IFNA(VLOOKUP($E42,'法術資料'!$K$2:$X$805,4,FALSE),"") | I42: =IFNA(VLOOKUP($E42,'法術資料'!$K$2:$X$805,7,FALSE),"") | L42: =IFNA(VLOOKUP($E42,'法術資料'!$K$2:$X$805,8,FALSE),"") | N42: =IFNA(VLOOKUP($E42,'法術資料'!$K$2:$X$805,14,FALSE),"") | P42: =IFNA(VLOOKUP($E42,'法術資料'!$K$2:$X$805,13,FALSE),"") | Q42: =IFNA(VLOOKUP($E42,'法術資料'!$K$2:$X$805,5,FALSE),"") | R42: =IFNA(VLOOKUP($E42,'法術資料'!$K$2:$X$805,6,FALSE),"") | S42: =IFNA(VLOOKUP($E42,'法術資料'!$K$2:$X$805,9,FALSE),"") | T42: =IFNA(VLOOKUP($E42,'法術資料'!$K$2:$X$805,10,FALSE),"") | U42: =IFNA(VLOOKUP($E42,'法術資料'!$K$2:$X$805,11,FALSE),"") | V42: =IFNA(VLOOKUP($E42,'法術資料'!$K$2:$W$805,12,FALSE),"")
C45: 二環
C46: 已準備 | D46: 來源 | E46: 法術名稱 | H46: 學派 | I46: 施法時間 | L46: 法術射程 | N46: 法術效果 | P46: 持續時間 | Q46: 專注 | R46: 儀式 | S46: 構材 | V46: 花費材料
S47: 聲音 | T47: 姿勢 | U47: 材料
C48: FALSE | E48: 隱形術 | H48: =IFNA(VLOOKUP($E48,'法術資料'!$K$2:$X$805,4,FALSE),"") -> 幻術 | I48: =IFNA(VLOOKUP($E48,'法術資料'!$K$2:$X$805,7,FALSE),"") -> 動作 | L48: =IFNA(VLOOKUP($E48,'法術資料'!$K$2:$X$805,8,FALSE),"") -> 觸碰 | N48: =IFNA(VLOOKUP($E48,'法術資料'!$K$2:$X$805,14,FALSE),"") -> 你觸碰的生物進入隱形狀態並維持至法術終止。如果目標進行攻擊檢定、造成傷害或施展法術，則該法術提前終止。 升環施法效應：使用三環或更高法術位施展法術時，你使用的法術位每比二環高一環，就可以額外指定一個生物作為目標。 | P48: =IFNA(VLOOKUP($E48,'法術資料'!$K$2:$X$805,13,FALSE),"") -> 最多 1 小時 | Q48: =IFNA(VLOOKUP($E48,'法術資料'!$K$2:$X$805,5,FALSE),"") -> TRUE | R48: =IFNA(VLOOKUP($E48,'法術資料'!$K$2:$X$805,6,FALSE),"") -> FALSE | S48: =IFNA(VLOOKUP($E48,'法術資料'!$K$2:$X$805,9,FALSE),"") -> TRUE | T48: =IFNA(VLOOKUP($E48,'法術資料'!$K$2:$X$805,10,FALSE),"") -> TRUE | U48: =IFNA(VLOOKUP($E48,'法術資料'!$K$2:$X$805,11,FALSE),"") -> TRUE | V48: =IFNA(VLOOKUP($E48,'法術資料'!$K$2:$W$805,12,FALSE),"") -> 一根包裹在阿拉伯膠中的睫毛
C49: FALSE | E49: 鏡影術 | H49: =IFNA(VLOOKUP($E49,'法術資料'!$K$2:$X$805,4,FALSE),"") -> 幻術 | I49: =IFNA(VLOOKUP($E49,'法術資料'!$K$2:$X$805,7,FALSE),"") -> 動作 | L49: =IFNA(VLOOKUP($E49,'法術資料'!$K$2:$X$805,8,FALSE),"") -> 自身 | N49: =IFNA(VLOOKUP($E49,'法術資料'!$K$2:$X$805,14,FALSE),"") -> 三個你自身的幻象分身出現在你的位置。直到法術終止前，分身都會隨你移動，並模仿你的動作和位置變換，使人無法追蹤判斷哪一個是你的真身。 在法術持續時間內，每當一個生物攻擊命中你時，為每個剩餘分身投擲一個d6，只要有任一d6骰出3或以上，一個分身代你承受本次命中並隨之被摧毀。分身無視於所有其他的傷害和效應。三個分身都被摧毀時，法術隨之結束。 如果生物處於目盲狀態，或擁有盲視，或擁有真實視覺，則該法術無法影響該生物。 | P49: =IFNA(VLOOKUP($E49,'法術資料'!$K$2:$X$805,13,FALSE),"") -> 1 分鐘 | Q49: =IFNA(VLOOKUP($E49,'法術資料'!$K$2:$X$805,5,FALSE),"") -> FALSE | R49: =IFNA(VLOOKUP($E49,'法術資料'!$K$2:$X$805,6,FALSE),"") -> FALSE | S49: =IFNA(VLOOKUP($E49,'法術資料'!$K$2:$X$805,9,FALSE),"") -> TRUE | T49: =IFNA(VLOOKUP($E49,'法術資料'!$K$2:$X$805,10,FALSE),"") -> TRUE | U49: =IFNA(VLOOKUP($E49,'法術資料'!$K$2:$X$805,11,FALSE),"") -> FALSE | V49: =IFNA(VLOOKUP($E49,'法術資料'!$K$2:$W$805,12,FALSE),"")
C50: FALSE | H50: =IFNA(VLOOKUP($E50,'法術資料'!$K$2:$X$805,4,FALSE),"") | I50: =IFNA(VLOOKUP($E50,'法術資料'!$K$2:$X$805,7,FALSE),"") | L50: =IFNA(VLOOKUP($E50,'法術資料'!$K$2:$X$805,8,FALSE),"") | N50: =IFNA(VLOOKUP($E50,'法術資料'!$K$2:$X$805,14,FALSE),"") | P50: =IFNA(VLOOKUP($E50,'法術資料'!$K$2:$X$805,13,FALSE),"") | Q50: =IFNA(VLOOKUP($E50,'法術資料'!$K$2:$X$805,5,FALSE),"") | R50: =IFNA(VLOOKUP($E50,'法術資料'!$K$2:$X$805,6,FALSE),"") | S50: =IFNA(VLOOKUP($E50,'法術資料'!$K$2:$X$805,9,FALSE),"") | T50: =IFNA(VLOOKUP($E50,'法術資料'!$K$2:$X$805,10,FALSE),"") | U50: =IFNA(VLOOKUP($E50,'法術資料'!$K$2:$X$805,11,FALSE),"") | V50: =IFNA(VLOOKUP($E50,'法術資料'!$K$2:$W$805,12,FALSE),"")
C51: FALSE | H51: =IFNA(VLOOKUP($E51,'法術資料'!$K$2:$X$805,4,FALSE),"") | I51: =IFNA(VLOOKUP($E51,'法術資料'!$K$2:$X$805,7,FALSE),"") | L51: =IFNA(VLOOKUP($E51,'法術資料'!$K$2:$X$805,8,FALSE),"") | N51: =IFNA(VLOOKUP($E51,'法術資料'!$K$2:$X$805,14,FALSE),"") | P51: =IFNA(VLOOKUP($E51,'法術資料'!$K$2:$X$805,13,FALSE),"") | Q51: =IFNA(VLOOKUP($E51,'法術資料'!$K$2:$X$805,5,FALSE),"") | R51: =IFNA(VLOOKUP($E51,'法術資料'!$K$2:$X$805,6,FALSE),"") | S51: =IFNA(VLOOKUP($E51,'法術資料'!$K$2:$X$805,9,FALSE),"") | T51: =IFNA(VLOOKUP($E51,'法術資料'!$K$2:$X$805,10,FALSE),"") | U51: =IFNA(VLOOKUP($E51,'法術資料'!$K$2:$X$805,11,FALSE),"") | V51: =IFNA(VLOOKUP($E51,'法術資料'!$K$2:$W$805,12,FALSE),"")
C52: FALSE | H52: =IFNA(VLOOKUP($E52,'法術資料'!$K$2:$X$805,4,FALSE),"") | I52: =IFNA(VLOOKUP($E52,'法術資料'!$K$2:$X$805,7,FALSE),"") | L52: =IFNA(VLOOKUP($E52,'法術資料'!$K$2:$X$805,8,FALSE),"") | N52: =IFNA(VLOOKUP($E52,'法術資料'!$K$2:$X$805,14,FALSE),"") | P52: =IFNA(VLOOKUP($E52,'法術資料'!$K$2:$X$805,13,FALSE),"") | Q52: =IFNA(VLOOKUP($E52,'法術資料'!$K$2:$X$805,5,FALSE),"") | R52: =IFNA(VLOOKUP($E52,'法術資料'!$K$2:$X$805,6,FALSE),"") | S52: =IFNA(VLOOKUP($E52,'法術資料'!$K$2:$X$805,9,FALSE),"") | T52: =IFNA(VLOOKUP($E52,'法術資料'!$K$2:$X$805,10,FALSE),"") | U52: =IFNA(VLOOKUP($E52,'法術資料'!$K$2:$X$805,11,FALSE),"") | V52: =IFNA(VLOOKUP($E52,'法術資料'!$K$2:$W$805,12,FALSE),"")
C53: FALSE | H53: =IFNA(VLOOKUP($E53,'法術資料'!$K$2:$X$805,4,FALSE),"") | I53: =IFNA(VLOOKUP($E53,'法術資料'!$K$2:$X$805,7,FALSE),"") | L53: =IFNA(VLOOKUP($E53,'法術資料'!$K$2:$X$805,8,FALSE),"") | N53: =IFNA(VLOOKUP($E53,'法術資料'!$K$2:$X$805,14,FALSE),"") | P53: =IFNA(VLOOKUP($E53,'法術資料'!$K$2:$X$805,13,FALSE),"") | Q53: =IFNA(VLOOKUP($E53,'法術資料'!$K$2:$X$805,5,FALSE),"") | R53: =IFNA(VLOOKUP($E53,'法術資料'!$K$2:$X$805,6,FALSE),"") | S53: =IFNA(VLOOKUP($E53,'法術資料'!$K$2:$X$805,9,FALSE),"") | T53: =IFNA(VLOOKUP($E53,'法術資料'!$K$2:$X$805,10,FALSE),"") | U53: =IFNA(VLOOKUP($E53,'法術資料'!$K$2:$X$805,11,FALSE),"") | V53: =IFNA(VLOOKUP($E53,'法術資料'!$K$2:$W$805,12,FALSE),"")
C54: FALSE | H54: =IFNA(VLOOKUP($E54,'法術資料'!$K$2:$X$805,4,FALSE),"") | I54: =IFNA(VLOOKUP($E54,'法術資料'!$K$2:$X$805,7,FALSE),"") | L54: =IFNA(VLOOKUP($E54,'法術資料'!$K$2:$X$805,8,FALSE),"") | N54: =IFNA(VLOOKUP($E54,'法術資料'!$K$2:$X$805,14,FALSE),"") | P54: =IFNA(VLOOKUP($E54,'法術資料'!$K$2:$X$805,13,FALSE),"") | Q54: =IFNA(VLOOKUP($E54,'法術資料'!$K$2:$X$805,5,FALSE),"") | R54: =IFNA(VLOOKUP($E54,'法術資料'!$K$2:$X$805,6,FALSE),"") | S54: =IFNA(VLOOKUP($E54,'法術資料'!$K$2:$X$805,9,FALSE),"") | T54: =IFNA(VLOOKUP($E54,'法術資料'!$K$2:$X$805,10,FALSE),"") | U54: =IFNA(VLOOKUP($E54,'法術資料'!$K$2:$X$805,11,FALSE),"") | V54: =IFNA(VLOOKUP($E54,'法術資料'!$K$2:$W$805,12,FALSE),"")
C55: FALSE | H55: =IFNA(VLOOKUP($E55,'法術資料'!$K$2:$X$805,4,FALSE),"") | I55: =IFNA(VLOOKUP($E55,'法術資料'!$K$2:$X$805,7,FALSE),"") | L55: =IFNA(VLOOKUP($E55,'法術資料'!$K$2:$X$805,8,FALSE),"") | N55: =IFNA(VLOOKUP($E55,'法術資料'!$K$2:$X$805,14,FALSE),"") | P55: =IFNA(VLOOKUP($E55,'法術資料'!$K$2:$X$805,13,FALSE),"") | Q55: =IFNA(VLOOKUP($E55,'法術資料'!$K$2:$X$805,5,FALSE),"") | R55: =IFNA(VLOOKUP($E55,'法術資料'!$K$2:$X$805,6,FALSE),"") | S55: =IFNA(VLOOKUP($E55,'法術資料'!$K$2:$X$805,9,FALSE),"") | T55: =IFNA(VLOOKUP($E55,'法術資料'!$K$2:$X$805,10,FALSE),"") | U55: =IFNA(VLOOKUP($E55,'法術資料'!$K$2:$X$805,11,FALSE),"") | V55: =IFNA(VLOOKUP($E55,'法術資料'!$K$2:$W$805,12,FALSE),"")
C58: 三環
C59: 已準備 | D59: 來源 | E59: 法術名稱 | H59: 學派 | I59: 施法時間 | L59: 法術射程 | N59: 法術效果 | P59: 持續時間 | Q59: 專注 | R59: 儀式 | S59: 構材 | V59: 花費材料
S60: 聲音 | T60: 姿勢 | U60: 材料
C61: FALSE | H61: =IFNA(VLOOKUP($E61,'法術資料'!$K$2:$X$805,4,FALSE),"") | I61: =IFNA(VLOOKUP($E61,'法術資料'!$K$2:$X$805,7,FALSE),"") | L61: =IFNA(VLOOKUP($E61,'法術資料'!$K$2:$X$805,8,FALSE),"") | N61: =IFNA(VLOOKUP($E61,'法術資料'!$K$2:$X$805,14,FALSE),"") | P61: =IFNA(VLOOKUP($E61,'法術資料'!$K$2:$X$805,13,FALSE),"") | Q61: =IFNA(VLOOKUP($E61,'法術資料'!$K$2:$X$805,5,FALSE),"") | R61: =IFNA(VLOOKUP($E61,'法術資料'!$K$2:$X$805,6,FALSE),"") | S61: =IFNA(VLOOKUP($E61,'法術資料'!$K$2:$X$805,9,FALSE),"") | T61: =IFNA(VLOOKUP($E61,'法術資料'!$K$2:$X$805,10,FALSE),"") | U61: =IFNA(VLOOKUP($E61,'法術資料'!$K$2:$X$805,11,FALSE),"") | V61: =IFNA(VLOOKUP($E61,'法術資料'!$K$2:$W$805,12,FALSE),"")
C62: FALSE | H62: =IFNA(VLOOKUP($E62,'法術資料'!$K$2:$X$805,4,FALSE),"") | I62: =IFNA(VLOOKUP($E62,'法術資料'!$K$2:$X$805,7,FALSE),"") | L62: =IFNA(VLOOKUP($E62,'法術資料'!$K$2:$X$805,8,FALSE),"") | N62: =IFNA(VLOOKUP($E62,'法術資料'!$K$2:$X$805,14,FALSE),"") | P62: =IFNA(VLOOKUP($E62,'法術資料'!$K$2:$X$805,13,FALSE),"") | Q62: =IFNA(VLOOKUP($E62,'法術資料'!$K$2:$X$805,5,FALSE),"") | R62: =IFNA(VLOOKUP($E62,'法術資料'!$K$2:$X$805,6,FALSE),"") | S62: =IFNA(VLOOKUP($E62,'法術資料'!$K$2:$X$805,9,FALSE),"") | T62: =IFNA(VLOOKUP($E62,'法術資料'!$K$2:$X$805,10,FALSE),"") | U62: =IFNA(VLOOKUP($E62,'法術資料'!$K$2:$X$805,11,FALSE),"") | V62: =IFNA(VLOOKUP($E62,'法術資料'!$K$2:$W$805,12,FALSE),"")
C63: FALSE | H63: =IFNA(VLOOKUP($E63,'法術資料'!$K$2:$X$805,4,FALSE),"") | I63: =IFNA(VLOOKUP($E63,'法術資料'!$K$2:$X$805,7,FALSE),"") | L63: =IFNA(VLOOKUP($E63,'法術資料'!$K$2:$X$805,8,FALSE),"") | N63: =IFNA(VLOOKUP($E63,'法術資料'!$K$2:$X$805,14,FALSE),"") | P63: =IFNA(VLOOKUP($E63,'法術資料'!$K$2:$X$805,13,FALSE),"") | Q63: =IFNA(VLOOKUP($E63,'法術資料'!$K$2:$X$805,5,FALSE),"") | R63: =IFNA(VLOOKUP($E63,'法術資料'!$K$2:$X$805,6,FALSE),"") | S63: =IFNA(VLOOKUP($E63,'法術資料'!$K$2:$X$805,9,FALSE),"") | T63: =IFNA(VLOOKUP($E63,'法術資料'!$K$2:$X$805,10,FALSE),"") | U63: =IFNA(VLOOKUP($E63,'法術資料'!$K$2:$X$805,11,FALSE),"") | V63: =IFNA(VLOOKUP($E63,'法術資料'!$K$2:$W$805,12,FALSE),"")
C64: FALSE | H64: =IFNA(VLOOKUP($E64,'法術資料'!$K$2:$X$805,4,FALSE),"") | I64: =IFNA(VLOOKUP($E64,'法術資料'!$K$2:$X$805,7,FALSE),"") | L64: =IFNA(VLOOKUP($E64,'法術資料'!$K$2:$X$805,8,FALSE),"") | N64: =IFNA(VLOOKUP($E64,'法術資料'!$K$2:$X$805,14,FALSE),"") | P64: =IFNA(VLOOKUP($E64,'法術資料'!$K$2:$X$805,13,FALSE),"") | Q64: =IFNA(VLOOKUP($E64,'法術資料'!$K$2:$X$805,5,FALSE),"") | R64: =IFNA(VLOOKUP($E64,'法術資料'!$K$2:$X$805,6,FALSE),"") | S64: =IFNA(VLOOKUP($E64,'法術資料'!$K$2:$X$805,9,FALSE),"") | T64: =IFNA(VLOOKUP($E64,'法術資料'!$K$2:$X$805,10,FALSE),"") | U64: =IFNA(VLOOKUP($E64,'法術資料'!$K$2:$X$805,11,FALSE),"") | V64: =IFNA(VLOOKUP($E64,'法術資料'!$K$2:$W$805,12,FALSE),"")
C65: FALSE | H65: =IFNA(VLOOKUP($E65,'法術資料'!$K$2:$X$805,4,FALSE),"") | I65: =IFNA(VLOOKUP($E65,'法術資料'!$K$2:$X$805,7,FALSE),"") | L65: =IFNA(VLOOKUP($E65,'法術資料'!$K$2:$X$805,8,FALSE),"") | N65: =IFNA(VLOOKUP($E65,'法術資料'!$K$2:$X$805,14,FALSE),"") | P65: =IFNA(VLOOKUP($E65,'法術資料'!$K$2:$X$805,13,FALSE),"") | Q65: =IFNA(VLOOKUP($E65,'法術資料'!$K$2:$X$805,5,FALSE),"") | R65: =IFNA(VLOOKUP($E65,'法術資料'!$K$2:$X$805,6,FALSE),"") | S65: =IFNA(VLOOKUP($E65,'法術資料'!$K$2:$X$805,9,FALSE),"") | T65: =IFNA(VLOOKUP($E65,'法術資料'!$K$2:$X$805,10,FALSE),"") | U65: =IFNA(VLOOKUP($E65,'法術資料'!$K$2:$X$805,11,FALSE),"") | V65: =IFNA(VLOOKUP($E65,'法術資料'!$K$2:$W$805,12,FALSE),"")
C66: FALSE | H66: =IFNA(VLOOKUP($E66,'法術資料'!$K$2:$X$805,4,FALSE),"") | I66: =IFNA(VLOOKUP($E66,'法術資料'!$K$2:$X$805,7,FALSE),"") | L66: =IFNA(VLOOKUP($E66,'法術資料'!$K$2:$X$805,8,FALSE),"") | N66: =IFNA(VLOOKUP($E66,'法術資料'!$K$2:$X$805,14,FALSE),"") | P66: =IFNA(VLOOKUP($E66,'法術資料'!$K$2:$X$805,13,FALSE),"") | Q66: =IFNA(VLOOKUP($E66,'法術資料'!$K$2:$X$805,5,FALSE),"") | R66: =IFNA(VLOOKUP($E66,'法術資料'!$K$2:$X$805,6,FALSE),"") | S66: =IFNA(VLOOKUP($E66,'法術資料'!$K$2:$X$805,9,FALSE),"") | T66: =IFNA(VLOOKUP($E66,'法術資料'!$K$2:$X$805,10,FALSE),"") | U66: =IFNA(VLOOKUP($E66,'法術資料'!$K$2:$X$805,11,FALSE),"") | V66: =IFNA(VLOOKUP($E66,'法術資料'!$K$2:$W$805,12,FALSE),"")
C67: FALSE | H67: =IFNA(VLOOKUP($E67,'法術資料'!$K$2:$X$805,4,FALSE),"") | I67: =IFNA(VLOOKUP($E67,'法術資料'!$K$2:$X$805,7,FALSE),"") | L67: =IFNA(VLOOKUP($E67,'法術資料'!$K$2:$X$805,8,FALSE),"") | N67: =IFNA(VLOOKUP($E67,'法術資料'!$K$2:$X$805,14,FALSE),"") | P67: =IFNA(VLOOKUP($E67,'法術資料'!$K$2:$X$805,13,FALSE),"") | Q67: =IFNA(VLOOKUP($E67,'法術資料'!$K$2:$X$805,5,FALSE),"") | R67: =IFNA(VLOOKUP($E67,'法術資料'!$K$2:$X$805,6,FALSE),"") | S67: =IFNA(VLOOKUP($E67,'法術資料'!$K$2:$X$805,9,FALSE),"") | T67: =IFNA(VLOOKUP($E67,'法術資料'!$K$2:$X$805,10,FALSE),"") | U67: =IFNA(VLOOKUP($E67,'法術資料'!$K$2:$X$805,11,FALSE),"") | V67: =IFNA(VLOOKUP($E67,'法術資料'!$K$2:$W$805,12,FALSE),"")
C68: FALSE | H68: =IFNA(VLOOKUP($E68,'法術資料'!$K$2:$X$805,4,FALSE),"") | I68: =IFNA(VLOOKUP($E68,'法術資料'!$K$2:$X$805,7,FALSE),"") | L68: =IFNA(VLOOKUP($E68,'法術資料'!$K$2:$X$805,8,FALSE),"") | N68: =IFNA(VLOOKUP($E68,'法術資料'!$K$2:$X$805,14,FALSE),"") | P68: =IFNA(VLOOKUP($E68,'法術資料'!$K$2:$X$805,13,FALSE),"") | Q68: =IFNA(VLOOKUP($E68,'法術資料'!$K$2:$X$805,5,FALSE),"") | R68: =IFNA(VLOOKUP($E68,'法術資料'!$K$2:$X$805,6,FALSE),"") | S68: =IFNA(VLOOKUP($E68,'法術資料'!$K$2:$X$805,9,FALSE),"") | T68: =IFNA(VLOOKUP($E68,'法術資料'!$K$2:$X$805,10,FALSE),"") | U68: =IFNA(VLOOKUP($E68,'法術資料'!$K$2:$X$805,11,FALSE),"") | V68: =IFNA(VLOOKUP($E68,'法術資料'!$K$2:$W$805,12,FALSE),"")
C71: 四環
C72: 已準備 | D72: 來源 | E72: 法術名稱 | H72: 學派 | I72: 施法時間 | L72: 法術射程 | N72: 法術效果 | P72: 持續時間 | Q72: 專注 | R72: 儀式 | S72: 構材 | V72: 花費材料
S73: 聲音 | T73: 姿勢 | U73: 材料
C74: FALSE | H74: =IFNA(VLOOKUP($E74,'法術資料'!$K$2:$X$805,4,FALSE),"") | I74: =IFNA(VLOOKUP($E74,'法術資料'!$K$2:$X$805,7,FALSE),"") | L74: =IFNA(VLOOKUP($E74,'法術資料'!$K$2:$X$805,8,FALSE),"") | N74: =IFNA(VLOOKUP($E74,'法術資料'!$K$2:$X$805,14,FALSE),"") | P74: =IFNA(VLOOKUP($E74,'法術資料'!$K$2:$X$805,13,FALSE),"") | Q74: =IFNA(VLOOKUP($E74,'法術資料'!$K$2:$X$805,5,FALSE),"") | R74: =IFNA(VLOOKUP($E74,'法術資料'!$K$2:$X$805,6,FALSE),"") | S74: =IFNA(VLOOKUP($E74,'法術資料'!$K$2:$X$805,9,FALSE),"") | T74: =IFNA(VLOOKUP($E74,'法術資料'!$K$2:$X$805,10,FALSE),"") | U74: =IFNA(VLOOKUP($E74,'法術資料'!$K$2:$X$805,11,FALSE),"") | V74: =IFNA(VLOOKUP($E74,'法術資料'!$K$2:$W$805,12,FALSE),"")
C75: FALSE | H75: =IFNA(VLOOKUP($E75,'法術資料'!$K$2:$X$805,4,FALSE),"") | I75: =IFNA(VLOOKUP($E75,'法術資料'!$K$2:$X$805,7,FALSE),"") | L75: =IFNA(VLOOKUP($E75,'法術資料'!$K$2:$X$805,8,FALSE),"") | N75: =IFNA(VLOOKUP($E75,'法術資料'!$K$2:$X$805,14,FALSE),"") | P75: =IFNA(VLOOKUP($E75,'法術資料'!$K$2:$X$805,13,FALSE),"") | Q75: =IFNA(VLOOKUP($E75,'法術資料'!$K$2:$X$805,5,FALSE),"") | R75: =IFNA(VLOOKUP($E75,'法術資料'!$K$2:$X$805,6,FALSE),"") | S75: =IFNA(VLOOKUP($E75,'法術資料'!$K$2:$X$805,9,FALSE),"") | T75: =IFNA(VLOOKUP($E75,'法術資料'!$K$2:$X$805,10,FALSE),"") | U75: =IFNA(VLOOKUP($E75,'法術資料'!$K$2:$X$805,11,FALSE),"") | V75: =IFNA(VLOOKUP($E75,'法術資料'!$K$2:$W$805,12,FALSE),"")
C76: FALSE | H76: =IFNA(VLOOKUP($E76,'法術資料'!$K$2:$X$805,4,FALSE),"") | I76: =IFNA(VLOOKUP($E76,'法術資料'!$K$2:$X$805,7,FALSE),"") | L76: =IFNA(VLOOKUP($E76,'法術資料'!$K$2:$X$805,8,FALSE),"") | N76: =IFNA(VLOOKUP($E76,'法術資料'!$K$2:$X$805,14,FALSE),"") | P76: =IFNA(VLOOKUP($E76,'法術資料'!$K$2:$X$805,13,FALSE),"") | Q76: =IFNA(VLOOKUP($E76,'法術資料'!$K$2:$X$805,5,FALSE),"") | R76: =IFNA(VLOOKUP($E76,'法術資料'!$K$2:$X$805,6,FALSE),"") | S76: =IFNA(VLOOKUP($E76,'法術資料'!$K$2:$X$805,9,FALSE),"") | T76: =IFNA(VLOOKUP($E76,'法術資料'!$K$2:$X$805,10,FALSE),"") | U76: =IFNA(VLOOKUP($E76,'法術資料'!$K$2:$X$805,11,FALSE),"") | V76: =IFNA(VLOOKUP($E76,'法術資料'!$K$2:$W$805,12,FALSE),"")
C77: FALSE | H77: =IFNA(VLOOKUP($E77,'法術資料'!$K$2:$X$805,4,FALSE),"") | I77: =IFNA(VLOOKUP($E77,'法術資料'!$K$2:$X$805,7,FALSE),"") | L77: =IFNA(VLOOKUP($E77,'法術資料'!$K$2:$X$805,8,FALSE),"") | N77: =IFNA(VLOOKUP($E77,'法術資料'!$K$2:$X$805,14,FALSE),"") | P77: =IFNA(VLOOKUP($E77,'法術資料'!$K$2:$X$805,13,FALSE),"") | Q77: =IFNA(VLOOKUP($E77,'法術資料'!$K$2:$X$805,5,FALSE),"") | R77: =IFNA(VLOOKUP($E77,'法術資料'!$K$2:$X$805,6,FALSE),"") | S77: =IFNA(VLOOKUP($E77,'法術資料'!$K$2:$X$805,9,FALSE),"") | T77: =IFNA(VLOOKUP($E77,'法術資料'!$K$2:$X$805,10,FALSE),"") | U77: =IFNA(VLOOKUP($E77,'法術資料'!$K$2:$X$805,11,FALSE),"") | V77: =IFNA(VLOOKUP($E77,'法術資料'!$K$2:$W$805,12,FALSE),"")
C78: FALSE | H78: =IFNA(VLOOKUP($E78,'法術資料'!$K$2:$X$805,4,FALSE),"") | I78: =IFNA(VLOOKUP($E78,'法術資料'!$K$2:$X$805,7,FALSE),"") | L78: =IFNA(VLOOKUP($E78,'法術資料'!$K$2:$X$805,8,FALSE),"") | N78: =IFNA(VLOOKUP($E78,'法術資料'!$K$2:$X$805,14,FALSE),"") | P78: =IFNA(VLOOKUP($E78,'法術資料'!$K$2:$X$805,13,FALSE),"") | Q78: =IFNA(VLOOKUP($E78,'法術資料'!$K$2:$X$805,5,FALSE),"") | R78: =IFNA(VLOOKUP($E78,'法術資料'!$K$2:$X$805,6,FALSE),"") | S78: =IFNA(VLOOKUP($E78,'法術資料'!$K$2:$X$805,9,FALSE),"") | T78: =IFNA(VLOOKUP($E78,'法術資料'!$K$2:$X$805,10,FALSE),"") | U78: =IFNA(VLOOKUP($E78,'法術資料'!$K$2:$X$805,11,FALSE),"") | V78: =IFNA(VLOOKUP($E78,'法術資料'!$K$2:$W$805,12,FALSE),"")
C79: FALSE | H79: =IFNA(VLOOKUP($E79,'法術資料'!$K$2:$X$805,4,FALSE),"") | I79: =IFNA(VLOOKUP($E79,'法術資料'!$K$2:$X$805,7,FALSE),"") | L79: =IFNA(VLOOKUP($E79,'法術資料'!$K$2:$X$805,8,FALSE),"") | N79: =IFNA(VLOOKUP($E79,'法術資料'!$K$2:$X$805,14,FALSE),"") | P79: =IFNA(VLOOKUP($E79,'法術資料'!$K$2:$X$805,13,FALSE),"") | Q79: =IFNA(VLOOKUP($E79,'法術資料'!$K$2:$X$805,5,FALSE),"") | R79: =IFNA(VLOOKUP($E79,'法術資料'!$K$2:$X$805,6,FALSE),"") | S79: =IFNA(VLOOKUP($E79,'法術資料'!$K$2:$X$805,9,FALSE),"") | T79: =IFNA(VLOOKUP($E79,'法術資料'!$K$2:$X$805,10,FALSE),"") | U79: =IFNA(VLOOKUP($E79,'法術資料'!$K$2:$X$805,11,FALSE),"") | V79: =IFNA(VLOOKUP($E79,'法術資料'!$K$2:$W$805,12,FALSE),"")
C80: FALSE | H80: =IFNA(VLOOKUP($E80,'法術資料'!$K$2:$X$805,4,FALSE),"") | I80: =IFNA(VLOOKUP($E80,'法術資料'!$K$2:$X$805,7,FALSE),"") | L80: =IFNA(VLOOKUP($E80,'法術資料'!$K$2:$X$805,8,FALSE),"") | N80: =IFNA(VLOOKUP($E80,'法術資料'!$K$2:$X$805,14,FALSE),"") | P80: =IFNA(VLOOKUP($E80,'法術資料'!$K$2:$X$805,13,FALSE),"") | Q80: =IFNA(VLOOKUP($E80,'法術資料'!$K$2:$X$805,5,FALSE),"") | R80: =IFNA(VLOOKUP($E80,'法術資料'!$K$2:$X$805,6,FALSE),"") | S80: =IFNA(VLOOKUP($E80,'法術資料'!$K$2:$X$805,9,FALSE),"") | T80: =IFNA(VLOOKUP($E80,'法術資料'!$K$2:$X$805,10,FALSE),"") | U80: =IFNA(VLOOKUP($E80,'法術資料'!$K$2:$X$805,11,FALSE),"") | V80: =IFNA(VLOOKUP($E80,'法術資料'!$K$2:$W$805,12,FALSE),"")
C81: FALSE | H81: =IFNA(VLOOKUP($E81,'法術資料'!$K$2:$X$805,4,FALSE),"") | I81: =IFNA(VLOOKUP($E81,'法術資料'!$K$2:$X$805,7,FALSE),"") | L81: =IFNA(VLOOKUP($E81,'法術資料'!$K$2:$X$805,8,FALSE),"") | N81: =IFNA(VLOOKUP($E81,'法術資料'!$K$2:$X$805,14,FALSE),"") | P81: =IFNA(VLOOKUP($E81,'法術資料'!$K$2:$X$805,13,FALSE),"") | Q81: =IFNA(VLOOKUP($E81,'法術資料'!$K$2:$X$805,5,FALSE),"") | R81: =IFNA(VLOOKUP($E81,'法術資料'!$K$2:$X$805,6,FALSE),"") | S81: =IFNA(VLOOKUP($E81,'法術資料'!$K$2:$X$805,9,FALSE),"") | T81: =IFNA(VLOOKUP($E81,'法術資料'!$K$2:$X$805,10,FALSE),"") | U81: =IFNA(VLOOKUP($E81,'法術資料'!$K$2:$X$805,11,FALSE),"") | V81: =IFNA(VLOOKUP($E81,'法術資料'!$K$2:$W$805,12,FALSE),"")
C84: 五環
C85: 已準備 | D85: 來源 | E85: 法術名稱 | H85: 學派 | I85: 施法時間 | L85: 法術射程 | N85: 法術效果 | P85: 持續時間 | Q85: 專注 | R85: 儀式 | S85: 構材 | V85: 花費材料
S86: 聲音 | T86: 姿勢 | U86: 材料
C87: FALSE | H87: =IFNA(VLOOKUP($E87,'法術資料'!$K$2:$X$805,4,FALSE),"") | I87: =IFNA(VLOOKUP($E87,'法術資料'!$K$2:$X$805,7,FALSE),"") | L87: =IFNA(VLOOKUP($E87,'法術資料'!$K$2:$X$805,8,FALSE),"") | N87: =IFNA(VLOOKUP($E87,'法術資料'!$K$2:$X$805,14,FALSE),"") | P87: =IFNA(VLOOKUP($E87,'法術資料'!$K$2:$X$805,13,FALSE),"") | Q87: =IFNA(VLOOKUP($E87,'法術資料'!$K$2:$X$805,5,FALSE),"") | R87: =IFNA(VLOOKUP($E87,'法術資料'!$K$2:$X$805,6,FALSE),"") | S87: =IFNA(VLOOKUP($E87,'法術資料'!$K$2:$X$805,9,FALSE),"") | T87: =IFNA(VLOOKUP($E87,'法術資料'!$K$2:$X$805,10,FALSE),"") | U87: =IFNA(VLOOKUP($E87,'法術資料'!$K$2:$X$805,11,FALSE),"") | V87: =IFNA(VLOOKUP($E87,'法術資料'!$K$2:$W$805,12,FALSE),"")
C88: FALSE | H88: =IFNA(VLOOKUP($E88,'法術資料'!$K$2:$X$805,4,FALSE),"") | I88: =IFNA(VLOOKUP($E88,'法術資料'!$K$2:$X$805,7,FALSE),"") | L88: =IFNA(VLOOKUP($E88,'法術資料'!$K$2:$X$805,8,FALSE),"") | N88: =IFNA(VLOOKUP($E88,'法術資料'!$K$2:$X$805,14,FALSE),"") | P88: =IFNA(VLOOKUP($E88,'法術資料'!$K$2:$X$805,13,FALSE),"") | Q88: =IFNA(VLOOKUP($E88,'法術資料'!$K$2:$X$805,5,FALSE),"") | R88: =IFNA(VLOOKUP($E88,'法術資料'!$K$2:$X$805,6,FALSE),"") | S88: =IFNA(VLOOKUP($E88,'法術資料'!$K$2:$X$805,9,FALSE),"") | T88: =IFNA(VLOOKUP($E88,'法術資料'!$K$2:$X$805,10,FALSE),"") | U88: =IFNA(VLOOKUP($E88,'法術資料'!$K$2:$X$805,11,FALSE),"") | V88: =IFNA(VLOOKUP($E88,'法術資料'!$K$2:$W$805,12,FALSE),"")
C89: FALSE | H89: =IFNA(VLOOKUP($E89,'法術資料'!$K$2:$X$805,4,FALSE),"") | I89: =IFNA(VLOOKUP($E89,'法術資料'!$K$2:$X$805,7,FALSE),"") | L89: =IFNA(VLOOKUP($E89,'法術資料'!$K$2:$X$805,8,FALSE),"") | N89: =IFNA(VLOOKUP($E89,'法術資料'!$K$2:$X$805,14,FALSE),"") | P89: =IFNA(VLOOKUP($E89,'法術資料'!$K$2:$X$805,13,FALSE),"") | Q89: =IFNA(VLOOKUP($E89,'法術資料'!$K$2:$X$805,5,FALSE),"") | R89: =IFNA(VLOOKUP($E89,'法術資料'!$K$2:$X$805,6,FALSE),"") | S89: =IFNA(VLOOKUP($E89,'法術資料'!$K$2:$X$805,9,FALSE),"") | T89: =IFNA(VLOOKUP($E89,'法術資料'!$K$2:$X$805,10,FALSE),"") | U89: =IFNA(VLOOKUP($E89,'法術資料'!$K$2:$X$805,11,FALSE),"") | V89: =IFNA(VLOOKUP($E89,'法術資料'!$K$2:$W$805,12,FALSE),"")
C90: FALSE | H90: =IFNA(VLOOKUP($E90,'法術資料'!$K$2:$X$805,4,FALSE),"") | I90: =IFNA(VLOOKUP($E90,'法術資料'!$K$2:$X$805,7,FALSE),"") | L90: =IFNA(VLOOKUP($E90,'法術資料'!$K$2:$X$805,8,FALSE),"") | N90: =IFNA(VLOOKUP($E90,'法術資料'!$K$2:$X$805,14,FALSE),"") | P90: =IFNA(VLOOKUP($E90,'法術資料'!$K$2:$X$805,13,FALSE),"") | Q90: =IFNA(VLOOKUP($E90,'法術資料'!$K$2:$X$805,5,FALSE),"") | R90: =IFNA(VLOOKUP($E90,'法術資料'!$K$2:$X$805,6,FALSE),"") | S90: =IFNA(VLOOKUP($E90,'法術資料'!$K$2:$X$805,9,FALSE),"") | T90: =IFNA(VLOOKUP($E90,'法術資料'!$K$2:$X$805,10,FALSE),"") | U90: =IFNA(VLOOKUP($E90,'法術資料'!$K$2:$X$805,11,FALSE),"") | V90: =IFNA(VLOOKUP($E90,'法術資料'!$K$2:$W$805,12,FALSE),"")
C91: FALSE | H91: =IFNA(VLOOKUP($E91,'法術資料'!$K$2:$X$805,4,FALSE),"") | I91: =IFNA(VLOOKUP($E91,'法術資料'!$K$2:$X$805,7,FALSE),"") | L91: =IFNA(VLOOKUP($E91,'法術資料'!$K$2:$X$805,8,FALSE),"") | N91: =IFNA(VLOOKUP($E91,'法術資料'!$K$2:$X$805,14,FALSE),"") | P91: =IFNA(VLOOKUP($E91,'法術資料'!$K$2:$X$805,13,FALSE),"") | Q91: =IFNA(VLOOKUP($E91,'法術資料'!$K$2:$X$805,5,FALSE),"") | R91: =IFNA(VLOOKUP($E91,'法術資料'!$K$2:$X$805,6,FALSE),"") | S91: =IFNA(VLOOKUP($E91,'法術資料'!$K$2:$X$805,9,FALSE),"") | T91: =IFNA(VLOOKUP($E91,'法術資料'!$K$2:$X$805,10,FALSE),"") | U91: =IFNA(VLOOKUP($E91,'法術資料'!$K$2:$X$805,11,FALSE),"") | V91: =IFNA(VLOOKUP($E91,'法術資料'!$K$2:$W$805,12,FALSE),"")
C92: FALSE | H92: =IFNA(VLOOKUP($E92,'法術資料'!$K$2:$X$805,4,FALSE),"") | I92: =IFNA(VLOOKUP($E92,'法術資料'!$K$2:$X$805,7,FALSE),"") | L92: =IFNA(VLOOKUP($E92,'法術資料'!$K$2:$X$805,8,FALSE),"") | N92: =IFNA(VLOOKUP($E92,'法術資料'!$K$2:$X$805,14,FALSE),"") | P92: =IFNA(VLOOKUP($E92,'法術資料'!$K$2:$X$805,13,FALSE),"") | Q92: =IFNA(VLOOKUP($E92,'法術資料'!$K$2:$X$805,5,FALSE),"") | R92: =IFNA(VLOOKUP($E92,'法術資料'!$K$2:$X$805,6,FALSE),"") | S92: =IFNA(VLOOKUP($E92,'法術資料'!$K$2:$X$805,9,FALSE),"") | T92: =IFNA(VLOOKUP($E92,'法術資料'!$K$2:$X$805,10,FALSE),"") | U92: =IFNA(VLOOKUP($E92,'法術資料'!$K$2:$X$805,11,FALSE),"") | V92: =IFNA(VLOOKUP($E92,'法術資料'!$K$2:$W$805,12,FALSE),"")
C93: FALSE | H93: =IFNA(VLOOKUP($E93,'法術資料'!$K$2:$X$805,4,FALSE),"") | I93: =IFNA(VLOOKUP($E93,'法術資料'!$K$2:$X$805,7,FALSE),"") | L93: =IFNA(VLOOKUP($E93,'法術資料'!$K$2:$X$805,8,FALSE),"") | N93: =IFNA(VLOOKUP($E93,'法術資料'!$K$2:$X$805,14,FALSE),"") | P93: =IFNA(VLOOKUP($E93,'法術資料'!$K$2:$X$805,13,FALSE),"") | Q93: =IFNA(VLOOKUP($E93,'法術資料'!$K$2:$X$805,5,FALSE),"") | R93: =IFNA(VLOOKUP($E93,'法術資料'!$K$2:$X$805,6,FALSE),"") | S93: =IFNA(VLOOKUP($E93,'法術資料'!$K$2:$X$805,9,FALSE),"") | T93: =IFNA(VLOOKUP($E93,'法術資料'!$K$2:$X$805,10,FALSE),"") | U93: =IFNA(VLOOKUP($E93,'法術資料'!$K$2:$X$805,11,FALSE),"") | V93: =IFNA(VLOOKUP($E93,'法術資料'!$K$2:$W$805,12,FALSE),"")
C94: FALSE | H94: =IFNA(VLOOKUP($E94,'法術資料'!$K$2:$X$805,4,FALSE),"") | I94: =IFNA(VLOOKUP($E94,'法術資料'!$K$2:$X$805,7,FALSE),"") | L94: =IFNA(VLOOKUP($E94,'法術資料'!$K$2:$X$805,8,FALSE),"") | N94: =IFNA(VLOOKUP($E94,'法術資料'!$K$2:$X$805,14,FALSE),"") | P94: =IFNA(VLOOKUP($E94,'法術資料'!$K$2:$X$805,13,FALSE),"") | Q94: =IFNA(VLOOKUP($E94,'法術資料'!$K$2:$X$805,5,FALSE),"") | R94: =IFNA(VLOOKUP($E94,'法術資料'!$K$2:$X$805,6,FALSE),"") | S94: =IFNA(VLOOKUP($E94,'法術資料'!$K$2:$X$805,9,FALSE),"") | T94: =IFNA(VLOOKUP($E94,'法術資料'!$K$2:$X$805,10,FALSE),"") | U94: =IFNA(VLOOKUP($E94,'法術資料'!$K$2:$X$805,11,FALSE),"") | V94: =IFNA(VLOOKUP($E94,'法術資料'!$K$2:$W$805,12,FALSE),"")
C97: 六環
C98: 已準備 | D98: 來源 | E98: 法術名稱 | H98: 學派 | I98: 施法時間 | L98: 法術射程 | N98: 法術效果 | P98: 持續時間 | Q98: 專注 | R98: 儀式 | S98: 構材 | V98: 花費材料
S99: 聲音 | T99: 姿勢 | U99: 材料
C100: FALSE | H100: =IFNA(VLOOKUP($E100,'法術資料'!$K$2:$X$805,4,FALSE),"") | I100: =IFNA(VLOOKUP($E100,'法術資料'!$K$2:$X$805,7,FALSE),"") | L100: =IFNA(VLOOKUP($E100,'法術資料'!$K$2:$X$805,8,FALSE),"") | N100: =IFNA(VLOOKUP($E100,'法術資料'!$K$2:$X$805,14,FALSE),"") | P100: =IFNA(VLOOKUP($E100,'法術資料'!$K$2:$X$805,13,FALSE),"") | Q100: =IFNA(VLOOKUP($E100,'法術資料'!$K$2:$X$805,5,FALSE),"") | R100: =IFNA(VLOOKUP($E100,'法術資料'!$K$2:$X$805,6,FALSE),"") | S100: =IFNA(VLOOKUP($E100,'法術資料'!$K$2:$X$805,9,FALSE),"") | T100: =IFNA(VLOOKUP($E100,'法術資料'!$K$2:$X$805,10,FALSE),"") | U100: =IFNA(VLOOKUP($E100,'法術資料'!$K$2:$X$805,11,FALSE),"") | V100: =IFNA(VLOOKUP($E100,'法術資料'!$K$2:$W$805,12,FALSE),"")
C101: FALSE | H101: =IFNA(VLOOKUP($E101,'法術資料'!$K$2:$X$805,4,FALSE),"") | I101: =IFNA(VLOOKUP($E101,'法術資料'!$K$2:$X$805,7,FALSE),"") | L101: =IFNA(VLOOKUP($E101,'法術資料'!$K$2:$X$805,8,FALSE),"") | N101: =IFNA(VLOOKUP($E101,'法術資料'!$K$2:$X$805,14,FALSE),"") | P101: =IFNA(VLOOKUP($E101,'法術資料'!$K$2:$X$805,13,FALSE),"") | Q101: =IFNA(VLOOKUP($E101,'法術資料'!$K$2:$X$805,5,FALSE),"") | R101: =IFNA(VLOOKUP($E101,'法術資料'!$K$2:$X$805,6,FALSE),"") | S101: =IFNA(VLOOKUP($E101,'法術資料'!$K$2:$X$805,9,FALSE),"") | T101: =IFNA(VLOOKUP($E101,'法術資料'!$K$2:$X$805,10,FALSE),"") | U101: =IFNA(VLOOKUP($E101,'法術資料'!$K$2:$X$805,11,FALSE),"") | V101: =IFNA(VLOOKUP($E101,'法術資料'!$K$2:$W$805,12,FALSE),"")
C102: FALSE | H102: =IFNA(VLOOKUP($E102,'法術資料'!$K$2:$X$805,4,FALSE),"") | I102: =IFNA(VLOOKUP($E102,'法術資料'!$K$2:$X$805,7,FALSE),"") | L102: =IFNA(VLOOKUP($E102,'法術資料'!$K$2:$X$805,8,FALSE),"") | N102: =IFNA(VLOOKUP($E102,'法術資料'!$K$2:$X$805,14,FALSE),"") | P102: =IFNA(VLOOKUP($E102,'法術資料'!$K$2:$X$805,13,FALSE),"") | Q102: =IFNA(VLOOKUP($E102,'法術資料'!$K$2:$X$805,5,FALSE),"") | R102: =IFNA(VLOOKUP($E102,'法術資料'!$K$2:$X$805,6,FALSE),"") | S102: =IFNA(VLOOKUP($E102,'法術資料'!$K$2:$X$805,9,FALSE),"") | T102: =IFNA(VLOOKUP($E102,'法術資料'!$K$2:$X$805,10,FALSE),"") | U102: =IFNA(VLOOKUP($E102,'法術資料'!$K$2:$X$805,11,FALSE),"") | V102: =IFNA(VLOOKUP($E102,'法術資料'!$K$2:$W$805,12,FALSE),"")
C103: FALSE | H103: =IFNA(VLOOKUP($E103,'法術資料'!$K$2:$X$805,4,FALSE),"") | I103: =IFNA(VLOOKUP($E103,'法術資料'!$K$2:$X$805,7,FALSE),"") | L103: =IFNA(VLOOKUP($E103,'法術資料'!$K$2:$X$805,8,FALSE),"") | N103: =IFNA(VLOOKUP($E103,'法術資料'!$K$2:$X$805,14,FALSE),"") | P103: =IFNA(VLOOKUP($E103,'法術資料'!$K$2:$X$805,13,FALSE),"") | Q103: =IFNA(VLOOKUP($E103,'法術資料'!$K$2:$X$805,5,FALSE),"") | R103: =IFNA(VLOOKUP($E103,'法術資料'!$K$2:$X$805,6,FALSE),"") | S103: =IFNA(VLOOKUP($E103,'法術資料'!$K$2:$X$805,9,FALSE),"") | T103: =IFNA(VLOOKUP($E103,'法術資料'!$K$2:$X$805,10,FALSE),"") | U103: =IFNA(VLOOKUP($E103,'法術資料'!$K$2:$X$805,11,FALSE),"") | V103: =IFNA(VLOOKUP($E103,'法術資料'!$K$2:$W$805,12,FALSE),"")
C104: FALSE | H104: =IFNA(VLOOKUP($E104,'法術資料'!$K$2:$X$805,4,FALSE),"") | I104: =IFNA(VLOOKUP($E104,'法術資料'!$K$2:$X$805,7,FALSE),"") | L104: =IFNA(VLOOKUP($E104,'法術資料'!$K$2:$X$805,8,FALSE),"") | N104: =IFNA(VLOOKUP($E104,'法術資料'!$K$2:$X$805,14,FALSE),"") | P104: =IFNA(VLOOKUP($E104,'法術資料'!$K$2:$X$805,13,FALSE),"") | Q104: =IFNA(VLOOKUP($E104,'法術資料'!$K$2:$X$805,5,FALSE),"") | R104: =IFNA(VLOOKUP($E104,'法術資料'!$K$2:$X$805,6,FALSE),"") | S104: =IFNA(VLOOKUP($E104,'法術資料'!$K$2:$X$805,9,FALSE),"") | T104: =IFNA(VLOOKUP($E104,'法術資料'!$K$2:$X$805,10,FALSE),"") | U104: =IFNA(VLOOKUP($E104,'法術資料'!$K$2:$X$805,11,FALSE),"") | V104: =IFNA(VLOOKUP($E104,'法術資料'!$K$2:$W$805,12,FALSE),"")
C105: FALSE | H105: =IFNA(VLOOKUP($E105,'法術資料'!$K$2:$X$805,4,FALSE),"") | I105: =IFNA(VLOOKUP($E105,'法術資料'!$K$2:$X$805,7,FALSE),"") | L105: =IFNA(VLOOKUP($E105,'法術資料'!$K$2:$X$805,8,FALSE),"") | N105: =IFNA(VLOOKUP($E105,'法術資料'!$K$2:$X$805,14,FALSE),"") | P105: =IFNA(VLOOKUP($E105,'法術資料'!$K$2:$X$805,13,FALSE),"") | Q105: =IFNA(VLOOKUP($E105,'法術資料'!$K$2:$X$805,5,FALSE),"") | R105: =IFNA(VLOOKUP($E105,'法術資料'!$K$2:$X$805,6,FALSE),"") | S105: =IFNA(VLOOKUP($E105,'法術資料'!$K$2:$X$805,9,FALSE),"") | T105: =IFNA(VLOOKUP($E105,'法術資料'!$K$2:$X$805,10,FALSE),"") | U105: =IFNA(VLOOKUP($E105,'法術資料'!$K$2:$X$805,11,FALSE),"") | V105: =IFNA(VLOOKUP($E105,'法術資料'!$K$2:$W$805,12,FALSE),"")
C108: 七環
C109: 已準備 | D109: 來源 | E109: 法術名稱 | H109: 學派 | I109: 施法時間 | L109: 法術射程 | N109: 法術效果 | P109: 持續時間 | Q109: 專注 | R109: 儀式 | S109: 構材 | V109: 花費材料
S110: 聲音 | T110: 姿勢 | U110: 材料
C111: FALSE | H111: =IFNA(VLOOKUP($E111,'法術資料'!$K$2:$X$805,4,FALSE),"") | I111: =IFNA(VLOOKUP($E111,'法術資料'!$K$2:$X$805,7,FALSE),"") | L111: =IFNA(VLOOKUP($E111,'法術資料'!$K$2:$X$805,8,FALSE),"") | N111: =IFNA(VLOOKUP($E111,'法術資料'!$K$2:$X$805,14,FALSE),"") | P111: =IFNA(VLOOKUP($E111,'法術資料'!$K$2:$X$805,13,FALSE),"") | Q111: =IFNA(VLOOKUP($E111,'法術資料'!$K$2:$X$805,5,FALSE),"") | R111: =IFNA(VLOOKUP($E111,'法術資料'!$K$2:$X$805,6,FALSE),"") | S111: =IFNA(VLOOKUP($E111,'法術資料'!$K$2:$X$805,9,FALSE),"") | T111: =IFNA(VLOOKUP($E111,'法術資料'!$K$2:$X$805,10,FALSE),"") | U111: =IFNA(VLOOKUP($E111,'法術資料'!$K$2:$X$805,11,FALSE),"") | V111: =IFNA(VLOOKUP($E111,'法術資料'!$K$2:$W$805,12,FALSE),"")
C112: FALSE | H112: =IFNA(VLOOKUP($E112,'法術資料'!$K$2:$X$805,4,FALSE),"") | I112: =IFNA(VLOOKUP($E112,'法術資料'!$K$2:$X$805,7,FALSE),"") | L112: =IFNA(VLOOKUP($E112,'法術資料'!$K$2:$X$805,8,FALSE),"") | N112: =IFNA(VLOOKUP($E112,'法術資料'!$K$2:$X$805,14,FALSE),"") | P112: =IFNA(VLOOKUP($E112,'法術資料'!$K$2:$X$805,13,FALSE),"") | Q112: =IFNA(VLOOKUP($E112,'法術資料'!$K$2:$X$805,5,FALSE),"") | R112: =IFNA(VLOOKUP($E112,'法術資料'!$K$2:$X$805,6,FALSE),"") | S112: =IFNA(VLOOKUP($E112,'法術資料'!$K$2:$X$805,9,FALSE),"") | T112: =IFNA(VLOOKUP($E112,'法術資料'!$K$2:$X$805,10,FALSE),"") | U112: =IFNA(VLOOKUP($E112,'法術資料'!$K$2:$X$805,11,FALSE),"") | V112: =IFNA(VLOOKUP($E112,'法術資料'!$K$2:$W$805,12,FALSE),"")
C113: FALSE | H113: =IFNA(VLOOKUP($E113,'法術資料'!$K$2:$X$805,4,FALSE),"") | I113: =IFNA(VLOOKUP($E113,'法術資料'!$K$2:$X$805,7,FALSE),"") | L113: =IFNA(VLOOKUP($E113,'法術資料'!$K$2:$X$805,8,FALSE),"") | N113: =IFNA(VLOOKUP($E113,'法術資料'!$K$2:$X$805,14,FALSE),"") | P113: =IFNA(VLOOKUP($E113,'法術資料'!$K$2:$X$805,13,FALSE),"") | Q113: =IFNA(VLOOKUP($E113,'法術資料'!$K$2:$X$805,5,FALSE),"") | R113: =IFNA(VLOOKUP($E113,'法術資料'!$K$2:$X$805,6,FALSE),"") | S113: =IFNA(VLOOKUP($E113,'法術資料'!$K$2:$X$805,9,FALSE),"") | T113: =IFNA(VLOOKUP($E113,'法術資料'!$K$2:$X$805,10,FALSE),"") | U113: =IFNA(VLOOKUP($E113,'法術資料'!$K$2:$X$805,11,FALSE),"") | V113: =IFNA(VLOOKUP($E113,'法術資料'!$K$2:$W$805,12,FALSE),"")
C114: FALSE | H114: =IFNA(VLOOKUP($E114,'法術資料'!$K$2:$X$805,4,FALSE),"") | I114: =IFNA(VLOOKUP($E114,'法術資料'!$K$2:$X$805,7,FALSE),"") | L114: =IFNA(VLOOKUP($E114,'法術資料'!$K$2:$X$805,8,FALSE),"") | N114: =IFNA(VLOOKUP($E114,'法術資料'!$K$2:$X$805,14,FALSE),"") | P114: =IFNA(VLOOKUP($E114,'法術資料'!$K$2:$X$805,13,FALSE),"") | Q114: =IFNA(VLOOKUP($E114,'法術資料'!$K$2:$X$805,5,FALSE),"") | R114: =IFNA(VLOOKUP($E114,'法術資料'!$K$2:$X$805,6,FALSE),"") | S114: =IFNA(VLOOKUP($E114,'法術資料'!$K$2:$X$805,9,FALSE),"") | T114: =IFNA(VLOOKUP($E114,'法術資料'!$K$2:$X$805,10,FALSE),"") | U114: =IFNA(VLOOKUP($E114,'法術資料'!$K$2:$X$805,11,FALSE),"") | V114: =IFNA(VLOOKUP($E114,'法術資料'!$K$2:$W$805,12,FALSE),"")
C115: FALSE | H115: =IFNA(VLOOKUP($E115,'法術資料'!$K$2:$X$805,4,FALSE),"") | I115: =IFNA(VLOOKUP($E115,'法術資料'!$K$2:$X$805,7,FALSE),"") | L115: =IFNA(VLOOKUP($E115,'法術資料'!$K$2:$X$805,8,FALSE),"") | N115: =IFNA(VLOOKUP($E115,'法術資料'!$K$2:$X$805,14,FALSE),"") | P115: =IFNA(VLOOKUP($E115,'法術資料'!$K$2:$X$805,13,FALSE),"") | Q115: =IFNA(VLOOKUP($E115,'法術資料'!$K$2:$X$805,5,FALSE),"") | R115: =IFNA(VLOOKUP($E115,'法術資料'!$K$2:$X$805,6,FALSE),"") | S115: =IFNA(VLOOKUP($E115,'法術資料'!$K$2:$X$805,9,FALSE),"") | T115: =IFNA(VLOOKUP($E115,'法術資料'!$K$2:$X$805,10,FALSE),"") | U115: =IFNA(VLOOKUP($E115,'法術資料'!$K$2:$X$805,11,FALSE),"") | V115: =IFNA(VLOOKUP($E115,'法術資料'!$K$2:$W$805,12,FALSE),"")
C116: FALSE | H116: =IFNA(VLOOKUP($E116,'法術資料'!$K$2:$X$805,4,FALSE),"") | I116: =IFNA(VLOOKUP($E116,'法術資料'!$K$2:$X$805,7,FALSE),"") | L116: =IFNA(VLOOKUP($E116,'法術資料'!$K$2:$X$805,8,FALSE),"") | N116: =IFNA(VLOOKUP($E116,'法術資料'!$K$2:$X$805,14,FALSE),"") | P116: =IFNA(VLOOKUP($E116,'法術資料'!$K$2:$X$805,13,FALSE),"") | Q116: =IFNA(VLOOKUP($E116,'法術資料'!$K$2:$X$805,5,FALSE),"") | R116: =IFNA(VLOOKUP($E116,'法術資料'!$K$2:$X$805,6,FALSE),"") | S116: =IFNA(VLOOKUP($E116,'法術資料'!$K$2:$X$805,9,FALSE),"") | T116: =IFNA(VLOOKUP($E116,'法術資料'!$K$2:$X$805,10,FALSE),"") | U116: =IFNA(VLOOKUP($E116,'法術資料'!$K$2:$X$805,11,FALSE),"") | V116: =IFNA(VLOOKUP($E116,'法術資料'!$K$2:$W$805,12,FALSE),"")
C119: 八環
C120: 已準備 | D120: 來源 | E120: 法術名稱 | H120: 學派 | I120: 施法時間 | L120: 法術射程 | N120: 法術效果 | P120: 持續時間 | Q120: 專注 | R120: 儀式 | S120: 構材 | V120: 花費材料
S121: 聲音 | T121: 姿勢 | U121: 材料
...

Sheet 法術篩選
A1: 0環 | B1: 1環 | C1: 2環 | D1: 3環 | E1: 4環 | F1: 5環 | G1: 6環 | H1: 7環 | I1: 8環 | J1: 9環
A2: 酸液濺爆 | B2: 警報術 | C2: 援助術 | D2: 活化死屍 | E2: 秘法眼 | F2: 活化物體 | G2: 秘法之門 | H2: 召喚天界之力 | I2: 動物化形 | J2: 星界投影
A3: 劍刃防護 | B3: 化獸為友 | C3: 變造自身 | D3: 活力靈光 | E3: 生命靈光 | F3: 反活物護罩 | G3: 劍刃障壁 | H3: 延遲爆裂火球 | I3: 反魔法結界 | J3: 預視術
A4: 寒顫之觸 | B4: 艾嘉西斯之鎧 | C4: 秘法鎖 | D4: 希望信標 | E4: 淨化靈光 | F4: 啟蒙術 | G4: 連環閃電 | H4: 聖言術 | I4: 嫌惡/共感術 | J4: 異界之門
A5: 舞光術 | B5: 哈達之臂 | C5: 動物信使 | D5: 降咒 | E5: 放逐術 | F5: 放逐斬 | G5: 死亡之環 | H5: 跨入乙太界 | I5: 摧毀心智 | J5: 禁錮術
A6: ​德魯伊伎倆 | B6: 災禍術 | C6: 秘法活力 | D6: 致盲斬 | E6: 枯萎術 | F6: 畢格比之掌 | G6: 召喚精類之力 | H6: 死亡一指 | I6: 克隆術 | J6: 群體治癒術
A7: 魔能爆 | B7: 祝福術 | C7: 卜筮 | D7: 閃現術 | E7: 魅惑怪物 | F7: 威能法環 | G7: 觸發術 | H7: 火焰風暴 | I7: 操控天氣 | J7: 流星爆
